Workbook

Sheet Best scenario
A1: EMILY'S RETIREMENT MODEL
G2: 0.4
A3: Parameter | G3: 0.3
A4: current salary: | B4: 70000 | C4: (rand) | D4: =RAND() -> 0.58933928 | G4: 0.3
A5: average growth rate/ yearly （ μ）： | B5: 0.035
A6: Standard variation（σ）： | B6: 0.007
A7: Estimated growth rate(norm) | B7: =_xlfn.NORM.INV(D4,B5,B6) -> 0.03658092
A8: Estimated salary | B8: =B4*(1+B7) -> 72560.664
A9: Contribution rate from Emily | B9: 0.1 | C9: 0.03 | D9: 0.06 | E9: 0.1
A10: superannuation rate from company | B10: 0.021 | C10: Deduct ESCT tax ($57,601 – $84,000) | D10: ESCT tax (> $84,000) | E10: Contribute based on pre-tax salary.
A11: KiwiSaver revenue tax(before retirement) | B11: 0.28
A12: KiwiSaver revenue tax(after retirement) | C12: NZ Super+bank intrest+fund revenue
A13: NZ Super(every 2 weeks) | B13: 1076.84
A14: NZ Super tax rate
A15: superannuation compensation from goverment | B15: =IF(B8*B9>C16,D16,B8*B9*50%) -> 521.43 | C15: Min personal contribute | D15: Max Member Tax Credit
C16: 1042.86 | D16: 521.43
A17: Annual Bank Savings | B17: =C18*(1+D18) -> 5581.242 | C17: Money saved per year | D17: Rate
C18: 5364 | D18: 0.0405
A19: Decision Variables | B19: Current allocation | C19: Annual Growth Rate | D19: Volatility （SD）
A20: Harbor safe | B20: 0.1 | C20: 0.0375 | D20: 0.05
A21: Horizon | B21: 0.25 | C21: 0.065 | D21: 0.105
A22: Skyhigh | B22: 0.65 | C22: 0.1025 | D22: 0.2075
A23: Total | B23: =SUM(B20:B22) -> 1
A24: Retirement age | B24: 65 | C24: 60 | D24: 63 | E24: 65 | F24: 0.03
B25: NORM.INV(D4,B5,B6) | C25: C19*(1+B20) | D25: IF(C10<84000,3%*(1-C13),3%*(1-D13)) | E25: IF(B8*B9>C13,D13,B8*B9*50%) | F25: C20*(B11+D20)+B14
A26: Year old（30-65 years old） | B26: Salary growth rate | C26: estimated salary | D26: superannuation rate from company | E26: superannuation compensation from gov | F26: Annual superannuation | G26: Harbor safe growth rate | H26: Harborsafe Profit | I26: Harborsafe balance | J26: Horizon growth rate | K26: Horizon Profit | L26: Horizon balance | M26: Skyhigh growth rate | N26: Skyhigh revenue | O26: Skyhigh balance | P26: Total balance (pre tax) | Q26: Amount needs taxed | R26: Kiwisaver TAX | S26: NZ super | T26: Total Balance( after tax)
A27: 30 | B27: =_xlfn.NORM.INV(RAND(),$B$5,$B$6) -> 0.041523488 | C27: 70000 | D27: =IF(C27<84000,3%*(1-30%),3%*(1-33%)) -> 0.021 | E27: =$B$15 -> 521.43 | F27: =C27*($B$9+D27)+E27 -> 8991.43 | G27: =_xlfn.NORM.INV(RAND(),$C$20,$D$20) -> 0.034948841 | H27: =(F27*$B$20)*G27 -> 31.424006 | I27: =F27*B20*(1+G27) -> 930.56701 | J27: =_xlfn.NORM.INV(RAND(),$C$21,$D$21) -> 0.14736308 | K27: =F27*$B$21*J27 -> 331.2512 | L27: =F27*B21*(1+J27) -> 2579.1087 | M27: =_xlfn.NORM.INV(RAND(),$C$22,$D$22) -> 0.081547597 | N27: =F27*$B$22*M27 -> 476.59918 | O27: =F27*B22*(1+M27) -> 6321.0287 | P27: =I27+L27+O27 -> 9830.7044 | Q27: =H27+K27+N27 -> 839.27439 | R27: =IF(Q27>0,Q27*$B$11,0) -> 234.99683 | S27: =26*$B$13 -> 27997.84 | T27: =P27-R27+S27 -> 37593.548
A28: 31 | B28: =_xlfn.NORM.INV(RAND(),$B$5,$B$6) -> 0.037047358 | C28: =C27*(1+B28) -> 72593.315 | D28: =IF(C28<84000,3%*(1-30%),3%*(1-33%)) -> 0.021 | E28: =$B$15 -> 521.43 | F28: =C28*($B$9+D28)+E28 -> 9305.2211 | G28: =_xlfn.NORM.INV(RAND(),$C$20,$D$20) -> 0.098225349 | H28: =(I27+F28*$B$20)*G28 -> 182.80613 | I28: =(I27+(F28*$B$20))*(1+G28) -> 2043.8952 | J28: =_xlfn.NORM.INV(RAND(),$C$21,$D$21) -> 0.11796912 | K28: =(L27+F28*$B$21)*J28 -> 578.68738 | L28: =(L27+F28*$B$21)*(1+J28) -> 5484.1014 | M28: =_xlfn.NORM.INV(RAND(),$C$22,$D$22) -> 0.023442358 | N28: =(O27+F28*$B$22)*M28 -> 289.96843 | O28: =(O27+F28*$B$22)*(1+M28) -> 12659.391 | P28: =I28+L28+O28 -> 20187.387 | Q28: =H28+K28+N28 -> 1051.4619 | R28: =IF(Q28>0,Q28*$B$11,0) -> 294.40934 | S28: =26*$B$13 -> 27997.84 | T28: =P28-R28+S28 -> 47890.818
A29: 32 | B29: =_xlfn.NORM.INV(RAND(),$B$5,$B$6) -> 0.040017106 | C29: 70001 | D29: =IF(C29<84000,3%*(1-30%),3%*(1-33%)) -> 0.021 | E29: =$B$15 -> 521.43 | F29: =C29*($B$9+D29)+E29 -> 8991.551 | G29: =_xlfn.NORM.INV(RAND(),$C$20,$D$20) -> -0.033884684 | H29: =(I28+F29*$B$20)*G29 -> -99.724331 | I29: =(I28+(F29*$B$20))*(1+G29) -> 2843.326 | J29: =_xlfn.NORM.INV(RAND(),$C$21,$D$21) -> 0.18659343 | K29: =(L28+F29*$B$21)*J29 -> 1442.7383 | L29: =(L28+F29*$B$21)*(1+J29) -> 9174.7275 | M29: =_xlfn.NORM.INV(RAND(),$C$22,$D$22) -> 0.047880189 | N29: =(O28+F29*$B$22)*M29 -> 885.97018 | O29: =(O28+F29*$B$22)*(1+M29) -> 19389.869 | P29: =I29+L29+O29 -> 31407.923 | Q29: =H29+K29+N29 -> 2228.9842 | R29: =IF(Q29>0,Q29*$B$11,0) -> 624.11557 | S29: =26*$B$13 -> 27997.84 | T29: =P29-R29+S29 -> 58781.647
A30: 33 | B30: =_xlfn.NORM.INV(RAND(),$B$5,$B$6) -> 0.030119556 | C30: =C29*(1+B30) -> 72109.399 | D30: =IF(C30<84000,3%*(1-30%),3%*(1-33%)) -> 0.021 | E30: =$B$15 -> 521.43 | F30: =C30*($B$9+D30)+E30 -> 9246.6673 | G30: =_xlfn.NORM.INV(RAND(),$C$20,$D$20) -> 0.080808884 | H30: =(I29+F30*$B$20)*G30 -> 304.48729 | I30: =(I29+(F30*$B$20))*(1+G30) -> 4072.48 | J30: =_xlfn.NORM.INV(RAND(),$C$21,$D$21) -> 0.16054056 | K30: =(L29+F30*$B$21)*J30 -> 1844.0321 | L30: =(L29+F30*$B$21)*(1+J30) -> 13330.426 | M30: =_xlfn.NORM.INV(RAND(),$C$22,$D$22) -> 0.017246443 | N30: =(O29+F30*$B$22)*M30 -> 438.06316 | O30: =(O29+F30*$B$22)*(1+M30) -> 25838.266 | P30: =I30+L30+O30 -> 43241.172 | Q30: =H30+K30+N30 -> 2586.5826 | R30: =IF(Q30>0,Q30*$B$11,0) -> 724.24312 | S30: =26*$B$13 -> 27997.84 | T30: =P30-R30+S30 -> 70514.769
A31: 34 | B31: =_xlfn.NORM.INV(RAND(),$B$5,$B$6) -> 0.039398914 | C31: =C30*(1+B31) -> 74950.431 | D31: =IF(C31<84000,3%*(1-30%),3%*(1-33%)) -> 0.021 | E31: =$B$15 -> 521.43 | F31: =C31*($B$9+D31)+E31 -> 9590.4322 | G31: =_xlfn.NORM.INV(RAND(),$C$20,$D$20) -> 0.022212206 | H31: =(I30+F31*$B$20)*G31 -> 111.76123 | I31: =(I30+(F31*$B$20))*(1+G31) -> 5143.2845 | J31: =_xlfn.NORM.INV(RAND(),$C$21,$D$21) -> -0.11575324 | K31: =(L30+F31*$B$21)*J31 -> -1820.5709 | L31: =(L30+F31*$B$21)*(1+J31) -> 13907.464 | M31: =_xlfn.NORM.INV(RAND(),$C$22,$D$22) -> 0.35493223 | N31: =(O30+F31*$B$22)*M31 -> 11383.403 | O31: =(O30+F31*$B$22)*(1+M31) -> 43455.45 | P31: =I31+L31+O31 -> 62506.198 | Q31: =H31+K31+N31 -> 9674.5933 | R31: =IF(Q31>0,Q31*$B$11,0) -> 2708.8861 | S31: =26*$B$13 -> 27997.84 | T31: =P31-R31+S31 -> 87795.152
A32: 35 | B32: =_xlfn.NORM.INV(RAND(),$B$5,$B$6) -> 0.035129141 | C32: =C31*(1+B32) -> 77583.375 | D32: =IF(C32<84000,3%*(1-30%),3%*(1-33%)) -> 0.021 | E32: =$B$15 -> 521.43 | F32: =C32*($B$9+D32)+E32 -> 9909.0184 | G32: =_xlfn.NORM.INV(RAND(),$C$20,$D$20) -> 0.10321141 | H32: =(I31+F32*$B$20)*G32 -> 633.11802 | I32: =(I31+(F32*$B$20))*(1+G32) -> 6767.3043 | J32: =_xlfn.NORM.INV(RAND(),$C$21,$D$21) -> 0.063301326 | K32: =(L31+F32*$B$21)*J32 -> 1037.1744 | L32: =(L31+F32*$B$21)*(1+J32) -> 17421.893 | M32: =_xlfn.NORM.INV(RAND(),$C$22,$D$22) -> 0.21233462 | N32: =(O31+F32*$B$22)*M32 -> 10594.714 | O32: =(O31+F32*$B$22)*(1+M32) -> 60491.026 | P32: =I32+L32+O32 -> 84680.223 | Q32: =H32+K32+N32 -> 12265.007 | R32: =IF(Q32>0,Q32*$B$11,0) -> 3434.2019 | S32: =26*$B$13 -> 27997.84 | T32: =P32-R32+S32 -> 109243.86
A33: 36 | B33: =_xlfn.NORM.INV(RAND(),$B$5,$B$6) -> 0.027665954 | C33: =C32*(1+B33) -> 79729.793 | D33: =IF(C33<84000,3%*(1-30%),3%*(1-33%)) -> 0.021 | E33: =$B$15 -> 521.43 | F33: =C33*($B$9+D33)+E33 -> 10168.735 | G33: =_xlfn.NORM.INV(RAND(),$C$20,$D$20) -> 0.015140994 | H33: =(I32+F33*$B$20)*G33 -> 117.86019 | I33: =(I32+(F33*$B$20))*(1+G33) -> 7902.038 | J33: =_xlfn.NORM.INV(RAND(),$C$21,$D$21) -> 0.0618178 | K33: =(L32+F33*$B$21)*J33 -> 1234.1353 | L33: =(L32+F33*$B$21)*(1+J33) -> 21198.212 | M33: =_xlfn.NORM.INV(RAND(),$C$22,$D$22) -> -0.41795848 | N33: =(O32+F33*$B$22)*M33 -> -28045.308 | O33: =(O32+F33*$B$22)*(1+M33) -> 39055.396 | P33: =I33+L33+O33 -> 68155.646 | Q33: =H33+K33+N33 -> -26693.313 | R33: =IF(Q33>0,Q33*$B$11,0) -> 0 | S33: =26*$B$13 -> 27997.84 | T33: =P33-R33+S33 -> 96153.486
A34: 37 | B34: =_xlfn.NORM.INV(RAND(),$B$5,$B$6) -> 0.040716011 | C34: =C33*(1+B34) -> 82976.073 | D34: =IF(C34<84000,3%*(1-30%),3%*(1-33%)) -> 0.021 | E34: =$B$15 -> 521.43 | F34: =C34*($B$9+D34)+E34 -> 10561.535 | G34: =_xlfn.NORM.INV(RAND(),$C$20,$D$20) -> -0.055309184 | H34: =(I33+F34*$B$20)*G34 -> -495.47026 | I34: =(I33+(F34*$B$20))*(1+G34) -> 8462.7212 | J34: =_xlfn.NORM.INV(RAND(),$C$21,$D$21) -> -0.072838043 | K34: =(L33+F34*$B$21)*J34 -> -1736.3566 | L34: =(L33+F34*$B$21)*(1+J34) -> 22102.239 | M34: =_xlfn.NORM.INV(RAND(),$C$22,$D$22) -> -0.15785879 | N34: =(O33+F34*$B$22)*M34 -> -7248.9378 | O34: =(O33+F34*$B$22)*(1+M34) -> 38671.456 | P34: =I34+L34+O34 -> 69236.416 | Q34: =H34+K34+N34 -> -9480.7647 | R34: =IF(Q34>0,Q34*$B$11,0) -> 0 | S34: =26*$B$13 -> 27997.84 | T34: =P34-R34+S34 -> 97234.256
A35: 38 | B35: =_xlfn.NORM.INV(RAND(),$B$5,$B$6) -> 0.029252459 | C35: =C34*(1+B35) -> 85403.327 | D35: =IF(C35<84000,3%*(1-30%),3%*(1-33%)) -> 0.0201 | E35: =$B$15 -> 521.43 | F35: =C35*($B$9+D35)+E35 -> 10778.37 | G35: =_xlfn.NORM.INV(RAND(),$C$20,$D$20) -> 0.089060681 | H35: =(I34+F35*$B$20)*G35 -> 849.68861 | I35: =(I34+(F35*$B$20))*(1+G35) -> 10390.247 | J35: =_xlfn.NORM.INV(RAND(),$C$21,$D$21) -> 0.15577325 | K35: =(L34+F35*$B$21)*J35 -> 3862.6828 | L35: =(L34+F35*$B$21)*(1+J35) -> 28659.514 | M35: =_xlfn.NORM.INV(RAND(),$C$22,$D$22) -> 0.19929564 | N35: =(O34+F35*$B$22)*M35 -> 9103.3058 | O35: =(O34+F35*$B$22)*(1+M35) -> 54780.702 | P35: =I35+L35+O35 -> 93830.463 | Q35: =H35+K35+N35 -> 13815.677 | R35: =IF(Q35>0,Q35*$B$11,0) -> 3868.3896 | S35: =26*$B$13 -> 27997.84 | T35: =P35-R35+S35 -> 117959.91
A36: 39 | B36: =_xlfn.NORM.INV(RAND(),$B$5,$B$6) -> 0.034622039 | C36: =C35*(1+B36) -> 88360.164 | D36: =IF(C36<84000,3%*(1-30%),3%*(1-33%)) -> 0.0201 | E36: =$B$15 -> 521.43 | F36: =C36*($B$9+D36)+E36 -> 11133.486 | G36: =_xlfn.NORM.INV(RAND(),$C$20,$D$20) -> 0.083781491 | H36: =(I35+F36*$B$20)*G36 -> 963.78837 | I36: =(I35+(F36*$B$20))*(1+G36) -> 12467.384 | J36: =_xlfn.NORM.INV(RAND(),$C$21,$D$21) -> -0.03545421 | K36: =(L35+F36*$B$21)*J36 -> -1114.7827 | L36: =(L35+F36*$B$21)*(1+J36) -> 30328.103 | M36: =_xlfn.NORM.INV(RAND(),$C$22,$D$22) -> 0.32915117 | N36: =(O35+F36*$B$22)*M36 -> 20413.122 | O36: =(O35+F36*$B$22)*(1+M36) -> 82430.59 | P36: =I36+L36+O36 -> 125226.08 | Q36: =H36+K36+N36 -> 20262.128 | R36: =IF(Q36>0,Q36*$B$11,0) -> 5673.3958 | S36: =26*$B$13 -> 27997.84 | T36: =P36-R36+S36 -> 147550.52
A37: 40 | B37: =_xlfn.NORM.INV(RAND(),$B$5,$B$6) -> 0.028731509 | C37: =C36*(1+B37) -> 90898.885 | D37: =IF(C37<84000,3%*(1-30%),3%*(1-33%)) -> 0.0201 | E37: =$B$15 -> 521.43 | F37: =C37*($B$9+D37)+E37 -> 11438.386 | G37: =_xlfn.NORM.INV(RAND(),$C$20,$D$20) -> 0.088113399 | H37: =(I36+F37*$B$20)*G37 -> 1199.3311 | I37: =(I36+(F37*$B$20))*(1+G37) -> 14810.553 | J37: =_xlfn.NORM.INV(RAND(),$C$21,$D$21) -> 0.043301792 | K37: =(L36+F37*$B$21)*J37 -> 1437.0869 | L37: =(L36+F37*$B$21)*(1+J37) -> 34624.786 | M37: =_xlfn.NORM.INV(RAND(),$C$22,$D$22) -> -0.084279754 | N37: =(O36+F37*$B$22)*M37 -> -7573.8457 | O37: =(O36+F37*$B$22)*(1+M37) -> 82291.695 | P37: =I37+L37+O37 -> 131727.03 | Q37: =H37+K37+N37 -> -4937.4278 | R37: =IF(Q37>0,Q37*$B$11,0) -> 0 | S37: =26*$B$13 -> 27997.84 | T37: =P37-R37+S37 -> 159724.87
A38: 41 | B38: =_xlfn.NORM.INV(RAND(),$B$5,$B$6) -> 0.031976879 | C38: =C37*(1+B38) -> 93805.547 | D38: =IF(C38<84000,3%*(1-30%),3%*(1-33%)) -> 0.0201 | E38: =$B$15 -> 521.43 | F38: =C38*($B$9+D38)+E38 -> 11787.476 | G38: =_xlfn.NORM.INV(RAND(),$C$20,$D$20) -> -0.022778132 | H38: =(I37+F38*$B$20)*G38 -> -364.20641 | I38: =(I37+(F38*$B$20))*(1+G38) -> 15625.095 | J38: =_xlfn.NORM.INV(RAND(),$C$21,$D$21) -> -0.07020051 | K38: =(L37+F38*$B$21)*J38 -> -2637.5493 | L38: =(L37+F38*$B$21)*(1+J38) -> 34934.106 | M38: =_xlfn.NORM.INV(RAND(),$C$22,$D$22) -> 0.27741865 | N38: =(O37+F38*$B$22)*M38 -> 24954.794 | O38: =(O37+F38*$B$22)*(1+M38) -> 114908.35 | P38: =I38+L38+O38 -> 165467.55 | Q38: =H38+K38+N38 -> 21953.038 | R38: =IF(Q38>0,Q38*$B$11,0) -> 6146.8507 | S38: =26*$B$13 -> 27997.84 | T38: =P38-R38+S38 -> 187318.54
A39: 42 | B39: =_xlfn.NORM.INV(RAND(),$B$5,$B$6) -> 0.031771625 | C39: =C38*(1+B39) -> 96785.902 | D39: =IF(C39<84000,3%*(1-30%),3%*(1-33%)) -> 0.0201 | E39: =$B$15 -> 521.43 | F39: =C39*($B$9+D39)+E39 -> 12145.417 | G39: =_xlfn.NORM.INV(RAND(),$C$20,$D$20) -> 0.027993708 | H39: =(I38+F39*$B$20)*G39 -> 471.40386 | I39: =(I38+(F39*$B$20))*(1+G39) -> 17311.04 | J39: =_xlfn.NORM.INV(RAND(),$C$21,$D$21) -> 0.11946474 | K39: =(L38+F39*$B$21)*J39 -> 4536.1309 | L39: =(L38+F39*$B$21)*(1+J39) -> 42506.591 | M39: =_xlfn.NORM.INV(RAND(),$C$22,$D$22) -> 0.1606009 | N39: =(O38+F39*$B$22)*M39 -> 19722.252 | O39: =(O38+F39*$B$22)*(1+M39) -> 142525.12 | P39: =I39+L39+O39 -> 202342.75 | Q39: =H39+K39+N39 -> 24729.787 | R39: =IF(Q39>0,Q39*$B$11,0) -> 6924.3403 | S39: =26*$B$13 -> 27997.84 | T39: =P39-R39+S39 -> 223416.25
A40: 43 | B40: =_xlfn.NORM.INV(RAND(),$B$5,$B$6) -> 0.036962691 | C40: =C39*(1+B40) -> 100363.37 | D40: =IF(C40<84000,3%*(1-30%),3%*(1-33%)) -> 0.0201 | E40: =$B$15 -> 521.43 | F40: =C40*($B$9+D40)+E40 -> 12575.071 | G40: =_xlfn.NORM.INV(RAND(),$C$20,$D$20) -> 0.046776818 | H40: =(I39+F40*$B$20)*G40 -> 868.57755 | I40: =(I39+(F40*$B$20))*(1+G40) -> 19437.125 | J40: =_xlfn.NORM.INV(RAND(),$C$21,$D$21) -> 0.13220687 | K40: =(L39+F40*$B$21)*J40 -> 6035.2909 | L40: =(L39+F40*$B$21)*(1+J40) -> 51685.649 | M40: =_xlfn.NORM.INV(RAND(),$C$22,$D$22) -> -0.020956164 | N40: =(O39+F40*$B$22)*M40 -> -3158.0712 | O40: =(O39+F40*$B$22)*(1+M40) -> 147540.85 | P40: =I40+L40+O40 -> 218663.62 | Q40: =H40+K40+N40 -> 3745.7972 | R40: =IF(Q40>0,Q40*$B$11,0) -> 1048.8232 | S40: =26*$B$13 -> 27997.84 | T40: =P40-R40+S40 -> 245612.64
A41: 44 | B41: =_xlfn.NORM.INV(RAND(),$B$5,$B$6) -> 0.026248854 | C41: =C40*(1+B41) -> 102997.79 | D41: =IF(C41<84000,3%*(1-30%),3%*(1-33%)) -> 0.0201 | E41: =$B$15 -> 521.43 | F41: =C41*($B$9+D41)+E41 -> 12891.465 | G41: =_xlfn.NORM.INV(RAND(),$C$20,$D$20) -> -0.0070941489 | H41: =(I40+F41*$B$20)*G41 -> -147.03525 | I41: =(I40+(F41*$B$20))*(1+G41) -> 20579.236 | J41: =_xlfn.NORM.INV(RAND(),$C$21,$D$21) -> -0.1720114 | K41: =(L40+F41*$B$21)*J41 -> -9444.8907 | L41: =(L40+F41*$B$21)*(1+J41) -> 45463.625 | M41: =_xlfn.NORM.INV(RAND(),$C$22,$D$22) -> 0.36892044 | N41: =(O40+F41*$B$22)*M41 -> 57522.185 | O41: =(O40+F41*$B$22)*(1+M41) -> 213442.48 | P41: =I41+L41+O41 -> 279485.34 | Q41: =H41+K41+N41 -> 47930.259 | R41: =IF(Q41>0,Q41*$B$11,0) -> 13420.473 | S41: =26*$B$13 -> 27997.84 | T41: =P41-R41+S41 -> 294062.71
... A62: 65 | B62: =_xlfn.NORM.INV(RAND(),$B$5,$B$6) -> 0.046222321 | C62: =C61*(1+B62) -> 213389.64 | D62: =IF(C62<84000,3%*(1-30%),3%*(1-33%)) -> 0.0201 | E62: =$B$15 -> 521.43 | F62: =C62*($B$9+D62)+E62 -> 26149.525 | G62: =_xlfn.NORM.INV(RAND(),$C$20,$D$20) -> 0.062082257 | H62: =(I61+F62*$B$20)*G62 -> 5661.1754 | I62: =(I61+(F62*$B$20))*(1+G62) -> 96849.475 | J62: =_xlfn.NORM.INV(RAND(),$C$21,$D$21) -> -0.039195226 | K62: =(L61+F62*$B$21)*J62 -> -16099.928 | L62: =(L61+F62*$B$21)*(1+J62) -> 394662.54 | M62: =_xlfn.NORM.INV(RAND(),$C$22,$D$22) -> -0.13852265 | N62: =(O61+F62*$B$22)*M62 -> -730705.58 | O62: =(O61+F62*$B$22)*(1+M62) -> 4544284.5 | P62: =I62+L62+O62 -> 5035796.5 | Q62: =H62+K62+N62 -> -741144.33 | R62: =IF(Q62>0,Q62*$B$11,0) -> 0 | S62: =26*$B$13 -> 27997.84 | T62: =P62-R62+S62 -> 5063794.3
S63: Total saving | T63: ='Bank saving'!G32 -> 399121.31
B64: Sum | C64: =SUM(C27:C62) -> 4491115.7 | E64: =SUM(E27:E62) -> 18771.48 | F64: =SUM(F27:F62) -> 558694.43 | P64: =P62 -> 5035796.5 | Q64: =SUM(Q27:Q62) -> 4477102.1 | R64: =SUM(R27:R62) -> 2217980.1 | T64: =P64-R64+T63+'Inflation rate & expenditure1'!P58 -> 5346437.3
A67: trial | B67: Total balance | C67: Total expenditure | D67: Status | E67: Difference
A68: {=_xlfn.SEQUENCE(5000)} -> 1 | B68: =T64 -> 5346437.3 | C68: ='Inflation rate & expenditure1'!N66 -> 3625499.2 | D68: =IF(B68>=C68,"met","unmet") -> met | E68: =B68-C68 -> 1720938
A69: 2 | B69: 4304637.3 | C69: 3633934.4 | D69: met | E69: -6952.6955 | G69: Difference | J69: count | K69: =COUNT(B68:B5067) -> 5000
A70: 3 | B70: 3591983.7 | C70: 3634004.1 | D70: unmet | E70: 885892.73 | G70: mean | H70: =AVERAGE(E68:E5067) -> 1362569.7 | J70: max balance | K70: =MAX(B68:B5067) -> 23243936
A71: 4 | B71: 7806725.1 | C71: 3634014.8 | D71: met | E71: 1030909.5 | G71: SD | H71: =_xlfn.STDEV.S(E68:E5067) -> 1823269.2 | J71: min balance | K71: =MIN(B68:B5067) -> 2692964
A72: 5 | B72: 3616338.4 | C72: 3634106.7 | D72: unmet | E72: 523411.76 | G72: 95%CI | H72: =H70+_xlfn.CONFIDENCE.T(0.05,H71,K69) -> 1413119.5 | J72: mean balance | K72: =AVERAGE(B68:B5067) -> 5059839.2
A73: 6 | B73: 5769670 | C73: 3634670.5 | D73: met | E73: 868424.03 | H73: =H70-_xlfn.CONFIDENCE.T(0.05,H71,K69) -> 1312020 | J73: SD | K73: =_xlfn.STDEV.S(B68:B5067) -> 1908699.5
A74: 7 | B74: 4847050.5 | C74: 3633917.9 | D74: met | E74: 439100.6
A75: 8 | B75: 4213836 | C75: 3634152.7 | D75: met | E75: 1517019.7 | J75: 95%C.I | K75: =K72-_xlfn.CONFIDENCE.T(0.05,K73,K69) -> 5006920.9
A76: 9 | B76: 7096545.9 | C76: 3634089.5 | D76: met | E76: 4047001 | K76: =K72+_xlfn.CONFIDENCE.T(0.05,K73,K69) -> 5112757.5 | N76: best scenario:
A77: 10 | B77: 6056255 | C77: 3634166.2 | D77: met | E77: 1800421.3 | J77: 95%P.I | K77: =_xlfn.PERCENTILE.EXC(B68:B5067,0.025) -> 3328598.6 | N77: 65 retirement age
A78: 11 | B78: 3535245.9 | C78: 3633737.2 | D78: unmet | E78: 1157890.7 | K78: =_xlfn.PERCENTILE.EXC(B68:B5067,0.975) -> 10582624 | N78: the highest controbution rate 10%
A79: 12 | B79: 4393966.1 | C79: 3634186.8 | D79: met | E79: 375138.4 | J79: met Number | K79: =COUNTIF(D68:D5067,"=met") -> 4446 | N79: The allocation rate of funds: 10%, 25% ,65%
A80: 13 | B80: 4550948.5 | C80: 3633723.3 | D80: met | E80: 94497.193 | J80: P(met) | K80: =K79/K69 -> 0.8892
A81: 14 | B81: 11110190 | C81: 3634693.6 | D81: met | E81: 552610.79 | J81: SE | K81: =SQRT(((1-K80)*K80)/K69) -> 0.0044389945 | N81: Compare to the total expenditure of lowest inflation rate
A82: 15 | B82: 4515912.6 | C82: 3634258.1 | D82: met | E82: 399753.04 | J82: 95%C.I | K82: =K80+(_xlfn.NORM.S.INV(0.975))*K81 -> 0.89790027
A83: 16 | B83: 4147981 | C83: 3633502.8 | D83: met | E83: 2566954.6 | K83: =K80-(_xlfn.NORM.S.INV(0.975))*K81 -> 0.88049973
A84: 17 | B84: 3274308.9 | C84: 3634182.2 | D84: unmet | E84: -263502.99
A85: 18 | B85: 3367635.5 | C85: 3634080.6 | D85: unmet | E85: 157169.87 | J85: FIXED
A86: 19 | B86: 4248983 | C86: 3634313.2 | D86: met | E86: 2930362.1 | J86: count | K86: 5000
A87: 20 | B87: 4878417 | C87: 3633971.6 | D87: met | E87: -434916.45 | J87: max balance | K87: 39531978
A88: 21 | B88: 7093360.6 | C88: 3634120.9 | D88: met | E88: -93898.726 | J88: min balance | K88: 2777673.5
A89: 22 | B89: 3306960.6 | C89: 3633614.5 | D89: unmet | E89: 339895.73 | J89: mean balance | K89: 5054992.2 | M89: =K89-C84 -> 1420810
A90: 23 | B90: 6824071.4 | C90: 3634382.4 | D90: met | E90: 563006.68 | J90: SD | K90: 2029472.6
A91: 24 | B91: 4481053.5 | C91: 3634232.8 | D91: met | E91: 1587750.1
A92: 25 | B92: 5070510.5 | C92: 3634064.8 | D92: met | E92: 1080551 | J92: 95%C.I | K92: 4992021.3
A93: 26 | B93: 5148122.3 | C93: 3634509.6 | D93: met | E93: 1284111.6 | K93: 5103507.3
A94: 27 | B94: 15565204 | C94: 3634059.6 | D94: met | E94: -159025.63 | J94: 95%P.I | K94: 3326600.4
A95: 28 | B95: 3713378.4 | C95: 3634268 | D95: met | E95: 401513.29 | K95: 9996185.9
A96: 29 | B96: 3649317.8 | C96: 3634343.7 | D96: met | E96: 1578583.9 | J96: met Number | K96: 4439
A97: 30 | B97: 3319190.9 | C97: 3633676.6 | D97: unmet | E97: 2214706.3 | J97: P(met) | K97: 0.8878 | L97: 85%-90%, safe for reaching goal
A98: 31 | B98: 5249459.9 | C98: 3633721.3 | D98: met | E98: 183058.09 | J98: SE | K98: 0.0044634328
A99: 32 | B99: 7999297.3 | C99: 3633973.9 | D99: met | E99: 620784.65 | J99: 95%C.I | K99: 0.89654817
A100: 33 | B100: 6356402.2 | C100: 3634309.4 | D100: met | E100: 1241131.3 | K100: 0.87905183
A101: 34 | B101: 4839053.8 | C101: 3634814.4 | D101: met | E101: 1298806.3 | K101: =1-K97 -> 0.1122
A102: 35 | B102: 7834072.8 | C102: 3634073.1 | D102: met | E102: 4775282.4
A103: 36 | B103: 4437625.9 | C103: 3633942.7 | D103: met | E103: 776078.13
A104: 37 | B104: 3687610.5 | C104: 3634038.3 | D104: met | E104: 415009.85
A105: 38 | B105: 9250960.5 | C105: 3634501.2 | D105: met | E105: 1299841
A106: 39 | B106: 4030462.9 | C106: 3633983.7 | D106: met | E106: 198659.22
A107: 40 | B107: 4611613.6 | C107: 3633993.2 | D107: met | E107: 2493796.7
A108: 41 | B108: 5616342 | C108: 3634109.6 | D108: met | E108: 1971548.3
A109: 42 | B109: 4246255.4 | C109: 3633991.9 | D109: met | E109: -514294.85
A110: 43 | B110: 7829341.5 | C110: 3634089 | D110: met | E110: 484672.98
A111: 44 | B111: 5318066 | C111: 3634049.8 | D111: met | E111: 1494137.5
A112: 45 | B112: 10817866 | C112: 3634031 | D112: met | E112: -334361.82
A113: 46 | B113: 4161814.2 | C113: 3634009.9 | D113: met | E113: 1368296.1
... A5067: 5000 | B5067: 4118458.2 | C5067: 3634325.6 | D5067: met | E5067: 62893.389

Sheet Neutral scenario 
A1: EMILY'S RETIREMENT MODEL
A3: Parameter | B3: 3910149
A4: current salary: | B4: 70000 | C4: (rand) | D4: =RAND() -> 0.54259986
A5: average growth rate/ yearly （ μ）： | B5: 0.035
A6: Standard variation（σ）： | B6: 0.007
A7: Estimated growth rate(norm) | B7: =_xlfn.NORM.INV(D4,B5,B6) -> 0.0357489
A8: Estimated salary | B8: =B4*(1+B7) -> 72502.423
A9: Contribution rate from Emily | B9: 0.06 | C9: 0.03 | D9: 0.06 | E9: 0.1
A10: superannuation rate from company | B10: 0.021 | C10: Deduct ESCT tax ($57,601 – $84,000) | D10: ESCT tax (> $84,000) | E10: Contribute based on pre-tax salary.
A11: KiwiSaver revenue tax(before retirement) | B11: 0.28
A12: KiwiSaver revenue tax(after retirement) | C12: NZ Super+bank intrest+fund revenue
A13: NZ Super tax | B13: 1076.84
A14: superannuation compensation from goverment | B14: =IF(B8*B9>C15,D15,B8*B9*50%) -> 521.43 | C14: Min personal contribute | D14: Max Member Tax Credit
C15: 1042.86 | D15: 521.43
A16: Annual Bank Savings | B16: =C17*(1+D17) -> 5581.242 | C16: Money saved per year | D16: Rate
C17: 5364 | D17: 0.0405
A18: Decision Variables | B18: Current allocation | C18: Annual Growth Rate | D18: Volatility （SD）
A19: Harbor safe | B19: 0.2 | C19: 0.0375 | D19: 0.05
A20: Horizon | B20: 0.3 | C20: 0.065 | D20: 0.105
A21: Skyhigh | B21: 0.5 | C21: 0.1025 | D21: 0.2075
A22: Total | B22: =SUM(B19:B21) -> 1
A23: Retirement age | B23: 63 | C23: 60 | D23: 63 | E23: 65 | F23: 0.03
B24: NORM.INV(D4,B5,B6) | C24: C19*(1+B20) | D24: IF(C10<84000,3%*(1-C13),3%*(1-D13)) | E24: IF(B8*B9>C13,D13,B8*B9*50%) | F24: C20*(B11+D20)+B14
A25: Year old（30-65 years old） | B25: Salary growth rate | C25: estimated salary | D25: superannuation rate from company | E25: superannuation compensation from gov | F25: Annual superannuation (pre-tax) | G25: Harbor safe growth rate | H25: Harborsafe revenue | I25: Harborsafe balance | J25: Horizon growth rate | K25: Horizon revenue | L25: Horizon balance | M25: Skyhigh growth rate | N25: Skyhigh revenue | O25: Skyhigh balance | P25: Total balance (pre tax) | Q25: Amount needs taxed | R25: Kiwisaver TAX | S25: NZ super | T25: Total Balance( after tax)
A26: 30 | B26: =_xlfn.NORM.INV(RAND(),$B$5,$B$6) -> 0.023086291 | C26: 70000 | D26: =IF(C26<84000,3%*(1-30%),3%*(1-33%)) -> 0.021 | E26: =$B$14 -> 521.43 | F26: =C26*($B$9+D26)+E26 -> 6191.43 | G26: =_xlfn.NORM.INV(RAND(),$C$19,$D$19) -> 0.0022208217 | H26: =(F26*$B$19)*G26 -> 2.7500124 | I26: =F26*B19*(1+G26) -> 1241.036 | J26: =_xlfn.NORM.INV(RAND(),$C$20,$D$20) -> 0.060037692 | K26: =F26*$B$20*J26 -> 111.51575 | L26: =F26*B20*(1+J26) -> 1968.9448 | M26: =_xlfn.NORM.INV(RAND(),$C$21,$D$21) -> 0.25860405 | N26: =F26*$B$21*M26 -> 800.56443 | O26: =F26*B21*(1+M26) -> 3896.2794 | P26: =I26+L26+O26 -> 7106.2602 | Q26: =H26+K26+N26 -> 914.8302 | R26: =IF(Q26>0,Q26*$B$11,0) -> 256.15246 | S26: =26*$B$13 -> 27997.84 | T26: =P26-R26+S26 -> 34847.948
A27: 31 | B27: =_xlfn.NORM.INV(RAND(),$B$5,$B$6) -> 0.018586821 | C27: =C26*(1+B27) -> 71301.077 | D27: =IF(C27<84000,3%*(1-30%),3%*(1-33%)) -> 0.021 | E27: =$B$14 -> 521.43 | F27: =C27*($B$9+D27)+E27 -> 6296.8173 | G27: =_xlfn.NORM.INV(RAND(),$C$19,$D$19) -> 0.12135885 | H27: =(I26+F27*$B$19)*G27 -> 303.44561 | I27: =(I26+(F27*$B$19))*(1+G27) -> 2803.8451 | J27: =_xlfn.NORM.INV(RAND(),$C$20,$D$20) -> -0.063887829 | K27: =(L26+F27*$B$20)*J27 -> -246.4786 | L27: =(L26+F27*$B$20)*(1+J27) -> 3611.5113 | M27: =_xlfn.NORM.INV(RAND(),$C$21,$D$21) -> 0.11487398 | N27: =(O26+F27*$B$21)*M27 -> 809.25135 | O27: =(O26+F27*$B$21)*(1+M27) -> 7853.9394 | P27: =I27+L27+O27 -> 14269.296 | Q27: =H27+K27+N27 -> 866.21836 | R27: =IF(Q27>0,Q27*$B$11,0) -> 242.54114 | S27: =26*$B$13 -> 27997.84 | T27: =P27-R27+S27 -> 42024.595
A28: 32 | B28: =_xlfn.NORM.INV(RAND(),$B$5,$B$6) -> 0.030249302 | C28: 70001 | D28: =IF(C28<84000,3%*(1-30%),3%*(1-33%)) -> 0.021 | E28: =$B$14 -> 521.43 | F28: =C28*($B$9+D28)+E28 -> 6191.511 | G28: =_xlfn.NORM.INV(RAND(),$C$19,$D$19) -> 0.021154084 | H28: =(I27+F28*$B$19)*G28 -> 85.507925 | I28: =(I27+(F28*$B$19))*(1+G28) -> 4127.6552 | J28: =_xlfn.NORM.INV(RAND(),$C$20,$D$20) -> 0.1274051 | K28: =(L27+F28*$B$20)*J28 -> 696.77397 | L28: =(L27+F28*$B$20)*(1+J28) -> 6165.7386 | M28: =_xlfn.NORM.INV(RAND(),$C$21,$D$21) -> 0.085485678 | N28: =(O27+F28*$B$21)*M28 -> 936.04209 | O28: =(O27+F28*$B$21)*(1+M28) -> 11885.737 | P28: =I28+L28+O28 -> 22179.131 | Q28: =H28+K28+N28 -> 1718.324 | R28: =IF(Q28>0,Q28*$B$11,0) -> 481.13071 | S28: =26*$B$13 -> 27997.84 | T28: =P28-R28+S28 -> 49695.84
A29: 33 | B29: =_xlfn.NORM.INV(RAND(),$B$5,$B$6) -> 0.026812615 | C29: =C28*(1+B29) -> 71877.91 | D29: =IF(C29<84000,3%*(1-30%),3%*(1-33%)) -> 0.021 | E29: =$B$14 -> 521.43 | F29: =C29*($B$9+D29)+E29 -> 6343.5407 | G29: =_xlfn.NORM.INV(RAND(),$C$19,$D$19) -> 0.13755063 | H29: =(I28+F29*$B$19)*G29 -> 742.27316 | I29: =(I28+(F29*$B$19))*(1+G29) -> 6138.6365 | J29: =_xlfn.NORM.INV(RAND(),$C$20,$D$20) -> -0.060198112 | K29: =(L28+F29*$B$20)*J29 -> -485.72658 | L29: =(L28+F29*$B$20)*(1+J29) -> 7583.0742 | M29: =_xlfn.NORM.INV(RAND(),$C$21,$D$21) -> 0.1904455 | N29: =(O28+F29*$B$21)*M29 -> 2867.6346 | O29: =(O28+F29*$B$21)*(1+M29) -> 17925.142 | P29: =I29+L29+O29 -> 31646.853 | Q29: =H29+K29+N29 -> 3124.1811 | R29: =IF(Q29>0,Q29*$B$11,0) -> 874.77072 | S29: =26*$B$13 -> 27997.84 | T29: =P29-R29+S29 -> 58769.922
A30: 34 | B30: =_xlfn.NORM.INV(RAND(),$B$5,$B$6) -> 0.048734406 | C30: =C29*(1+B30) -> 75380.837 | D30: =IF(C30<84000,3%*(1-30%),3%*(1-33%)) -> 0.021 | E30: =$B$14 -> 521.43 | F30: =C30*($B$9+D30)+E30 -> 6627.2778 | G30: =_xlfn.NORM.INV(RAND(),$C$19,$D$19) -> 0.0045141188 | H30: =(I29+F30*$B$19)*G30 -> 33.693799 | I30: =(I29+(F30*$B$19))*(1+G30) -> 7497.7859 | J30: =_xlfn.NORM.INV(RAND(),$C$20,$D$20) -> 0.065532212 | K30: =(L29+F30*$B$20)*J30 -> 627.22568 | L30: =(L29+F30*$B$20)*(1+J30) -> 10198.483 | M30: =_xlfn.NORM.INV(RAND(),$C$21,$D$21) -> -0.49635148 | N30: =(O29+F30*$B$21)*M30 -> -10541.9 | O30: =(O29+F30*$B$21)*(1+M30) -> 10696.88 | P30: =I30+L30+O30 -> 28393.15 | Q30: =H30+K30+N30 -> -9880.9809 | R30: =IF(Q30>0,Q30*$B$11,0) -> 0 | S30: =26*$B$13 -> 27997.84 | T30: =P30-R30+S30 -> 56390.99
A31: 35 | B31: =_xlfn.NORM.INV(RAND(),$B$5,$B$6) -> 0.035537931 | C31: =C30*(1+B31) -> 78059.716 | D31: =IF(C31<84000,3%*(1-30%),3%*(1-33%)) -> 0.021 | E31: =$B$14 -> 521.43 | F31: =C31*($B$9+D31)+E31 -> 6844.267 | G31: =_xlfn.NORM.INV(RAND(),$C$19,$D$19) -> 0.067191498 | H31: =(I30+F31*$B$19)*G31 -> 595.76277 | I31: =(I30+(F31*$B$19))*(1+G31) -> 9462.402 | J31: =_xlfn.NORM.INV(RAND(),$C$20,$D$20) -> 0.019651643 | K31: =(L30+F31*$B$20)*J31 -> 240.76728 | L31: =(L30+F31*$B$20)*(1+J31) -> 12492.531 | M31: =_xlfn.NORM.INV(RAND(),$C$21,$D$21) -> 0.14278926 | N31: =(O30+F31*$B$21)*M31 -> 2016.0436 | O31: =(O30+F31*$B$21)*(1+M31) -> 16135.058 | P31: =I31+L31+O31 -> 38089.99 | Q31: =H31+K31+N31 -> 2852.5736 | R31: =IF(Q31>0,Q31*$B$11,0) -> 798.72062 | S31: =26*$B$13 -> 27997.84 | T31: =P31-R31+S31 -> 65289.11
A32: 36 | B32: =_xlfn.NORM.INV(RAND(),$B$5,$B$6) -> 0.031972488 | C32: =C31*(1+B32) -> 80555.479 | D32: =IF(C32<84000,3%*(1-30%),3%*(1-33%)) -> 0.021 | E32: =$B$14 -> 521.43 | F32: =C32*($B$9+D32)+E32 -> 7046.4238 | G32: =_xlfn.NORM.INV(RAND(),$C$19,$D$19) -> 0.076980501 | H32: =(I31+F32*$B$19)*G32 -> 836.90789 | I32: =(I31+(F32*$B$19))*(1+G32) -> 11708.595 | J32: =_xlfn.NORM.INV(RAND(),$C$20,$D$20) -> 0.06780081 | K32: =(L31+F32*$B$20)*J32 -> 990.32967 | L32: =(L31+F32*$B$20)*(1+J32) -> 15596.787 | M32: =_xlfn.NORM.INV(RAND(),$C$21,$D$21) -> 0.037359101 | N32: =(O31+F32*$B$21)*M32 -> 734.41527 | O32: =(O31+F32*$B$21)*(1+M32) -> 20392.685 | P32: =I32+L32+O32 -> 47698.067 | Q32: =H32+K32+N32 -> 2561.6528 | R32: =IF(Q32>0,Q32*$B$11,0) -> 717.26279 | S32: =26*$B$13 -> 27997.84 | T32: =P32-R32+S32 -> 74978.644
A33: 37 | B33: =_xlfn.NORM.INV(RAND(),$B$5,$B$6) -> 0.048925036 | C33: =C32*(1+B33) -> 84496.659 | D33: =IF(C33<84000,3%*(1-30%),3%*(1-33%)) -> 0.0201 | E33: =$B$14 -> 521.43 | F33: =C33*($B$9+D33)+E33 -> 7289.6124 | G33: =_xlfn.NORM.INV(RAND(),$C$19,$D$19) -> 0.090164952 | H33: =(I32+F33*$B$19)*G33 -> 1187.1584 | I33: =(I32+(F33*$B$19))*(1+G33) -> 14353.676 | J33: =_xlfn.NORM.INV(RAND(),$C$20,$D$20) -> 0.060475179 | K33: =(L32+F33*$B$20)*J33 -> 1075.4707 | L33: =(L32+F33*$B$20)*(1+J33) -> 18859.142 | M33: =_xlfn.NORM.INV(RAND(),$C$21,$D$21) -> 0.011297334 | N33: =(O32+F33*$B$21)*M33 -> 271.55956 | O33: =(O32+F33*$B$21)*(1+M33) -> 24309.05 | P33: =I33+L33+O33 -> 57521.868 | Q33: =H33+K33+N33 -> 2534.1886 | R33: =IF(Q33>0,Q33*$B$11,0) -> 709.57282 | S33: =26*$B$13 -> 27997.84 | T33: =P33-R33+S33 -> 84810.135
A34: 38 | B34: =_xlfn.NORM.INV(RAND(),$B$5,$B$6) -> 0.039789106 | C34: =C33*(1+B34) -> 87858.706 | D34: =IF(C34<84000,3%*(1-30%),3%*(1-33%)) -> 0.0201 | E34: =$B$14 -> 521.43 | F34: =C34*($B$9+D34)+E34 -> 7558.9123 | G34: =_xlfn.NORM.INV(RAND(),$C$19,$D$19) -> 0.020045727 | H34: =(I33+F34*$B$19)*G34 -> 318.03464 | I34: =(I33+(F34*$B$19))*(1+G34) -> 16183.493 | J34: =_xlfn.NORM.INV(RAND(),$C$20,$D$20) -> 0.097907321 | K34: =(L33+F34*$B$20)*J34 -> 2068.4699 | L34: =(L33+F34*$B$20)*(1+J34) -> 23195.285 | M34: =_xlfn.NORM.INV(RAND(),$C$21,$D$21) -> -0.12107688 | N34: =(O33+F34*$B$21)*M34 -> -3400.8689 | O34: =(O33+F34*$B$21)*(1+M34) -> 24687.638 | P34: =I34+L34+O34 -> 64066.416 | Q34: =H34+K34+N34 -> -1014.3643 | R34: =IF(Q34>0,Q34*$B$11,0) -> 0 | S34: =26*$B$13 -> 27997.84 | T34: =P34-R34+S34 -> 92064.256
A35: 39 | B35: =_xlfn.NORM.INV(RAND(),$B$5,$B$6) -> 0.044303056 | C35: =C34*(1+B35) -> 91751.115 | D35: =IF(C35<84000,3%*(1-30%),3%*(1-33%)) -> 0.0201 | E35: =$B$14 -> 521.43 | F35: =C35*($B$9+D35)+E35 -> 7870.6943 | G35: =_xlfn.NORM.INV(RAND(),$C$19,$D$19) -> 0.029005087 | H35: =(I34+F35*$B$19)*G35 -> 515.06164 | I35: =(I34+(F35*$B$19))*(1+G35) -> 18272.693 | J35: =_xlfn.NORM.INV(RAND(),$C$20,$D$20) -> 0.0797277 | K35: =(L34+F35*$B$20)*J35 -> 2037.5605 | L35: =(L34+F35*$B$20)*(1+J35) -> 27594.054 | M35: =_xlfn.NORM.INV(RAND(),$C$21,$D$21) -> 0.13762021 | N35: =(O34+F35*$B$21)*M35 -> 3939.1011 | O35: =(O34+F35*$B$21)*(1+M35) -> 32562.086 | P35: =I35+L35+O35 -> 78428.833 | Q35: =H35+K35+N35 -> 6491.7232 | R35: =IF(Q35>0,Q35*$B$11,0) -> 1817.6825 | S35: =26*$B$13 -> 27997.84 | T35: =P35-R35+S35 -> 104608.99
A36: 40 | B36: =_xlfn.NORM.INV(RAND(),$B$5,$B$6) -> 0.03629439 | C36: =C35*(1+B36) -> 95081.166 | D36: =IF(C36<84000,3%*(1-30%),3%*(1-33%)) -> 0.0201 | E36: =$B$14 -> 521.43 | F36: =C36*($B$9+D36)+E36 -> 8137.4314 | G36: =_xlfn.NORM.INV(RAND(),$C$19,$D$19) -> 0.21291917 | H36: =(I35+F36*$B$19)*G36 -> 4237.1296 | I36: =(I35+(F36*$B$19))*(1+G36) -> 24137.309 | J36: =_xlfn.NORM.INV(RAND(),$C$20,$D$20) -> 0.22779501 | K36: =(L35+F36*$B$20)*J36 -> 6841.8878 | L36: =(L35+F36*$B$20)*(1+J36) -> 36877.171 | M36: =_xlfn.NORM.INV(RAND(),$C$21,$D$21) -> 0.45644241 | N36: =(O35+F36*$B$21)*M36 -> 16719.851 | O36: =(O35+F36*$B$21)*(1+M36) -> 53350.653 | P36: =I36+L36+O36 -> 114365.13 | Q36: =H36+K36+N36 -> 27798.869 | R36: =IF(Q36>0,Q36*$B$11,0) -> 7783.6833 | S36: =26*$B$13 -> 27997.84 | T36: =P36-R36+S36 -> 134579.29
A37: 41 | B37: =_xlfn.NORM.INV(RAND(),$B$5,$B$6) -> 0.04017256 | C37: =C36*(1+B37) -> 98900.819 | D37: =IF(C37<84000,3%*(1-30%),3%*(1-33%)) -> 0.0201 | E37: =$B$14 -> 521.43 | F37: =C37*($B$9+D37)+E37 -> 8443.3856 | G37: =_xlfn.NORM.INV(RAND(),$C$19,$D$19) -> 0.05613659 | H37: =(I36+F37*$B$19)*G37 -> 1449.7828 | I37: =(I36+(F37*$B$19))*(1+G37) -> 27275.769 | J37: =_xlfn.NORM.INV(RAND(),$C$20,$D$20) -> 0.057768784 | K37: =(L36+F37*$B$20)*J37 -> 2276.6786 | L37: =(L36+F37*$B$20)*(1+J37) -> 41686.866 | M37: =_xlfn.NORM.INV(RAND(),$C$21,$D$21) -> -0.13281333 | N37: =(O36+F37*$B$21)*M37 -> -7646.3748 | O37: =(O36+F37*$B$21)*(1+M37) -> 49925.971 | P37: =I37+L37+O37 -> 118888.61 | Q37: =H37+K37+N37 -> -3919.9134 | R37: =IF(Q37>0,Q37*$B$11,0) -> 0 | S37: =26*$B$13 -> 27997.84 | T37: =P37-R37+S37 -> 146886.45
A38: 42 | B38: =_xlfn.NORM.INV(RAND(),$B$5,$B$6) -> 0.034094801 | C38: =C37*(1+B38) -> 102272.82 | D38: =IF(C38<84000,3%*(1-30%),3%*(1-33%)) -> 0.0201 | E38: =$B$14 -> 521.43 | F38: =C38*($B$9+D38)+E38 -> 8713.4831 | G38: =_xlfn.NORM.INV(RAND(),$C$19,$D$19) -> 0.12094766 | H38: =(I37+F38*$B$19)*G38 -> 3509.7156 | I38: =(I37+(F38*$B$19))*(1+G38) -> 32528.181 | J38: =_xlfn.NORM.INV(RAND(),$C$20,$D$20) -> -0.027467188 | K38: =(L37+F38*$B$20)*J38 -> -1216.8214 | L38: =(L37+F38*$B$20)*(1+J38) -> 43084.089 | M38: =_xlfn.NORM.INV(RAND(),$C$21,$D$21) -> 0.3618874 | N38: =(O37+F38*$B$21)*M38 -> 19644.23 | O38: =(O37+F38*$B$21)*(1+M38) -> 73926.942 | P38: =I38+L38+O38 -> 149539.21 | Q38: =H38+K38+N38 -> 21937.124 | R38: =IF(Q38>0,Q38*$B$11,0) -> 6142.3947 | S38: =26*$B$13 -> 27997.84 | T38: =P38-R38+S38 -> 171394.66
A39: 43 | B39: =_xlfn.NORM.INV(RAND(),$B$5,$B$6) -> 0.03562993 | C39: =C38*(1+B39) -> 105916.8 | D39: =IF(C39<84000,3%*(1-30%),3%*(1-33%)) -> 0.0201 | E39: =$B$14 -> 521.43 | F39: =C39*($B$9+D39)+E39 -> 9005.3654 | G39: =_xlfn.NORM.INV(RAND(),$C$19,$D$19) -> 0.018426325 | H39: =(I38+F39*$B$19)*G39 -> 632.562 | I39: =(I38+(F39*$B$19))*(1+G39) -> 34961.816 | J39: =_xlfn.NORM.INV(RAND(),$C$20,$D$20) -> 0.094213248 | K39: =(L38+F39*$B$20)*J39 -> 4313.6194 | L39: =(L38+F39*$B$20)*(1+J39) -> 50099.318 | M39: =_xlfn.NORM.INV(RAND(),$C$21,$D$21) -> 0.22934566 | N39: =(O38+F39*$B$21)*M39 -> 17987.494 | O39: =(O38+F39*$B$21)*(1+M39) -> 96417.119 | P39: =I39+L39+O39 -> 181478.25 | Q39: =H39+K39+N39 -> 22933.676 | R39: =IF(Q39>0,Q39*$B$11,0) -> 6421.4292 | S39: =26*$B$13 -> 27997.84 | T39: =P39-R39+S39 -> 203054.66
A40: 44 | B40: =_xlfn.NORM.INV(RAND(),$B$5,$B$6) -> 0.04621668 | C40: =C39*(1+B40) -> 110811.92 | D40: =IF(C40<84000,3%*(1-30%),3%*(1-33%)) -> 0.0201 | E40: =$B$14 -> 521.43 | F40: =C40*($B$9+D40)+E40 -> 9397.4647 | G40: =_xlfn.NORM.INV(RAND(),$C$19,$D$19) -> 0.11958228 | H40: =(I39+F40*$B$19)*G40 -> 4405.5679 | I40: =(I39+(F40*$B$19))*(1+G40) -> 41246.877 | J40: =_xlfn.NORM.INV(RAND(),$C$20,$D$20) -> 0.048798526 | K40: =(L39+F40*$B$20)*J40 -> 2582.3476 | L40: =(L39+F40*$B$20)*(1+J40) -> 55500.905 | M40: =_xlfn.NORM.INV(RAND(),$C$21,$D$21) -> 0.22361685 | N40: =(O39+F40*$B$21)*M40 -> 22611.209 | O40: =(O39+F40*$B$21)*(1+M40) -> 123727.06 | P40: =I40+L40+O40 -> 220474.84 | Q40: =H40+K40+N40 -> 29599.124 | R40: =IF(Q40>0,Q40*$B$11,0) -> 8287.7548 | S40: =26*$B$13 -> 27997.84 | T40: =P40-R40+S40 -> 240184.93
... A59: 63 | B59: =_xlfn.NORM.INV(RAND(),$B$5,$B$6) -> 0.035177849 | C59: =C58*(1+B59) -> 193636.7 | D59: =IF(C59<84000,3%*(1-30%),3%*(1-33%)) -> 0.0201 | E59: =$B$14 -> 521.43 | F59: =C59*($B$9+D59)+E59 -> 16031.729 | G59: =_xlfn.NORM.INV(RAND(),$C$19,$D$19) -> 0.072547985 | H59: =(I58+F59*$B$19)*G59 -> 9156.5471 | I59: =(I58+(F59*$B$19))*(1+G59) -> 135370.21 | J59: =_xlfn.NORM.INV(RAND(),$C$20,$D$20) -> -0.099343302 | K59: =(L58+F59*$B$20)*J59 -> -20629.963 | L59: =(L58+F59*$B$20)*(1+J59) -> 187033.39 | M59: =_xlfn.NORM.INV(RAND(),$C$21,$D$21) -> 0.36874664 | N59: =(O58+F59*$B$21)*M59 -> 101761.66 | O59: =(O58+F59*$B$21)*(1+M59) -> 377728.01 | P59: =I59+L59+O59 -> 700131.61 | Q59: =H59+K59+N59 -> 90288.248 | R59: =IF(Q59>0,Q59*$B$11,0) -> 25280.709 | S59: =26*$B$13 -> 27997.84 | T59: =P59-R59+S59 -> 702848.74
A60: 64
A61: 65 | U61: NZ Super | V61: 2027565.5
S62: Total Savng | T62: ='Bank saving'!G30 -> 361317.75 | U62: Bank Saving | V62: 361317.75
B63: Sum | C63: =SUM(C26:C61) -> 4190605.7 | E63: =SUM(E26:E61) -> 17728.62 | F63: =SUM(F26:F61) -> 353861.6 | P63: =P59 -> 700131.61 | Q63: =SUM(Q26:Q61) -> 346270.02 | R63: =SUM(R26:R61) -> 176854.67 | T63: =P63-R63+T62+'Inflation rate & expenditure1'!P58 -> 3014094.3
A66: trial | B66: Total balance | C66: Total expenditure | D66: Status | E66: Difference
A67: {=_xlfn.SEQUENCE(5000)} -> 1 | B67: =T63 -> 3014094.3 | C67: ='Inflation rate & expenditure1'!AD66 -> 3891102.8 | D67: =IF(B67>=C67,"met","unmet") -> unmet | E67: =B67-C67 -> -877008.58
A68: 2 | B68: 3129062.3 | C68: 3890765.3 | D68: unmet | E68: -761702.95
A69: 3 | B69: 3803777.2 | C69: 3890633.8 | D69: unmet | E69: -86856.634 | G69: Difference
A70: 4 | B70: 4290842 | C70: 3890230.2 | D70: met | E70: 400611.85 | G70: Mean | H70: =AVERAGE(E67:E5066) -> 23974.923
A71: 5 | B71: 4946515.9 | C71: 3890594.6 | D71: met | E71: 1055921.2 | G71: SD | H71: =_xlfn.STDEV.S(E67:E5066) -> 794703.92
A72: 6 | B72: 3452322.4 | C72: 3890794.5 | D72: unmet | E72: -438472.13 | G72: 95%CI | H72: =H70+_xlfn.CONFIDENCE.T(0.05,H71,H76) -> 46007.922
A73: 7 | B73: 3205710.6 | C73: 3890380.7 | D73: unmet | E73: -684670.11 | H73: =H70-_xlfn.CONFIDENCE.T(0.05,H71,H76) -> 1941.9247
A74: 8 | B74: 5808660.8 | C74: 3890678.4 | D74: met | E74: 1917982.4
A75: 9 | B75: 3852065 | C75: 3890622.3 | D75: unmet | E75: -38557.341
A76: 10 | B76: 4480184.4 | C76: 3890415.5 | D76: met | E76: 589768.87 | G76: count | H76: =COUNT(B67:B5066) -> 5000
A77: 11 | B77: 4265291.1 | C77: 3890607.3 | D77: met | E77: 374683.81 | G77: max balance | H77: =MAX(B67:B5066) -> 14396557 | L77: Tot_balance | M77: Tot_expenditure | N77: P(met)
A78: 12 | B78: 3606440.1 | C78: 3891215.7 | D78: unmet | E78: -284775.53 | G78: min balance | H78: =MIN(B67:B5066) -> 2638592.2 | K78: Best scenario | L78: 5054992 | M78: 3616121 | N78: 0.8878
A79: 13 | B79: 3179807.7 | C79: 3891403.6 | D79: unmet | E79: -711595.95 | G79: mean balance | H79: =AVERAGE(B67:B5066) -> 3914753.9 | K79: Neutral scenario | L79: 3926670 | M79: 3906935 | N79: 0.3876
A80: 14 | B80: 3440709.4 | C80: 3890711.5 | D80: unmet | E80: -450002.05 | G80: SD | H80: =_xlfn.STDEV.S(B67:B5066) -> 794705.01 | K80: Worst scenario | L80: 3238939 | M80: 4253608 | N80: 0.0148
A81: 15 | B81: 3909073.4 | C81: 3890590.5 | D81: met | E81: 18482.883
A82: 16 | B82: 3549491.8 | C82: 3890540.9 | D82: unmet | E82: -341049.15 | G82: 95%C.I | H82: =H79-_xlfn.CONFIDENCE.T(0.05,H80,H76) -> 3892720.8
A83: 17 | B83: 3182792.9 | C83: 3890511.9 | D83: unmet | E83: -707719.04 | H83: =H79+_xlfn.CONFIDENCE.T(0.05,H80,H76) -> 3936786.9
A84: 18 | B84: 3355403.9 | C84: 3890716.3 | D84: unmet | E84: -535312.43 | G84: 95%P.I | H84: =_xlfn.PERCENTILE.EXC(B67:B5066,0.025) -> 3058117.5
A85: 19 | B85: 6464626.5 | C85: 3890432.5 | D85: met | E85: 2574194.1 | H85: =_xlfn.PERCENTILE.EXC(B67:B5066,0.975) -> 5913673
A86: 20 | B86: 4064624.3 | C86: 3891003.2 | D86: met | E86: 173621.08 | G86: Met Number | H86: =COUNTIF(D67:D5066,"=met") -> 1869
A87: 21 | B87: 3229419.3 | C87: 3890795 | D87: unmet | E87: -661375.77 | G87: P(met) | H87: =H86/H76 -> 0.3738
A88: 22 | B88: 3187419.3 | C88: 3890279.6 | D88: unmet | E88: -702860.32 | G88: SE | H88: =SQRT(((1-H87)*H87)/H76) -> 0.0068421277
A89: 23 | B89: 3630280.1 | C89: 3890829 | D89: unmet | E89: -260548.85 | G89: 95%C.I | H89: =H87+(_xlfn.NORM.S.INV(0.975))*H88 -> 0.38721032
A90: 24 | B90: 4035638.3 | C90: 3890554.8 | D90: met | E90: 145083.55 | H90: =H87-(_xlfn.NORM.S.INV(0.975))*H88 -> 0.36038968
A91: 25 | B91: 3717631.6 | C91: 3891310.3 | D91: unmet | E91: -173678.73
A92: 26 | B92: 4862736.5 | C92: 3890570.8 | D92: met | E92: 972165.7
A93: 27 | B93: 5488789.1 | C93: 3890441.7 | D93: met | E93: 1598347.4 | G93: FIXED
A94: 28 | B94: 3543614.7 | C94: 3890729.1 | D94: unmet | E94: -347114.35 | G94: count | H94: 5000
A95: 29 | B95: 3175930.6 | C95: 3891225.3 | D95: unmet | E95: -715294.76 | G95: max balance | H95: 17501028
A96: 30 | B96: 3478670.5 | C96: 3890716.7 | D96: unmet | E96: -412046.2 | G96: min balance | H96: 2778355.9
A97: 31 | B97: 4763463 | C97: 3890762.1 | D97: met | E97: 872700.99 | G97: mean balance | H97: 3926670.7
A98: 32 | B98: 3883474.6 | C98: 3891047.4 | D98: unmet | E98: -7572.7678 | G98: SD | H98: 863643.65
A99: 33 | B99: 6194181.8 | C99: 3890317.6 | D99: met | E99: 2303864.1
A100: 34 | B100: 3412899.3 | C100: 3890859.2 | D100: unmet | E100: -477959.86 | G100: 95%C.I | H100: 3902726.4
A101: 35 | B101: 5968858.7 | C101: 3890303.6 | D101: met | E101: 2078555.1 | H101: 3950615
A102: 36 | B102: 3100795.9 | C102: 3890594 | D102: unmet | E102: -789798.02 | G102: 95%P.I | H102: 3052320.1
A103: 37 | B103: 4227212.4 | C103: 3890711.2 | D103: met | E103: 336501.15 | H103: 6087487.1
A104: 38 | B104: 2973254.3 | C104: 3890917.2 | D104: unmet | E104: -917662.9 | G104: Met Number | H104: 1897
A105: 39 | B105: 3163893.1 | C105: 3890390.9 | D105: unmet | E105: -726497.77 | G105: P(met) | H105: 0.3794
A106: 40 | B106: 3294882.9 | C106: 3891034.1 | D106: unmet | E106: -596151.16 | G106: SE | H106: 0.0068622976
A107: 41 | B107: 4009305.8 | C107: 3890725.8 | D107: met | E107: 118580.03 | G107: 95%C.I | H107: 0.39284986
A108: 42 | B108: 3708228.6 | C108: 3890731.9 | D108: unmet | E108: -182503.39 | H108: 0.36595014
A109: 43 | B109: 3874188.9 | C109: 3890727.3 | D109: unmet | E109: -16538.392
A110: 44 | B110: 4135826.1 | C110: 3891255 | D110: met | E110: 244571.1
A111: 45 | B111: 3357804.2 | C111: 3890555.3 | D111: unmet | E111: -532751.18
A112: 46 | B112: 3728440.3 | C112: 3890751.3 | D112: unmet | E112: -162310.98
A113: 47 | B113: 3440017.2 | C113: 3890612 | D113: unmet | E113: -450594.78
A114: 48 | B114: 3631179.3 | C114: 3890666.1 | D114: unmet | E114: -259486.75
A115: 49 | B115: 3699981.7 | C115: 3890375.6 | D115: unmet | E115: -190393.94
A116: 50 | B116: 3988652.5 | C116: 3890875.2 | D116: met | E116: 97777.276
A117: 51 | B117: 4217786.9 | C117: 3890940.2 | D117: met | E117: 326846.74
A118: 52 | B118: 4049297.6 | C118: 3890570.5 | D118: met | E118: 158727.13
A119: 53 | B119: 4871373.6 | C119: 3890503.1 | D119: met | E119: 980870.52
A120: 54 | B120: 4070883.4 | C120: 3890221 | D120: met | E120: 180662.41
... A5066: 5000 | B5066: 3122764.8 | C5066: 3890510.1 | D5066: unmet | E5066: -767745.27

Sheet Worst scenario
A1: EMILY'S RETIREMENT MODEL
A3: Parameter
A4: current salary: | B4: 70000 | C4: (rand) | D4: =RAND() -> 0.31454696
A5: average growth rate/ yearly （ μ）： | B5: 0.035
A6: Standard variation（σ）： | B6: 0.007
A7: Estimated growth rate(norm) | B7: =_xlfn.NORM.INV(D4,B5,B6) -> 0.031618982
A8: Estimated salary | B8: =B4*(1+B7) -> 72213.329
A9: Contribution rate from Emily | B9: 0.03 | C9: 0.03 | D9: 0.06 | E9: 0.1
A10: superannuation rate from company | B10: 0.021 | C10: Deduct ESCT tax ($57,601 – $84,000) | D10: ESCT tax (> $84,000) | E10: Contribute based on pre-tax salary.
A11: KiwiSaver revenue tax(before retirement) | B11: 0.28
A12: KiwiSaver revenue tax(after retirement) | C12: NZ Super+bank intrest+fund revenue
A13: NZ Super tax | B13: 1076.84
A14: superannuation compensation from goverment | B14: =IF(B8*B9>C15,D15,B8*B9*50%) -> 521.43 | C14: Min personal contribute | D14: Max Member Tax Credit
C15: 1042.86 | D15: 521.43
A16: Annual Bank Savings | B16: =C17*(1+D17) -> 5581.242 | C16: Money saved per year | D16: Rate
C17: 5364 | D17: 0.0405
A18: Decision Variables | B18: Current allocation | C18: Annual Growth Rate | D18: Volatility （SD）
A19: Harbor safe | B19: 0.4 | C19: 0.0375 | D19: 0.05
A20: Horizon | B20: 0.3 | C20: 0.065 | D20: 0.105
A21: Skyhigh | B21: 0.3 | C21: 0.1025 | D21: 0.2075
A22: Total | B22: =SUM(B19:B21) -> 1
A23: Retirement age | B23: 60 | C23: 60 | D23: 63 | E23: 65
F24: 0.03
B25: NORM.INV(D4,B5,B6) | C25: C19*(1+B20) | D25: IF(C10<84000,3%*(1-C13),3%*(1-D13)) | E25: IF(B8*B9>C13,D13,B8*B9*50%) | F25: C20*(B11+D20)+B14
A26: Year old（30-65 years old） | B26: Salary growth rate | C26: estimated salary | D26: superannuation rate from company | E26: superannuation compensation from gov | F26: Annual superannuation (pre-tax) | G26: Harbor safe growth rate | H26: Harborsafe revenue | I26: Harborsafe balance | J26: Horizon growth rate | K26: Horizon revenue | L26: Horizon balance | M26: Skyhigh growth rate | N26: Skyhigh revenue | O26: Skyhigh balance | P26: Total balance (pre tax) | Q26: Amount needs taxed | R26: Kiwisaver TAX | S26: NZ super | T26: Total Balance( after tax)
A27: 30 | B27: =_xlfn.NORM.INV(RAND(),$B$5,$B$6) -> 0.034041556 | C27: 70000 | D27: =IF(C27<84000,3%*(1-30%),3%*(1-33%)) -> 0.021 | E27: =$B$14 -> 521.43 | F27: =C27*($B$9+D27)+E27 -> 4091.43 | G27: =_xlfn.NORM.INV(RAND(),$C$19,$D$19) -> 0.057169888 | H27: =(F27*$B$19)*G27 -> 93.562638 | I27: =F27*B20*(1+G27) -> 1297.601 | J27: =_xlfn.NORM.INV(RAND(),$C$20,$D$20) -> 0.072363751 | K27: =F27*$B$20*J27 -> 88.821366 | L27: =F27*B21*(1+J27) -> 1316.2504 | M27: =_xlfn.NORM.INV(RAND(),$C$21,$D$21) -> 0.11653358 | N27: =F27*$B$21*M27 -> 143.03669 | O27: =F27*B22*(1+M27) -> 4568.219 | P27: =I27+L27+O27 -> 7182.0703 | Q27: =H27+K27+N27 -> 325.42069 | R27: =IF(Q27>0,Q27*$B$11,0) -> 91.117794 | S27: =26*$B$13 -> 27997.84 | T27: =P27-R27+S27 -> 35088.793
A28: 31 | B28: =_xlfn.NORM.INV(RAND(),$B$5,$B$6) -> 0.035711792 | C28: =C27*(1+B28) -> 72499.825 | D28: =IF(C28<84000,3%*(1-30%),3%*(1-33%)) -> 0.021 | E28: =$B$14 -> 521.43 | F28: =C28*($B$9+D28)+E28 -> 4218.9211 | G28: =_xlfn.NORM.INV(RAND(),$C$19,$D$19) -> 0.069402698 | H28: =(I27+F28*$B$19)*G28 -> 207.17881 | I28: =(I27+(F28*$B$19))*(1+G28) -> 3192.3482 | J28: =_xlfn.NORM.INV(RAND(),$C$20,$D$20) -> 0.23517553 | K28: =(L27+F28*$B$20)*J28 -> 607.20597 | L28: =(L27+F28*$B$20)*(1+J28) -> 3189.1327 | M28: =_xlfn.NORM.INV(RAND(),$C$21,$D$21) -> -0.33593082 | N28: =(O27+F28*$B$21)*M28 -> -1959.7853 | O28: =(O27+F28*$B$21)*(1+M28) -> 3874.11 | P28: =I28+L28+O28 -> 10255.591 | Q28: =H28+K28+N28 -> -1145.4005 | R28: =IF(Q28>0,Q28*$B$11,0) -> 0 | S28: =26*$B$13 -> 27997.84 | T28: =P28-R28+S28 -> 38253.431
A29: 32 | B29: =_xlfn.NORM.INV(RAND(),$B$5,$B$6) -> 0.033908332 | C29: 70001 | D29: =IF(C29<84000,3%*(1-30%),3%*(1-33%)) -> 0.021 | E29: =$B$14 -> 521.43 | F29: =C29*($B$9+D29)+E29 -> 4091.481 | G29: =_xlfn.NORM.INV(RAND(),$C$19,$D$19) -> 0.011964981 | H29: =(I28+F29*$B$19)*G29 -> 57.778184 | I29: =(I28+(F29*$B$19))*(1+G29) -> 4886.7188 | J29: =_xlfn.NORM.INV(RAND(),$C$20,$D$20) -> 0.14927292 | K29: =(L28+F29*$B$20)*J29 -> 659.27534 | L29: =(L28+F29*$B$20)*(1+J29) -> 5075.8523 | M29: =_xlfn.NORM.INV(RAND(),$C$21,$D$21) -> 0.082653448 | N29: =(O28+F29*$B$21)*M29 -> 421.66106 | O29: =(O28+F29*$B$21)*(1+M29) -> 5523.2154 | P29: =I29+L29+O29 -> 15485.787 | Q29: =H29+K29+N29 -> 1138.7146 | R29: =IF(Q29>0,Q29*$B$11,0) -> 318.84008 | S29: =26*$B$13 -> 27997.84 | T29: =P29-R29+S29 -> 43164.786
A30: 33 | B30: =_xlfn.NORM.INV(RAND(),$B$5,$B$6) -> 0.040114549 | C30: =C29*(1+B30) -> 72809.059 | D30: =IF(C30<84000,3%*(1-30%),3%*(1-33%)) -> 0.021 | E30: =$B$14 -> 521.43 | F30: =C30*($B$9+D30)+E30 -> 4234.692 | G30: =_xlfn.NORM.INV(RAND(),$C$19,$D$19) -> 0.08422204 | H30: =(I29+F30*$B$19)*G30 -> 554.23118 | I30: =(I29+(F30*$B$19))*(1+G30) -> 7134.8268 | J30: =_xlfn.NORM.INV(RAND(),$C$20,$D$20) -> 0.065613895 | K30: =(L29+F30*$B$20)*J30 -> 416.40283 | L30: =(L29+F30*$B$20)*(1+J30) -> 6762.6627 | M30: =_xlfn.NORM.INV(RAND(),$C$21,$D$21) -> -0.26222376 | N30: =(O29+F30*$B$21)*M30 -> -1781.4494 | O30: =(O29+F30*$B$21)*(1+M30) -> 5012.1736 | P30: =I30+L30+O30 -> 18909.663 | Q30: =H30+K30+N30 -> -810.81535 | R30: =IF(Q30>0,Q30*$B$11,0) -> 0 | S30: =26*$B$13 -> 27997.84 | T30: =P30-R30+S30 -> 46907.503
A31: 34 | B31: =_xlfn.NORM.INV(RAND(),$B$5,$B$6) -> 0.036403391 | C31: =C30*(1+B31) -> 75459.555 | D31: =IF(C31<84000,3%*(1-30%),3%*(1-33%)) -> 0.021 | E31: =$B$14 -> 521.43 | F31: =C31*($B$9+D31)+E31 -> 4369.8673 | G31: =_xlfn.NORM.INV(RAND(),$C$19,$D$19) -> 0.12062208 | H31: =(I30+F31*$B$19)*G31 -> 1071.4586 | I31: =(I30+(F31*$B$19))*(1+G31) -> 9954.2323 | J31: =_xlfn.NORM.INV(RAND(),$C$20,$D$20) -> -0.057904579 | K31: =(L30+F31*$B$20)*J31 -> -467.49973 | L31: =(L30+F31*$B$20)*(1+J31) -> 7606.1232 | M31: =_xlfn.NORM.INV(RAND(),$C$21,$D$21) -> 0.05859683 | N31: =(O30+F31*$B$21)*M31 -> 370.51559 | O31: =(O30+F31*$B$21)*(1+M31) -> 6693.6494 | P31: =I31+L31+O31 -> 24254.005 | Q31: =H31+K31+N31 -> 974.47446 | R31: =IF(Q31>0,Q31*$B$11,0) -> 272.85285 | S31: =26*$B$13 -> 27997.84 | T31: =P31-R31+S31 -> 51978.992
A32: 35 | B32: =_xlfn.NORM.INV(RAND(),$B$5,$B$6) -> 0.038943348 | C32: =C31*(1+B32) -> 78398.203 | D32: =IF(C32<84000,3%*(1-30%),3%*(1-33%)) -> 0.021 | E32: =$B$14 -> 521.43 | F32: =C32*($B$9+D32)+E32 -> 4519.7383 | G32: =_xlfn.NORM.INV(RAND(),$C$19,$D$19) -> 0.074504612 | H32: =(I31+F32*$B$19)*G32 -> 876.33275 | I32: =(I31+(F32*$B$19))*(1+G32) -> 12638.46 | J32: =_xlfn.NORM.INV(RAND(),$C$20,$D$20) -> 0.032872267 | K32: =(L31+F32*$B$20)*J32 -> 294.60273 | L32: =(L31+F32*$B$20)*(1+J32) -> 9256.6474 | M32: =_xlfn.NORM.INV(RAND(),$C$21,$D$21) -> 0.36859843 | N32: =(O31+F32*$B$21)*M32 -> 2967.0592 | O32: =(O31+F32*$B$21)*(1+M32) -> 11016.63 | P32: =I32+L32+O32 -> 32911.738 | Q32: =H32+K32+N32 -> 4137.9946 | R32: =IF(Q32>0,Q32*$B$11,0) -> 1158.6385 | S32: =26*$B$13 -> 27997.84 | T32: =P32-R32+S32 -> 59750.939
A33: 36 | B33: =_xlfn.NORM.INV(RAND(),$B$5,$B$6) -> 0.035050687 | C33: =C32*(1+B33) -> 81146.114 | D33: =IF(C33<84000,3%*(1-30%),3%*(1-33%)) -> 0.021 | E33: =$B$14 -> 521.43 | F33: =C33*($B$9+D33)+E33 -> 4659.8818 | G33: =_xlfn.NORM.INV(RAND(),$C$19,$D$19) -> 0.024453563 | H33: =(I32+F33*$B$19)*G33 -> 354.63567 | I33: =(I32+(F33*$B$19))*(1+G33) -> 14857.049 | J33: =_xlfn.NORM.INV(RAND(),$C$20,$D$20) -> 0.14942095 | K33: =(L32+F33*$B$20)*J33 -> 1592.0223 | L33: =(L32+F33*$B$20)*(1+J33) -> 12246.634 | M33: =_xlfn.NORM.INV(RAND(),$C$21,$D$21) -> 0.14119403 | N33: =(O32+F33*$B$21)*M33 -> 1752.8666 | O33: =(O32+F33*$B$21)*(1+M33) -> 14167.461 | P33: =I33+L33+O33 -> 41271.144 | Q33: =H33+K33+N33 -> 3699.5246 | R33: =IF(Q33>0,Q33*$B$11,0) -> 1035.8669 | S33: =26*$B$13 -> 27997.84 | T33: =P33-R33+S33 -> 68233.117
A34: 37 | B34: =_xlfn.NORM.INV(RAND(),$B$5,$B$6) -> 0.024234904 | C34: =C33*(1+B34) -> 83112.682 | D34: =IF(C34<84000,3%*(1-30%),3%*(1-33%)) -> 0.021 | E34: =$B$14 -> 521.43 | F34: =C34*($B$9+D34)+E34 -> 4760.1768 | G34: =_xlfn.NORM.INV(RAND(),$C$19,$D$19) -> 0.0060139597 | H34: =(I33+F34*$B$19)*G34 -> 100.8007 | I34: =(I33+(F34*$B$19))*(1+G34) -> 16861.92 | J34: =_xlfn.NORM.INV(RAND(),$C$20,$D$20) -> 0.16697686 | K34: =(L33+F34*$B$20)*J34 -> 2283.3564 | L34: =(L33+F34*$B$20)*(1+J34) -> 15958.044 | M34: =_xlfn.NORM.INV(RAND(),$C$21,$D$21) -> -0.17385086 | N34: =(O33+F34*$B$21)*M34 -> -2711.2936 | O34: =(O33+F34*$B$21)*(1+M34) -> 12884.221 | P34: =I34+L34+O34 -> 45704.185 | Q34: =H34+K34+N34 -> -327.13651 | R34: =IF(Q34>0,Q34*$B$11,0) -> 0 | S34: =26*$B$13 -> 27997.84 | T34: =P34-R34+S34 -> 73702.025
A35: 38 | B35: =_xlfn.NORM.INV(RAND(),$B$5,$B$6) -> 0.034954299 | C35: =C34*(1+B35) -> 86017.828 | D35: =IF(C35<84000,3%*(1-30%),3%*(1-33%)) -> 0.0201 | E35: =$B$14 -> 521.43 | F35: =C35*($B$9+D35)+E35 -> 4830.9232 | G35: =_xlfn.NORM.INV(RAND(),$C$19,$D$19) -> -0.0054303651 | H35: =(I34+F35*$B$19)*G35 -> -102.05985 | I35: =(I34+(F35*$B$19))*(1+G35) -> 18692.23 | J35: =_xlfn.NORM.INV(RAND(),$C$20,$D$20) -> 0.082526049 | K35: =(L34+F35*$B$20)*J35 -> 1436.5574 | L35: =(L34+F35*$B$20)*(1+J35) -> 18843.878 | M35: =_xlfn.NORM.INV(RAND(),$C$21,$D$21) -> -0.08600079 | N35: =(O34+F35*$B$21)*M35 -> -1232.6921 | O35: =(O34+F35*$B$21)*(1+M35) -> 13100.805 | P35: =I35+L35+O35 -> 50636.913 | Q35: =H35+K35+N35 -> 101.80543 | R35: =IF(Q35>0,Q35*$B$11,0) -> 28.505521 | S35: =26*$B$13 -> 27997.84 | T35: =P35-R35+S35 -> 78606.248
A36: 39 | B36: =_xlfn.NORM.INV(RAND(),$B$5,$B$6) -> 0.034613721 | C36: =C35*(1+B36) -> 88995.225 | D36: =IF(C36<84000,3%*(1-30%),3%*(1-33%)) -> 0.0201 | E36: =$B$14 -> 521.43 | F36: =C36*($B$9+D36)+E36 -> 4980.0908 | G36: =_xlfn.NORM.INV(RAND(),$C$19,$D$19) -> -0.0067473029 | H36: =(I35+F36*$B$19)*G36 -> -139.56301 | I36: =(I35+(F36*$B$19))*(1+G36) -> 20544.703 | J36: =_xlfn.NORM.INV(RAND(),$C$20,$D$20) -> 0.201125 | K36: =(L35+F36*$B$20)*J36 -> 4090.4612 | L36: =(L35+F36*$B$20)*(1+J36) -> 24428.366 | M36: =_xlfn.NORM.INV(RAND(),$C$21,$D$21) -> 0.059341353 | N36: =(O35+F36*$B$21)*M36 -> 866.07713 | O36: =(O35+F36*$B$21)*(1+M36) -> 15460.91 | P36: =I36+L36+O36 -> 60433.979 | Q36: =H36+K36+N36 -> 4816.9754 | R36: =IF(Q36>0,Q36*$B$11,0) -> 1348.7531 | S36: =26*$B$13 -> 27997.84 | T36: =P36-R36+S36 -> 87083.066
A37: 40 | B37: =_xlfn.NORM.INV(RAND(),$B$5,$B$6) -> 0.025771866 | C37: =C36*(1+B37) -> 91288.798 | D37: =IF(C37<84000,3%*(1-30%),3%*(1-33%)) -> 0.0201 | E37: =$B$14 -> 521.43 | F37: =C37*($B$9+D37)+E37 -> 5094.9988 | G37: =_xlfn.NORM.INV(RAND(),$C$19,$D$19) -> 0.049125781 | H37: =(I36+F37*$B$19)*G37 -> 1109.3929 | I37: =(I36+(F37*$B$19))*(1+G37) -> 23692.095 | J37: =_xlfn.NORM.INV(RAND(),$C$20,$D$20) -> 0.14163334 | K37: =(L36+F37*$B$20)*J37 -> 3676.3576 | L37: =(L36+F37*$B$20)*(1+J37) -> 29633.224 | M37: =_xlfn.NORM.INV(RAND(),$C$21,$D$21) -> 0.28192389 | N37: =(O36+F37*$B$21)*M37 -> 4789.7203 | O37: =(O36+F37*$B$21)*(1+M37) -> 21779.13 | P37: =I37+L37+O37 -> 75104.449 | Q37: =H37+K37+N37 -> 9575.4708 | R37: =IF(Q37>0,Q37*$B$11,0) -> 2681.1318 | S37: =26*$B$13 -> 27997.84 | T37: =P37-R37+S37 -> 100421.16
A38: 41 | B38: =_xlfn.NORM.INV(RAND(),$B$5,$B$6) -> 0.034557116 | C38: =C37*(1+B38) -> 94443.475 | D38: =IF(C38<84000,3%*(1-30%),3%*(1-33%)) -> 0.0201 | E38: =$B$14 -> 521.43 | F38: =C38*($B$9+D38)+E38 -> 5253.0481 | G38: =_xlfn.NORM.INV(RAND(),$C$19,$D$19) -> 0.071340544 | H38: =(I37+F38*$B$19)*G38 -> 1840.1091 | I38: =(I37+(F38*$B$19))*(1+G38) -> 27633.424 | J38: =_xlfn.NORM.INV(RAND(),$C$20,$D$20) -> 0.0014234904 | K38: =(L37+F38*$B$20)*J38 -> 44.425907 | L38: =(L37+F38*$B$20)*(1+J38) -> 31253.564 | M38: =_xlfn.NORM.INV(RAND(),$C$21,$D$21) -> -0.10716494 | N38: =(O37+F38*$B$21)*M38 -> -2502.842 | O38: =(O37+F38*$B$21)*(1+M38) -> 20852.202 | P38: =I38+L38+O38 -> 79739.19 | Q38: =H38+K38+N38 -> -618.30698 | R38: =IF(Q38>0,Q38*$B$11,0) -> 0 | S38: =26*$B$13 -> 27997.84 | T38: =P38-R38+S38 -> 107737.03
A39: 42 | B39: =_xlfn.NORM.INV(RAND(),$B$5,$B$6) -> 0.034968881 | C39: =C38*(1+B39) -> 97746.058 | D39: =IF(C39<84000,3%*(1-30%),3%*(1-33%)) -> 0.0201 | E39: =$B$14 -> 521.43 | F39: =C39*($B$9+D39)+E39 -> 5418.5075 | G39: =_xlfn.NORM.INV(RAND(),$C$19,$D$19) -> -0.013852044 | H39: =(I38+F39*$B$19)*G39 -> -412.80236 | I39: =(I38+(F39*$B$19))*(1+G39) -> 29388.024 | J39: =_xlfn.NORM.INV(RAND(),$C$20,$D$20) -> -0.062582037 | K39: =(L38+F39*$B$20)*J39 -> -2057.6421 | L39: =(L38+F39*$B$20)*(1+J39) -> 30821.474 | M39: =_xlfn.NORM.INV(RAND(),$C$21,$D$21) -> -0.1197113 | N39: =(O38+F39*$B$21)*M39 -> -2690.8412 | O39: =(O38+F39*$B$21)*(1+M39) -> 19786.913 | P39: =I39+L39+O39 -> 79996.412 | Q39: =H39+K39+N39 -> -5161.2857 | R39: =IF(Q39>0,Q39*$B$11,0) -> 0 | S39: =26*$B$13 -> 27997.84 | T39: =P39-R39+S39 -> 107994.25
A40: 43 | B40: =_xlfn.NORM.INV(RAND(),$B$5,$B$6) -> 0.025146063 | C40: =C39*(1+B40) -> 100203.99 | D40: =IF(C40<84000,3%*(1-30%),3%*(1-33%)) -> 0.0201 | E40: =$B$14 -> 521.43 | F40: =C40*($B$9+D40)+E40 -> 5541.6497 | G40: =_xlfn.NORM.INV(RAND(),$C$19,$D$19) -> 0.057105778 | H40: =(I39+F40*$B$19)*G40 -> 1804.8101 | I40: =(I39+(F40*$B$19))*(1+G40) -> 33409.494 | J40: =_xlfn.NORM.INV(RAND(),$C$20,$D$20) -> 0.12816238 | K40: =(L39+F40*$B$20)*J40 -> 4163.2227 | L40: =(L39+F40*$B$20)*(1+J40) -> 36647.192 | M40: =_xlfn.NORM.INV(RAND(),$C$21,$D$21) -> 0.23375269 | N40: =(O39+F40*$B$21)*M40 -> 5013.8569 | O40: =(O39+F40*$B$21)*(1+M40) -> 26463.265 | P40: =I40+L40+O40 -> 96519.951 | Q40: =H40+K40+N40 -> 10981.89 | R40: =IF(Q40>0,Q40*$B$11,0) -> 3074.9291 | S40: =26*$B$13 -> 27997.84 | T40: =P40-R40+S40 -> 121442.86
A41: 44 | B41: =_xlfn.NORM.INV(RAND(),$B$5,$B$6) -> 0.038672742 | C41: =C40*(1+B41) -> 104079.15 | D41: =IF(C41<84000,3%*(1-30%),3%*(1-33%)) -> 0.0201 | E41: =$B$14 -> 521.43 | F41: =C41*($B$9+D41)+E41 -> 5735.7954 | G41: =_xlfn.NORM.INV(RAND(),$C$19,$D$19) -> 0.068717203 | H41: =(I40+F41*$B$19)*G41 -> 2453.4661 | I41: =(I40+(F41*$B$19))*(1+G41) -> 38157.279 | J41: =_xlfn.NORM.INV(RAND(),$C$20,$D$20) -> 0.006744756 | K41: =(L40+F41*$B$20)*J41 -> 258.78233 | L41: =(L40+F41*$B$20)*(1+J41) -> 38626.713 | M41: =_xlfn.NORM.INV(RAND(),$C$21,$D$21) -> 0.35428853 | N41: =(O40+F41*$B$21)*M41 -> 9985.2692 | O41: =(O40+F41*$B$21)*(1+M41) -> 38169.273 | P41: =I41+L41+O41 -> 114953.26 | Q41: =H41+K41+N41 -> 12697.518 | R41: =IF(Q41>0,Q41*$B$11,0) -> 3555.3049 | S41: =26*$B$13 -> 27997.84 | T41: =P41-R41+S41 -> 139395.8
... A57: 60 | B57: =_xlfn.NORM.INV(RAND(),$B$5,$B$6) -> 0.04316143 | C57: =C56*(1+B57) -> 182825.1 | D57: =IF(C57<84000,3%*(1-30%),3%*(1-33%)) -> 0.0201 | E57: =$B$14 -> 521.43 | F57: =C57*($B$9+D57)+E57 -> 9680.9677 | G57: =_xlfn.NORM.INV(RAND(),$C$19,$D$19) -> 0.028811018 | H57: =(I56+F57*$B$19)*G57 -> 4127.4073 | I57: =(I56+(F57*$B$19))*(1+G57) -> 147385.35 | J57: =_xlfn.NORM.INV(RAND(),$C$20,$D$20) -> 0.039022367 | K57: =(L56+F57*$B$20)*J57 -> 4443.7162 | L57: =(L56+F57*$B$20)*(1+J57) -> 118319.85 | M57: =_xlfn.NORM.INV(RAND(),$C$21,$D$21) -> 0.25017062 | N57: =(O56+F57*$B$21)*M57 -> 51432.804 | O57: =(O56+F57*$B$21)*(1+M57) -> 257023.71 | P57: =I57+L57+O57 -> 522728.91 | Q57: =H57+K57+N57 -> 60003.927 | R57: =IF(Q57>0,Q57*$B$11,0) -> 16801.1 | S57: =26*$B$13 -> 27997.84 | T57: =P57-R57+S57 -> 533925.65
A58: 61
A59: 62
A60: 63
A61: 64
A62: 65
S63: Bank Saving | T63: ='Bank saving'!G27 -> 309084.63
B64: Sum | C64: =SUM(C27:C62) -> 3547178.5 | E64: =SUM(E27:E62) -> 16164.33 | F64: =SUM(F27:F62) -> 194421.06 | P64: =P57 -> 522728.91 | R64: =SUM(R27:R57) -> 111700.64 | T64: =P64-R64+T63+'Inflation rate & expenditure1'!P58 -> 2849612.5
A67: trial | B67: Total balance | C67: Total expenditure | D67: Status | E67: Difference
A68: {=_xlfn.SEQUENCE(5000)} -> 1 | B68: =T64 -> 2849612.5 | C68: ='Inflation rate & expenditure1'!W66 -> 4253088.1 | D68: =IF(B68>=C68,"met","unmet") -> unmet | E68: =B68-C68 -> -1403475.7
A69: 2 | B69: 2988141.2 | C69: 4253209.5 | D69: unmet | E69: -1265068.3
A70: 3 | B70: 3610813.7 | C70: 4253017.6 | D70: unmet | E70: -642203.82
A71: 4 | B71: 3281841.6 | C71: 4253388.3 | D71: unmet | E71: -971546.74
A72: 5 | B72: 3179421.1 | C72: 4253417.8 | D72: unmet | E72: -1073996.8
A73: 6 | B73: 3155269.6 | C73: 4253638.4 | D73: unmet | E73: -1098368.7
A74: 7 | B74: 3075266.5 | C74: 4253302.5 | D74: unmet | E74: -1178036
A75: 8 | B75: 3149552 | C75: 4253352.6 | D75: unmet | E75: -1103800.6
A76: 9 | B76: 3332283.9 | C76: 4253198.7 | D76: unmet | E76: -920914.74
A77: 10 | B77: 3433788.3 | C77: 4253263.5 | D77: unmet | E77: -819475.15
A78: 11 | B78: 3726197.5 | C78: 4253140.4 | D78: unmet | E78: -526942.91
A79: 12 | B79: 3166199.6 | C79: 4252998.5 | D79: unmet | E79: -1086798.9
A80: 13 | B80: 2987096.3 | C80: 4253120 | D80: unmet | E80: -1266023.7
... A98: 31 | B98: 3553506.8 | C98: 4253833.8 | D98: unmet | E98: -700326.98
A99: 32 | B99: 3277003.1 | C99: 4253771.3 | D99: unmet | E99: -976768.14 | H99: count | I99: =COUNT(B68:B5067) -> 5000
A100: 33 | B100: 3487339.9 | C100: 4253121.6 | D100: unmet | E100: -765781.76 | H100: max balance | I100: =MAX(B68:B5067) -> 8380559.5
A101: 34 | B101: 3014665.4 | C101: 4253901.7 | D101: unmet | E101: -1239236.3 | H101: min balance | I101: =MIN(B68:B5067) -> 2435378.7
A102: 35 | B102: 3342770.6 | C102: 4253603.5 | D102: unmet | E102: -910832.82 | H102: mean balance | I102: =AVERAGE(B68:B5067) -> 3247595.1
A103: 36 | B103: 3282155.3 | C103: 4253598.1 | D103: unmet | E103: -971442.8 | H103: SD | I103: =_xlfn.STDEV.S(B68:B5067) -> 345465.95
A104: 37 | B104: 2845471 | C104: 4253460.6 | D104: unmet | E104: -1407989.5
A105: 38 | B105: 3070374.6 | C105: 4253504.5 | D105: unmet | E105: -1183129.9 | H105: 95%C.I | I105: =I102-_xlfn.CONFIDENCE.T(0.05,I103,I99) -> 3238017.1
A106: 39 | B106: 3195667.2 | C106: 4253557.9 | D106: unmet | E106: -1057890.7 | I106: =I102+_xlfn.CONFIDENCE.T(0.05,I103,I99) -> 3257173.1
A107: 40 | B107: 3265455.4 | C107: 4253757.9 | D107: unmet | E107: -988302.51 | H107: 95%P.I | I107: =_xlfn.PERCENTILE.EXC(B68:B5067,0.025) -> 2775053.3
A108: 41 | B108: 3682087.4 | C108: 4253084.6 | D108: unmet | E108: -570997.23 | I108: =_xlfn.PERCENTILE.EXC(B68:B5067,0.975) -> 4073185
A109: 42 | B109: 3409209.9 | C109: 4253778.7 | D109: unmet | E109: -844568.75 | H109: Met Number | I109: =COUNTIF(D68:D5067,"=met") -> 70
A110: 43 | B110: 3764717.7 | C110: 4253559.6 | D110: unmet | E110: -488841.91 | H110: P(met) | I110: =I109/I99 -> 0.014
A111: 44 | B111: 3429886.9 | C111: 4253793.8 | D111: unmet | E111: -823906.86 | H111: SE | I111: =SQRT(((1-I110)*I110)/I99) -> 0.0016615655
A112: 45 | B112: 2950605.3 | C112: 4252686.6 | D112: unmet | E112: -1302081.3 | H112: 95%C.I | I112: =I110+(_xlfn.NORM.S.INV(0.975))*I111 -> 0.017256609
A113: 46 | B113: 3459587.6 | C113: 4253157.1 | D113: unmet | E113: -793569.46 | I113: =I110-(_xlfn.NORM.S.INV(0.975))*I111 -> 0.010743391
A114: 47 | B114: 4245181 | C114: 4253357.3 | D114: unmet | E114: -8176.2852
A115: 48 | B115: 3442586.8 | C115: 4252987.7 | D115: unmet | E115: -810400.98
A116: 49 | B116: 3321781.4 | C116: 4253336 | D116: unmet | E116: -931554.6 | H116: Fixed value
A117: 50 | B117: 2963082.7 | C117: 4253477.7 | D117: unmet | E117: -1290394.9 | H117: count | I117: 5000
A118: 51 | B118: 2939752.5 | C118: 4253456.1 | D118: unmet | E118: -1313703.6 | H118: max balance | I118: 7118691.2
A119: 52 | B119: 3113069.8 | C119: 4253446.3 | D119: unmet | E119: -1140376.5 | H119: min balance | I119: 2478011.8
A120: 53 | B120: 3444374 | C120: 4253276.4 | D120: unmet | E120: -808902.47 | H120: mean balance | I120: 3238939.5
A121: 54 | B121: 3464504.7 | C121: 4253155.9 | D121: unmet | E121: -788651.18 | H121: SD | I121: 316636.15
A122: 55 | B122: 3276276.7 | C122: 4252953.7 | D122: unmet | E122: -976677.03
A123: 56 | B123: 4292366.6 | C123: 4253482.1 | D123: met | E123: 38884.452 | H123: 95%C.I | I123: 3230160.8 | K123: 2504918.2
A124: 57 | B124: 3396412.5 | C124: 4253543.1 | D124: unmet | E124: -857130.58 | I124: 3247718.1 | K124: 450943.29
A125: 58 | B125: 3283130.9 | C125: 4253341.7 | D125: unmet | E125: -970210.8 | H125: 95%P.I | I125: 2773650.5
A126: 59 | B126: 3280423 | C126: 4254286.4 | D126: unmet | E126: -973863.48 | I126: 3955323.6
A127: 60 | B127: 3736769.7 | C127: 4253543.3 | D127: unmet | E127: -516773.57 | H127: Met Number | I127: 50
A128: 61 | B128: 3423363.7 | C128: 4253251.6 | D128: unmet | E128: -829887.96 | H128: P(met) | I128: 0.01
A129: 62 | B129: 3616418.3 | C129: 4253256.8 | D129: unmet | E129: -636838.48 | H129: SE | I129: 0.0014071247
A130: 63 | B130: 3546113 | C130: 4253319.1 | D130: unmet | E130: -707206.09 | H130: 95%C.I | I130: 0.012757914 | J130: 5000
A131: 64 | B131: 2916061.3 | C131: 4254061.8 | D131: unmet | E131: -1338000.5 | I131: 0.0072420862 | J131: 6761237.9
A132: 65 | B132: 2927500.5 | C132: 4253659.3 | D132: unmet | E132: -1326158.8 | I132: min balance | J132: 2394947.1
A133: 66 | B133: 3490178.5 | C133: 4253050.5 | D133: unmet | E133: -762872.02 | I133: mean balance | J133: 3241012.1
A134: 67 | B134: 3170808.2 | C134: 4253628.9 | D134: unmet | E134: -1082820.7 | I134: SD | J134: 326649.91
A135: 68 | B135: 3330367 | C135: 4253657.3 | D135: unmet | E135: -923290.24
...

Sheet Inflation rate & expenditure
D2: Min | F2: 0.001
D3: average | F3: 0.025643564
D4: Max | F4: 0.073
D5: SD | F5: 0.016450887
A7: Date | B7: CPI (Annual % change) | D7: AGE | E7: Inflation rate | F7: Average annual expenditure | G7: Total expenditure | J7: trial | K7: Total Expenditure | R7: Best senario | S7: AGE | T7: Inflation rate | U7: Average annual expenditure | V7: Total expenditure | W7: Cumalative expenditure | Y7: worst senario | Z7: AGE | AA7: Inflation rate | AB7: Average annaul expenditure | AC7: Total expenture | AD7: Cumalative expenditure
A8: 3/31/2000 | B8: 1.5 | D8: 65 | E8: 0.024008407 | F8: 39279.836 | G8: 40222.883 | J8: {=_xlfn.SEQUENCE(5000)} -> 1 | K8: =V34 -> 1043808.6 | M8: max | N8: =MAX(K8:K5007) -> 1054404.6 | S8: 65 | T8: =_xlfn.NORM.INV(RAND(),'Inflation rate & expenditure1'!E29,'Inflation rate & expenditure1'!E30) -> 0.0091686012 | U8: 39279.836 | V8: =U8*(1+T8) -> 39639.978 | W8: =V8 -> 39639.978 | Z8: 60 | AA8: =_xlfn.NORM.INV(RAND(),'Inflation rate & expenditure1'!$E$29,'Inflation rate & expenditure1'!$E$30) -> 0.026038213 | AB8: 39279.836 | AC8: =AB8*(1+AA8) -> 40302.613 | AD8: =AC8 -> 40302.613
A9: 6/30/2000 | B9: 2 | D9: 66 | E9: 0.04544144 | F9: 39279.836 | G9: 41064.769 | J9: 2 | K9: 1045974.1 | M9: min | N9: =MIN(K8:K5007) -> 1035686.7 | S9: 66 | T9: =_xlfn.NORM.INV(RAND(),'Inflation rate & expenditure1'!E29,'Inflation rate & expenditure1'!E30) -> 0.013419979 | U9: 39279.836 | V9: =U9*(1+T9) -> 39806.971 | W9: =V9+W8 -> 79446.949 | Z9: 61 | AA9: =_xlfn.NORM.INV(RAND(),'Inflation rate & expenditure1'!$E$29,'Inflation rate & expenditure1'!$E$30) -> 0.0022884717 | AB9: 39279.836 | AC9: =AB9*(1+AA9) -> 39369.727 | AD9: =AC9+AD8 -> 79672.34
A10: 9/30/2000 | B10: 3 | D10: 67 | E10: 0.021357737 | F10: 39279.836 | G10: 40118.765 | J10: 3 | K10: 1044323.6 | M10: mean | N10: =AVERAGE(K8:K5007) -> 1044988.2 | S10: 67 | T10: =_xlfn.NORM.INV(RAND(),'Inflation rate & expenditure1'!E29,'Inflation rate & expenditure1'!E30) -> 0.01766742 | U10: 39279.836 | V10: =U10*(1+T10) -> 39973.81 | W10: =V10+W9 -> 119420.76 | Z10: 62 | AA10: =_xlfn.NORM.INV(RAND(),'Inflation rate & expenditure1'!$E$29,'Inflation rate & expenditure1'!$E$30) -> 0.03353774 | AB10: 39279.836 | AC10: =AB10*(1+AA10) -> 40597.193 | AD10: =AC10+AD9 -> 120269.53
A11: 12/31/2000 | B11: 4 | D11: 68 | E11: 0.013409904 | F11: 39279.836 | G11: 39806.575 | J11: 4 | K11: 1048496.4 | M11: sd | N11: =_xlfn.STDEV.S(K8:K5007) -> 2671.3689 | S11: 68 | T11: =_xlfn.NORM.INV(RAND(),'Inflation rate & expenditure1'!E29,'Inflation rate & expenditure1'!E30) -> 0.054401346 | U11: 39279.836 | V11: =U11*(1+T11) -> 41416.712 | W11: =V11+W10 -> 160837.47 | Z11: 63 | AA11: =_xlfn.NORM.INV(RAND(),'Inflation rate & expenditure1'!$E$29,'Inflation rate & expenditure1'!$E$30) -> 0.049521619 | AB11: 39279.836 | AC11: =AB11*(1+AA11) -> 41225.037 | AD11: =AC11+AD10 -> 161494.57
A12: 3/31/2001 | B12: 3.1 | D12: 69 | E12: 0.0064509825 | F12: 39279.836 | G12: 39533.23 | J12: 5 | K12: 1042033.5 | M12: count | N12: =COUNT(K8:K5007) -> 5000 | S12: 69 | T12: =_xlfn.NORM.INV(RAND(),'Inflation rate & expenditure1'!E29,'Inflation rate & expenditure1'!E30) -> 0.032534327 | U12: 39279.836 | V12: =U12*(1+T12) -> 40557.779 | W12: =V12+W11 -> 201395.25 | Z12: 64 | AA12: =_xlfn.NORM.INV(RAND(),'Inflation rate & expenditure1'!$E$29,'Inflation rate & expenditure1'!$E$30) -> 0.012188187 | AB12: 39279.836 | AC12: =AB12*(1+AA12) -> 39758.586 | AD12: =AC12+AD11 -> 201253.16
A13: 6/30/2001 | B13: 3.2 | D13: 70 | E13: 0.0058239922 | F13: 39279.836 | G13: 39508.602 | J13: 6 | K13: 1050614.2 | S13: 70 | T13: =_xlfn.NORM.INV(RAND(),'Inflation rate & expenditure1'!E29,'Inflation rate & expenditure1'!E30) -> 0.0478443 | U13: 39279.836 | V13: =U13*(1+T13) -> 41159.153 | W13: =V13+W12 -> 242554.4 | Z13: 65 | AA13: =_xlfn.NORM.INV(RAND(),'Inflation rate & expenditure1'!$E$29,'Inflation rate & expenditure1'!$E$30) -> 0.025942822 | AB13: 39279.836 | AC13: =AB13*(1+AA13) -> 40298.866 | AD13: =AC13+AD12 -> 241552.02
A14: 9/30/2001 | B14: 2.4 | D14: 71 | E14: -0.018863775 | F14: 39279.836 | G14: 38538.87 | J14: 7 | K14: 1048413.4 | M14: Fixed expenditure | S14: 71 | T14: =_xlfn.NORM.INV(RAND(),'Inflation rate & expenditure1'!E29,'Inflation rate & expenditure1'!E30) -> 0.033779915 | U14: 39279.836 | V14: =U14*(1+T14) -> 40606.706 | W14: =V14+W13 -> 283161.11 | Z14: 66 | AA14: =_xlfn.NORM.INV(RAND(),'Inflation rate & expenditure1'!$E$29,'Inflation rate & expenditure1'!$E$30) -> 0.0021879312 | AB14: 39279.836 | AC14: =AB14*(1+AA14) -> 39365.778 | AD14: =AC14+AD13 -> 280917.8
A15: 12/31/2001 | B15: 1.8 | D15: 72 | E15: 0.015890055 | F15: 39279.836 | G15: 39903.995 | J15: 8 | K15: 1041547.6 | M15: Worst scenario | N15: 1185666.7 | S15: 72 | T15: =_xlfn.NORM.INV(RAND(),'Inflation rate & expenditure1'!E29,'Inflation rate & expenditure1'!E30) -> 0.024112897 | U15: 39279.836 | V15: =U15*(1+T15) -> 40226.987 | W15: =V15+W14 -> 323388.1 | Z15: 67 | AA15: =_xlfn.NORM.INV(RAND(),'Inflation rate & expenditure1'!$E$29,'Inflation rate & expenditure1'!$E$30) -> 0.041515489 | AB15: 39279.836 | AC15: =AB15*(1+AA15) -> 40910.558 | AD15: =AC15+AD14 -> 321828.36
A16: 3/31/2002 | B16: 2.6 | D16: 73 | E16: 0.044829112 | F16: 39279.836 | G16: 41040.717 | J16: 9 | K16: 1041364 | M16: Best scenario | N16: 1164278.3 | S16: 73 | T16: =_xlfn.NORM.INV(RAND(),'Inflation rate & expenditure1'!E29,'Inflation rate & expenditure1'!E30) -> 0.034749055 | U16: 39279.836 | V16: =U16*(1+T16) -> 40644.774 | W16: =V16+W15 -> 364032.87 | Z16: 68 | AA16: =_xlfn.NORM.INV(RAND(),'Inflation rate & expenditure1'!$E$29,'Inflation rate & expenditure1'!$E$30) -> 0.025652986 | AB16: 39279.836 | AC16: =AB16*(1+AA16) -> 40287.481 | AD16: =AC16+AD15 -> 362115.84
A17: 6/30/2002 | B17: 2.8 | D17: 74 | E17: 0.025374325 | F17: 39279.836 | G17: 40276.536 | J17: 10 | K17: 1039321.6 | M17: neutral scenario | N17: 1175187.8 | S17: 74 | T17: =_xlfn.NORM.INV(RAND(),'Inflation rate & expenditure1'!E29,'Inflation rate & expenditure1'!E30) -> 0.050592503 | U17: 39279.836 | V17: =U17*(1+T17) -> 41267.102 | W17: =V17+W16 -> 405299.97 | Z17: 69 | AA17: =_xlfn.NORM.INV(RAND(),'Inflation rate & expenditure1'!$E$29,'Inflation rate & expenditure1'!$E$30) -> 0.014879102 | AB17: 39279.836 | AC17: =AB17*(1+AA17) -> 39864.285 | AD17: =AC17+AD16 -> 401980.13
A18: 9/30/2002 | B18: 2.6 | D18: 75 | E18: 0.024976512 | F18: 39279.836 | G18: 40260.91 | J18: 11 | K18: 1048771.9 | M18: sd | N18: 2957.5255 | S18: 75 | T18: =_xlfn.NORM.INV(RAND(),'Inflation rate & expenditure1'!E29,'Inflation rate & expenditure1'!E30) -> 0.014030693 | U18: 39279.836 | V18: =U18*(1+T18) -> 39830.96 | W18: =V18+W17 -> 445130.93 | Z18: 70 | AA18: =_xlfn.NORM.INV(RAND(),'Inflation rate & expenditure1'!$E$29,'Inflation rate & expenditure1'!$E$30) -> 0.039752556 | AB18: 39279.836 | AC18: =AB18*(1+AA18) -> 40841.31 | AD18: =AC18+AD17 -> 442821.44
A19: 12/31/2002 | B19: 2.7 | D19: 76 | E19: 0.019162966 | F19: 39279.836 | G19: 40032.555 | J19: 12 | K19: 1045034 | M19: count | N19: 5000 | S19: 76 | T19: =_xlfn.NORM.INV(RAND(),'Inflation rate & expenditure1'!E29,'Inflation rate & expenditure1'!E30) -> 0.029567577 | U19: 39279.836 | V19: =U19*(1+T19) -> 40441.246 | W19: =V19+W18 -> 485572.18 | Z19: 71 | AA19: =_xlfn.NORM.INV(RAND(),'Inflation rate & expenditure1'!$E$29,'Inflation rate & expenditure1'!$E$30) -> 0.072584581 | AB19: 39279.836 | AC19: =AB19*(1+AA19) -> 42130.947 | AD19: =AC19+AD18 -> 484952.38
A20: 3/31/2003 | B20: 2.5 | D20: 77 | E20: 0.017357163 | F20: 39279.836 | G20: 39961.623 | J20: 13 | K20: 1046039.6 | S20: 77 | T20: =_xlfn.NORM.INV(RAND(),'Inflation rate & expenditure1'!E29,'Inflation rate & expenditure1'!E30) -> 0.015844581 | U20: 39279.836 | V20: =U20*(1+T20) -> 39902.209 | W20: =V20+W19 -> 525474.39 | Z20: 72 | AA20: =_xlfn.NORM.INV(RAND(),'Inflation rate & expenditure1'!$E$29,'Inflation rate & expenditure1'!$E$30) -> 0.037997109 | AB20: 39279.836 | AC20: =AB20*(1+AA20) -> 40772.357 | AD20: =AC20+AD19 -> 525724.74
A21: 6/30/2003 | B21: 1.5 | D21: 78 | E21: 0.023034767 | F21: 39279.836 | G21: 40184.638 | J21: 14 | K21: 1041847.7 | M21: 95% CI | N21: =N17-_xlfn.CONFIDENCE.T(0.05,N18,N12) -> 1175105.8 | S21: 78 | T21: =_xlfn.NORM.INV(RAND(),'Inflation rate & expenditure1'!E29,'Inflation rate & expenditure1'!E30) -> -0.0043107093 | U21: 39279.836 | V21: =U21*(1+T21) -> 39110.512 | W21: =V21+W20 -> 564584.9 | Z21: 73 | AA21: =_xlfn.NORM.INV(RAND(),'Inflation rate & expenditure1'!$E$29,'Inflation rate & expenditure1'!$E$30) -> 0.015057965 | AB21: 39279.836 | AC21: =AB21*(1+AA21) -> 39871.311 | AD21: =AC21+AD20 -> 565596.05
A22: 9/30/2003 | B22: 1.5 | D22: 79 | E22: 0.0017156173 | F22: 39279.836 | G22: 39347.226 | J22: 15 | K22: 1041759.4 | N22: =N17+_xlfn.CONFIDENCE.T(0.05,N18,N19) -> 1175269.8 | S22: 79 | T22: =_xlfn.NORM.INV(RAND(),'Inflation rate & expenditure1'!E29,'Inflation rate & expenditure1'!E30) -> 0.028305617 | U22: 39279.836 | V22: =U22*(1+T22) -> 40391.676 | W22: =V22+W21 -> 604976.57 | Z22: 74 | AA22: =_xlfn.NORM.INV(RAND(),'Inflation rate & expenditure1'!$E$29,'Inflation rate & expenditure1'!$E$30) -> -0.0072830945 | AB22: 39279.836 | AC22: =AB22*(1+AA22) -> 38993.758 | AD22: =AC22+AD21 -> 604589.81
A23: 12/31/2003 | B23: 1.6 | D23: 80 | E23: 0.002667952 | F23: 39279.836 | G23: 39384.633 | J23: 16 | K23: 1047367.7 | S23: 80 | T23: =_xlfn.NORM.INV(RAND(),'Inflation rate & expenditure1'!E29,'Inflation rate & expenditure1'!E30) -> 0.016626593 | U23: 39279.836 | V23: =U23*(1+T23) -> 39932.926 | W23: =V23+W22 -> 644909.5 | Z23: 75 | AA23: =_xlfn.NORM.INV(RAND(),'Inflation rate & expenditure1'!$E$29,'Inflation rate & expenditure1'!$E$30) -> 0.0054999067 | AB23: 39279.836 | AC23: =AB23*(1+AA23) -> 39495.872 | AD23: =AC23+AD22 -> 644085.68
A24: 3/31/2004 | B24: 1.5 | D24: 81 | E24: 0.032870432 | F24: 39279.836 | G24: 40570.982 | J24: 17 | K24: 1043977.7 | S24: 81 | T24: =_xlfn.NORM.INV(RAND(),'Inflation rate & expenditure1'!E29,'Inflation rate & expenditure1'!E30) -> 0.034401267 | U24: 39279.836 | V24: =U24*(1+T24) -> 40631.113 | W24: =V24+W23 -> 685540.61 | Z24: 76 | AA24: =_xlfn.NORM.INV(RAND(),'Inflation rate & expenditure1'!$E$29,'Inflation rate & expenditure1'!$E$30) -> 0.044097014 | AB24: 39279.836 | AC24: =AB24*(1+AA24) -> 41011.96 | AD24: =AC24+AD23 -> 685097.64
A25: 6/30/2004 | B25: 2.4 | D25: 82 | E25: 0.013467928 | F25: 39279.836 | G25: 39808.854 | J25: 18 | K25: 1043583.3 | M25: add: 60/63 retirement age expenditure | S25: 82 | T25: =_xlfn.NORM.INV(RAND(),'Inflation rate & expenditure1'!E29,'Inflation rate & expenditure1'!E30) -> 0.01166179 | U25: 39279.836 | V25: =U25*(1+T25) -> 39737.91 | W25: =V25+W24 -> 725278.52 | Z25: 77 | AA25: =_xlfn.NORM.INV(RAND(),'Inflation rate & expenditure1'!$E$29,'Inflation rate & expenditure1'!$E$30) -> 0.015379174 | AB25: 39279.836 | AC25: =AB25*(1+AA25) -> 39883.928 | AD25: =AC25+AD24 -> 724981.57
A26: 9/30/2004 | B26: 2.5 | D26: 83 | E26: 0.042635392 | F26: 39279.836 | G26: 40954.548 | J26: 19 | K26: 1045935.5 | S26: 83 | T26: =_xlfn.NORM.INV(RAND(),'Inflation rate & expenditure1'!E29,'Inflation rate & expenditure1'!E30) -> 0.032212287 | U26: 39279.836 | V26: =U26*(1+T26) -> 40545.13 | W26: =V26+W25 -> 765823.65 | Z26: 78 | AA26: =_xlfn.NORM.INV(RAND(),'Inflation rate & expenditure1'!$E$29,'Inflation rate & expenditure1'!$E$30) -> 0.014874265 | AB26: 39279.836 | AC26: =AB26*(1+AA26) -> 39864.095 | AD26: =AC26+AD25 -> 764845.66
A27: 12/31/2004 | B27: 2.7 | D27: 84 | E27: 0.013777679 | F27: 39279.836 | G27: 39821.021 | J27: 20 | K27: 1042733.3 | S27: 84 | T27: =_xlfn.NORM.INV(RAND(),'Inflation rate & expenditure1'!E29,'Inflation rate & expenditure1'!E30) -> -0.014631154 | U27: 39279.836 | V27: =U27*(1+T27) -> 38705.127 | W27: =V27+W26 -> 804528.78 | Z27: 79 | AA27: =_xlfn.NORM.INV(RAND(),'Inflation rate & expenditure1'!$E$29,'Inflation rate & expenditure1'!$E$30) -> 0.024392723 | AB27: 39279.836 | AC27: =AB27*(1+AA27) -> 40237.979 | AD27: =AC27+AD26 -> 805083.64
A28: 3/31/2005 | B28: 2.8 | E28: Emergency Fund(Total) | F28: 39279.836 | J28: 21 | K28: 1048038.3 | T28: Emergency Fund(Total) | U28: 39279.836 | Z28: 80 | AA28: =_xlfn.NORM.INV(RAND(),'Inflation rate & expenditure1'!$E$29,'Inflation rate & expenditure1'!$E$30) -> 0.035402836 | AB28: 39279.836
A29: 6/30/2005 | B29: 2.8 | E29: Children | F29: 130172 | J29: 22 | K29: 1045011 | T29: Children | U29: 130172 | Z29: 81 | AA29: =_xlfn.NORM.INV(RAND(),'Inflation rate & expenditure1'!$E$29,'Inflation rate & expenditure1'!$E$30) -> 0.033256051 | AB29: 39279.836
A30: 9/30/2005 | B30: 3.4 | E30: Traveling expenditure per year | F30: 10000 | J30: 23 | K30: 1042243.6 | T30: Traveling expenditure per year | U30: 10000 | Z30: 82 | AA30: =_xlfn.NORM.INV(RAND(),'Inflation rate & expenditure1'!$E$29,'Inflation rate & expenditure1'!$E$30) -> 0.035704476 | AB30: 39279.836
A31: 12/31/2005 | B31: 3.2 | E31: Retirement period | F31: 20 | J31: 24 | K31: 1043477.4 | T31: Retirement period | U31: 20 | Z31: 83 | AA31: =_xlfn.NORM.INV(RAND(),'Inflation rate & expenditure1'!$E$29,'Inflation rate & expenditure1'!$E$30) -> 0.010855109 | AB31: 39279.836
A32: 3/31/2006 | B32: 3.3 | J32: 25 | K32: 1050000.1 | Z32: 84 | AA32: =_xlfn.NORM.INV(RAND(),'Inflation rate & expenditure1'!$E$29,'Inflation rate & expenditure1'!$E$30) -> 0.013588318 | AB32: 39279.836
A33: 6/30/2006 | B33: 4 | F33: 785596.73 | G33: 800341.93 | J33: 26 | K33: 1043390.3 | U33: =SUM(U8:U27) -> 785596.73 | V33: =SUM(V8:V27) -> 804528.78 | AA33: Emergency Fund(Total) | AB33: 39279.836
A34: 9/30/2006 | B34: 3.5 | F34: TOTAL expenditure | G34: 1169793.8 | J34: 27 | K34: 1044314.4 | U34: Total expenditure | V34: =V33+U28+(U30*U31) -> 1043808.6 | AA34: Children | AB34: 130172
A35: 12/31/2006 | B35: 2.6 | J35: 28 | K35: 1043633 | AA35: Traveling expenditure per year | AB35: 10000
A36: 3/31/2007 | B36: 2.5 | J36: 29 | K36: 1045758.5 | AA36: Retirement period | AB36: 20
A37: 6/30/2007 | B37: 2 | J37: 30 | K37: 1043029.3
A38: 9/30/2007 | B38: 1.8 | J38: 31 | K38: 1045011.9 | AB38: =SUM(AB13:AB32) -> 785596.73 | AC38: =SUM(AC13:AC32) -> 603830.48
A39: 12/31/2007 | B39: 3.2 | J39: 32 | K39: 1051136.3 | AB39: Total expenditure | AC39: =AC38+AB33+AB34+(AB35*AB36) -> 973282.32
A40: 3/31/2008 | B40: 3.4 | J40: 33 | K40: 1042026.1
A41: 6/30/2008 | B41: 4 | J41: 34 | K41: 1047963.5
A42: 9/30/2008 | B42: 5.1 | J42: 35 | K42: 1043749.3
A43: 12/31/2008 | B43: 3.4 | J43: 36 | K43: 1048943.1
A44: 3/31/2009 | B44: 3 | J44: 37 | K44: 1047452.5
A45: 6/30/2009 | B45: 1.9 | J45: 38 | K45: 1043175.7
A46: 9/30/2009 | B46: 1.7 | J46: 39 | K46: 1047359
A47: 12/31/2009 | B47: 2 | J47: 40 | K47: 1041783
A48: 3/31/2010 | B48: 2 | J48: 41 | K48: 1043788
A49: 6/30/2010 | B49: 1.7 | J49: 42 | K49: 1042195.3
A50: 9/30/2010 | B50: 1.5 | J50: 43 | K50: 1052408
A51: 12/31/2010 | B51: 4 | J51: 44 | K51: 1039538.8
... A108: 3/31/2025 | B108: 2.5 | J108: 101 | K108: 1038121.1
J109: 102 | K109: 1042198.9
J110: 103 | K110: 1045520.5
J111: 104 | K111: 1044221.5
J112: 105 | K112: 1046031.8
J113: 106 | K113: 1042284.2
J114: 107 | K114: 1045427.9
J115: 108 | K115: 1045358.7
J116: 109 | K116: 1044366.1
J117: 110 | K117: 1041530.2
J118: 111 | K118: 1046273.6
J119: 112 | K119: 1047672.3
J120: 113 | K120: 1045047.4
... J5007: 5000 | K5007: 1039470.3

Sheet Inflation rate & expenditure1
A1: Date | B1: CPI (Annual % change) | D1: annual inflation | J1: Best senario | K1: AGE | L1: Inflation rate | M1: Average annual expenditure | N1: Total expenditure | O1: NZ Super(no inflation) | P1: NZ Super(inflation) | S1: worst scenario | T1: AGE | U1: Inflation rate | V1: Average annaul expenditure | W1: Total expenditure | X1: Cumulative expenditure | Z1: neutral scenario | AA1: AGE | AB1: Inflation rate | AC1: Average annaul expenditure | AD1: Total expenture | AE1: Cumulative expenditure
A2: 3/31/2000 | B2: 1.5 | D2: 2000 | E2: =AVERAGE(B2:B5)/100 -> 0.02625 | K2: {=_xlfn.SEQUENCE(55,1,30)} -> 30 | L2: =IF(RAND()<($E$37/$E$35),$E$32+SQRT(RAND()*$E$35*$E$37),$E$31-SQRT((1-RAND())*$E$36*$E$35)) -> 0.032330136 | M2: 39279.836 | N2: =M2*(1+L2) -> 40549.759 | O2: ='Best scenario'!$S$27 -> 27997.84 | P2: =O2*(1+L2) -> 28903.014 | T2: {=_xlfn.SEQUENCE(55,1,30)} -> 30 | U2: =IF(RAND()<($E$37/$E$35),$E$32+SQRT(RAND()*$E$35*$E$37),$E$31-SQRT((1-RAND())*$E$36*$E$35)) -> 0.037339937 | V2: 39279.836 | W2: =V2*(1+U2) -> 40746.543 | X2: =W2 -> 40746.543 | AA2: {=_xlfn.SEQUENCE(55,1,30)} -> 30 | AB2: =IF(RAND()<($E$37/$E$35),$E$32+SQRT(RAND()*$E$35*$E$37),$E$31-SQRT((1-RAND())*$E$36*$E$35)) -> 0.032765164 | AC2: 39279.836 | AD2: =AC2*(1+AB2) -> 40566.847 | AE2: =AD2 -> 40566.847
A3: 6/30/2000 | B3: 2 | D3: 2001 | E3: =AVERAGE(B6:B9)/100 -> 0.02625 | K3: 31 | L3: =IF(RAND()<($E$37/$E$35),$E$32+SQRT(RAND()*$E$35*$E$37),$E$31-SQRT((1-RAND())*$E$36*$E$35)) -> 0.03091307 | M3: 39279.836 | N3: =N2*(1+L3) -> 41803.276 | O3: ='Best scenario'!$S$27 -> 27997.84 | P3: =P2*(1+L3) -> 29796.495 | T3: 31 | U3: =IF(RAND()<($E$37/$E$35),$E$32+SQRT(RAND()*$E$35*$E$37),$E$31-SQRT((1-RAND())*$E$36*$E$35)) -> 0.025421482 | V3: 39279.836 | W3: =W2*(1+U3) -> 41782.381 | X3: =W3+X2 -> 82528.924 | AA3: 31 | AB3: =IF(RAND()<($E$37/$E$35),$E$32+SQRT(RAND()*$E$35*$E$37),$E$31-SQRT((1-RAND())*$E$36*$E$35)) -> 0.023494486 | AC3: 39279.836 | AD3: =AD2*(1+AB3) -> 41519.944 | AE3: =AE2+AD3 -> 82086.791
A4: 9/30/2000 | B4: 3 | D4: 2002 | E4: =AVERAGE(B10:B13)/100 -> 0.02675 | K4: 32 | L4: =IF(RAND()<($E$37/$E$35),$E$32+SQRT(RAND()*$E$35*$E$37),$E$31-SQRT((1-RAND())*$E$36*$E$35)) -> 0.021212388 | M4: 39279.836 | N4: =N3*(1+L4) -> 42690.024 | O4: ='Best scenario'!$S$27 -> 27997.84 | P4: =P3*(1+L4) -> 30428.55 | T4: 32 | U4: =IF(RAND()<($E$37/$E$35),$E$32+SQRT(RAND()*$E$35*$E$37),$E$31-SQRT((1-RAND())*$E$36*$E$35)) -> 0.018039567 | V4: 39279.836 | W4: =W3*(1+U4) -> 42536.117 | X4: =W4+X3 -> 125065.04 | AA4: 32 | AB4: =IF(RAND()<($E$37/$E$35),$E$32+SQRT(RAND()*$E$35*$E$37),$E$31-SQRT((1-RAND())*$E$36*$E$35)) -> 0.016459943 | AC4: 39279.836 | AD4: =AD3*(1+AB4) -> 42203.36 | AE4: =AE3+AD4 -> 124290.15
A5: 12/31/2000 | B5: 4 | D5: 2003 | E5: =AVERAGE(B14:B17)/100 -> 0.01775 | K5: 33 | L5: =IF(RAND()<($E$37/$E$35),$E$32+SQRT(RAND()*$E$35*$E$37),$E$31-SQRT((1-RAND())*$E$36*$E$35)) -> 0.019337635 | M5: 39279.836 | N5: =N4*(1+L5) -> 43515.548 | O5: ='Best scenario'!$S$27 -> 27997.84 | P5: =P4*(1+L5) -> 31016.966 | T5: 33 | U5: =IF(RAND()<($E$37/$E$35),$E$32+SQRT(RAND()*$E$35*$E$37),$E$31-SQRT((1-RAND())*$E$36*$E$35)) -> 0.023903456 | V5: 39279.836 | W5: =W4*(1+U5) -> 43552.877 | X5: =W5+X4 -> 168617.92 | AA5: 33 | AB5: =IF(RAND()<($E$37/$E$35),$E$32+SQRT(RAND()*$E$35*$E$37),$E$31-SQRT((1-RAND())*$E$36*$E$35)) -> 0.031049141 | AC5: 39279.836 | AD5: =AD4*(1+AB5) -> 43513.738 | AE5: =AE4+AD5 -> 167803.89
A6: 3/31/2001 | B6: 3.1 | D6: 2004 | E6: =AVERAGE(B18:B21)/100 -> 0.02275 | K6: 34 | L6: =IF(RAND()<($E$37/$E$35),$E$32+SQRT(RAND()*$E$35*$E$37),$E$31-SQRT((1-RAND())*$E$36*$E$35)) -> 0.012516047 | M6: 39279.836 | N6: =N5*(1+L6) -> 44060.19 | O6: ='Best scenario'!$S$27 -> 27997.84 | P6: =P5*(1+L6) -> 31405.176 | T6: 34 | U6: =IF(RAND()<($E$37/$E$35),$E$32+SQRT(RAND()*$E$35*$E$37),$E$31-SQRT((1-RAND())*$E$36*$E$35)) -> 0.033562119 | V6: 39279.836 | W6: =W5*(1+U6) -> 45014.604 | X6: =W6+X5 -> 213632.52 | AA6: 34 | AB6: =IF(RAND()<($E$37/$E$35),$E$32+SQRT(RAND()*$E$35*$E$37),$E$31-SQRT((1-RAND())*$E$36*$E$35)) -> 0.037787648 | AC6: 39279.836 | AD6: =AD5*(1+AB6) -> 45158.02 | AE6: =AE5+AD6 -> 212961.91
A7: 6/30/2001 | B7: 3.2 | D7: 2005 | E7: =AVERAGE(B22:B25)/100 -> 0.0305 | K7: 35 | L7: =IF(RAND()<($E$37/$E$35),$E$32+SQRT(RAND()*$E$35*$E$37),$E$31-SQRT((1-RAND())*$E$36*$E$35)) -> 0.027013646 | M7: 39279.836 | N7: =N6*(1+L7) -> 45250.417 | O7: ='Best scenario'!$S$27 -> 27997.84 | P7: =P6*(1+L7) -> 32253.544 | T7: 35 | U7: =IF(RAND()<($E$37/$E$35),$E$32+SQRT(RAND()*$E$35*$E$37),$E$31-SQRT((1-RAND())*$E$36*$E$35)) -> 0.02834446 | V7: 39279.836 | W7: =W6*(1+U7) -> 46290.518 | X7: =W7+X6 -> 259923.04 | AA7: 35 | AB7: =IF(RAND()<($E$37/$E$35),$E$32+SQRT(RAND()*$E$35*$E$37),$E$31-SQRT((1-RAND())*$E$36*$E$35)) -> 0.03982426 | AC7: 39279.836 | AD7: =AD6*(1+AB7) -> 46956.404 | AE7: =AE6+AD7 -> 259918.31
A8: 9/30/2001 | B8: 2.4 | D8: 2006 | E8: =AVERAGE(B26:B29)/100 -> 0.0335 | K8: 36 | L8: =IF(RAND()<($E$37/$E$35),$E$32+SQRT(RAND()*$E$35*$E$37),$E$31-SQRT((1-RAND())*$E$36*$E$35)) -> 0.016563629 | M8: 39279.836 | N8: =N7*(1+L8) -> 45999.928 | O8: ='Best scenario'!$S$27 -> 27997.84 | P8: =P7*(1+L8) -> 32787.78 | T8: 36 | U8: =IF(RAND()<($E$37/$E$35),$E$32+SQRT(RAND()*$E$35*$E$37),$E$31-SQRT((1-RAND())*$E$36*$E$35)) -> 0.021518651 | V8: 39279.836 | W8: =W7*(1+U8) -> 47286.628 | X8: =W8+X7 -> 307209.67 | AA8: 36 | AB8: =IF(RAND()<($E$37/$E$35),$E$32+SQRT(RAND()*$E$35*$E$37),$E$31-SQRT((1-RAND())*$E$36*$E$35)) -> 0.022977319 | AC8: 39279.836 | AD8: =AD7*(1+AB8) -> 48035.337 | AE8: =AE7+AD8 -> 307953.65
A9: 12/31/2001 | B9: 1.8 | D9: 2007 | E9: =AVERAGE(B30:B33)/100 -> 0.02375 | K9: 37 | L9: =IF(RAND()<($E$37/$E$35),$E$32+SQRT(RAND()*$E$35*$E$37),$E$31-SQRT((1-RAND())*$E$36*$E$35)) -> 0.035936845 | M9: 39279.836 | N9: =N8*(1+L9) -> 47653.02 | O9: ='Best scenario'!$S$27 -> 27997.84 | P9: =P8*(1+L9) -> 33966.069 | T9: 37 | U9: =IF(RAND()<($E$37/$E$35),$E$32+SQRT(RAND()*$E$35*$E$37),$E$31-SQRT((1-RAND())*$E$36*$E$35)) -> 0.031940461 | V9: 39279.836 | W9: =W8*(1+U9) -> 48796.984 | X9: =W9+X8 -> 356006.65 | AA9: 37 | AB9: =IF(RAND()<($E$37/$E$35),$E$32+SQRT(RAND()*$E$35*$E$37),$E$31-SQRT((1-RAND())*$E$36*$E$35)) -> 0.016405231 | AC9: 39279.836 | AD9: =AD8*(1+AB9) -> 48823.367 | AE9: =AE8+AD9 -> 356777.02
A10: 3/31/2002 | B10: 2.6 | D10: 2008 | E10: =AVERAGE(B34:B37)/100 -> 0.03975 | K10: 38 | L10: =IF(RAND()<($E$37/$E$35),$E$32+SQRT(RAND()*$E$35*$E$37),$E$31-SQRT((1-RAND())*$E$36*$E$35)) -> 0.041293297 | M10: 39279.836 | N10: =N9*(1+L10) -> 49620.771 | O10: ='Best scenario'!$S$27 -> 27997.84 | P10: =P9*(1+L10) -> 35368.64 | T10: 38 | U10: =IF(RAND()<($E$37/$E$35),$E$32+SQRT(RAND()*$E$35*$E$37),$E$31-SQRT((1-RAND())*$E$36*$E$35)) -> 0.035737763 | V10: 39279.836 | W10: =W9*(1+U10) -> 50540.879 | X10: =W10+X9 -> 406547.53 | AA10: 38 | AB10: =IF(RAND()<($E$37/$E$35),$E$32+SQRT(RAND()*$E$35*$E$37),$E$31-SQRT((1-RAND())*$E$36*$E$35)) -> 0.028570857 | AC10: 39279.836 | AD10: =AD9*(1+AB10) -> 50218.293 | AE10: =AE9+AD10 -> 406995.31
A11: 6/30/2002 | B11: 2.8 | D11: 2009 | E11: =AVERAGE(B38:B41)/100 -> 0.0215 | K11: 39 | L11: =IF(RAND()<($E$37/$E$35),$E$32+SQRT(RAND()*$E$35*$E$37),$E$31-SQRT((1-RAND())*$E$36*$E$35)) -> 0.026513006 | M11: 39279.836 | N11: =N10*(1+L11) -> 50936.366 | O11: ='Best scenario'!$S$27 -> 27997.84 | P11: =P10*(1+L11) -> 36306.369 | T11: 39 | U11: =IF(RAND()<($E$37/$E$35),$E$32+SQRT(RAND()*$E$35*$E$37),$E$31-SQRT((1-RAND())*$E$36*$E$35)) -> 0.020948017 | V11: 39279.836 | W11: =W10*(1+U11) -> 51599.611 | X11: =W11+X10 -> 458147.14 | AA11: 39 | AB11: =IF(RAND()<($E$37/$E$35),$E$32+SQRT(RAND()*$E$35*$E$37),$E$31-SQRT((1-RAND())*$E$36*$E$35)) -> 0.041162755 | AC11: 39279.836 | AD11: =AD10*(1+AB11) -> 52285.416 | AE11: =AE10+AD11 -> 459280.73
A12: 9/30/2002 | B12: 2.6 | D12: 2010 | E12: =AVERAGE(B42:B45)/100 -> 0.023 | K12: 40 | L12: =IF(RAND()<($E$37/$E$35),$E$32+SQRT(RAND()*$E$35*$E$37),$E$31-SQRT((1-RAND())*$E$36*$E$35)) -> 0.036501153 | M12: 39279.836 | N12: =N11*(1+L12) -> 52795.602 | O12: ='Best scenario'!$S$27 -> 27997.84 | P12: =P11*(1+L12) -> 37631.593 | T12: 40 | U12: =IF(RAND()<($E$37/$E$35),$E$32+SQRT(RAND()*$E$35*$E$37),$E$31-SQRT((1-RAND())*$E$36*$E$35)) -> 0.034286008 | V12: 39279.836 | W12: =W11*(1+U12) -> 53368.755 | X12: =W12+X11 -> 511515.9 | AA12: 40 | AB12: =IF(RAND()<($E$37/$E$35),$E$32+SQRT(RAND()*$E$35*$E$37),$E$31-SQRT((1-RAND())*$E$36*$E$35)) -> 0.04767391 | AC12: 39279.836 | AD12: =AD11*(1+AB12) -> 54778.066 | AE12: =AE11+AD12 -> 514058.79
A13: 12/31/2002 | B13: 2.7 | D13: 2011 | E13: =AVERAGE(B46:B49)/100 -> 0.0405 | K13: 41 | L13: =IF(RAND()<($E$37/$E$35),$E$32+SQRT(RAND()*$E$35*$E$37),$E$31-SQRT((1-RAND())*$E$36*$E$35)) -> 0.019485195 | M13: 39279.836 | N13: =N12*(1+L13) -> 53824.335 | O13: ='Best scenario'!$S$27 -> 27997.84 | P13: =P12*(1+L13) -> 38364.852 | T13: 41 | U13: =IF(RAND()<($E$37/$E$35),$E$32+SQRT(RAND()*$E$35*$E$37),$E$31-SQRT((1-RAND())*$E$36*$E$35)) -> 0.035006285 | V13: 39279.836 | W13: =W12*(1+U13) -> 55236.997 | X13: =W13+X12 -> 566752.89 | AA13: 41 | AB13: =IF(RAND()<($E$37/$E$35),$E$32+SQRT(RAND()*$E$35*$E$37),$E$31-SQRT((1-RAND())*$E$36*$E$35)) -> 0.024530152 | AC13: 39279.836 | AD13: =AD12*(1+AB13) -> 56121.781 | AE13: =AE12+AD13 -> 570180.57
A14: 3/31/2003 | B14: 2.5 | D14: 2012 | E14: =AVERAGE(B50:B53)/100 -> 0.01075 | K14: 42 | L14: =IF(RAND()<($E$37/$E$35),$E$32+SQRT(RAND()*$E$35*$E$37),$E$31-SQRT((1-RAND())*$E$36*$E$35)) -> 0.026906781 | M14: 39279.836 | N14: =N13*(1+L14) -> 55272.575 | O14: ='Best scenario'!$S$27 -> 27997.84 | P14: =P13*(1+L14) -> 39397.127 | T14: 42 | U14: =IF(RAND()<($E$37/$E$35),$E$32+SQRT(RAND()*$E$35*$E$37),$E$31-SQRT((1-RAND())*$E$36*$E$35)) -> 0.025708973 | V14: 39279.836 | W14: =W13*(1+U14) -> 56657.084 | X14: =W14+X13 -> 623409.98 | AA14: 42 | AB14: =IF(RAND()<($E$37/$E$35),$E$32+SQRT(RAND()*$E$35*$E$37),$E$31-SQRT((1-RAND())*$E$36*$E$35)) -> 0.029674987 | AC14: 39279.836 | AD14: =AD13*(1+AB14) -> 57787.194 | AE14: =AE13+AD14 -> 627967.77
A15: 6/30/2003 | B15: 1.5 | D15: 2013 | E15: =AVERAGE(B54:B57)/100 -> 0.0115 | K15: 43 | L15: =IF(RAND()<($E$37/$E$35),$E$32+SQRT(RAND()*$E$35*$E$37),$E$31-SQRT((1-RAND())*$E$36*$E$35)) -> 0.040375452 | M15: 39279.836 | N15: =N14*(1+L15) -> 57504.23 | O15: ='Best scenario'!$S$27 -> 27997.84 | P15: =P14*(1+L15) -> 40987.804 | T15: 43 | U15: =IF(RAND()<($E$37/$E$35),$E$32+SQRT(RAND()*$E$35*$E$37),$E$31-SQRT((1-RAND())*$E$36*$E$35)) -> 0.039585093 | V15: 39279.836 | W15: =W14*(1+U15) -> 58899.86 | X15: =W15+X14 -> 682309.84 | AA15: 43 | AB15: =IF(RAND()<($E$37/$E$35),$E$32+SQRT(RAND()*$E$35*$E$37),$E$31-SQRT((1-RAND())*$E$36*$E$35)) -> 0.032639923 | AC15: 39279.836 | AD15: =AD14*(1+AB15) -> 59673.363 | AE15: =AE14+AD15 -> 687641.13
A16: 9/30/2003 | B16: 1.5 | D16: 2014 | E16: =AVERAGE(B58:B61)/100 -> 0.01225 | K16: 44 | L16: =IF(RAND()<($E$37/$E$35),$E$32+SQRT(RAND()*$E$35*$E$37),$E$31-SQRT((1-RAND())*$E$36*$E$35)) -> 0.041170415 | M16: 39279.836 | N16: =N15*(1+L16) -> 59871.703 | O16: ='Best scenario'!$S$27 -> 27997.84 | P16: =P15*(1+L16) -> 42675.289 | T16: 44 | U16: =IF(RAND()<($E$37/$E$35),$E$32+SQRT(RAND()*$E$35*$E$37),$E$31-SQRT((1-RAND())*$E$36*$E$35)) -> 0.034901988 | V16: 39279.836 | W16: =W15*(1+U16) -> 60955.582 | X16: =W16+X15 -> 743265.42 | AA16: 44 | AB16: =IF(RAND()<($E$37/$E$35),$E$32+SQRT(RAND()*$E$35*$E$37),$E$31-SQRT((1-RAND())*$E$36*$E$35)) -> 0.04136784 | AC16: 39279.836 | AD16: =AD15*(1+AB16) -> 62141.922 | AE16: =AE15+AD16 -> 749783.05
A17: 12/31/2003 | B17: 1.6 | D17: 2015 | E17: =AVERAGE(B62:B65)/100 -> 0.003 | K17: 45 | L17: =IF(RAND()<($E$37/$E$35),$E$32+SQRT(RAND()*$E$35*$E$37),$E$31-SQRT((1-RAND())*$E$36*$E$35)) -> 0.017427035 | M17: 39279.836 | N17: =N16*(1+L17) -> 60915.089 | O17: ='Best scenario'!$S$27 -> 27997.84 | P17: =P16*(1+L17) -> 43418.992 | T17: 45 | U17: =IF(RAND()<($E$37/$E$35),$E$32+SQRT(RAND()*$E$35*$E$37),$E$31-SQRT((1-RAND())*$E$36*$E$35)) -> 0.026736796 | V17: 39279.836 | W17: =W16*(1+U17) -> 62585.339 | X17: =W17+X16 -> 805850.76 | AA17: 45 | AB17: =IF(RAND()<($E$37/$E$35),$E$32+SQRT(RAND()*$E$35*$E$37),$E$31-SQRT((1-RAND())*$E$36*$E$35)) -> 0.020350574 | AC17: 39279.836 | AD17: =AD16*(1+AB17) -> 63406.545 | AE17: =AE16+AD17 -> 813189.6
A18: 3/31/2004 | B18: 1.5 | D18: 2016 | E18: =AVERAGE(B66:B69)/100 -> 0.00625 | K18: 46 | L18: =IF(RAND()<($E$37/$E$35),$E$32+SQRT(RAND()*$E$35*$E$37),$E$31-SQRT((1-RAND())*$E$36*$E$35)) -> 0.03366844 | M18: 39279.836 | N18: =N17*(1+L18) -> 62966.005 | O18: ='Best scenario'!$S$27 -> 27997.84 | P18: =P17*(1+L18) -> 44880.842 | T18: 46 | U18: =IF(RAND()<($E$37/$E$35),$E$32+SQRT(RAND()*$E$35*$E$37),$E$31-SQRT((1-RAND())*$E$36*$E$35)) -> 0.034945202 | V18: 39279.836 | W18: =W17*(1+U18) -> 64772.396 | X18: =W18+X17 -> 870623.15 | AA18: 46 | AB18: =IF(RAND()<($E$37/$E$35),$E$32+SQRT(RAND()*$E$35*$E$37),$E$31-SQRT((1-RAND())*$E$36*$E$35)) -> 0.019776699 | AC18: 39279.836 | AD18: =AD17*(1+AB18) -> 64660.517 | AE18: =AE17+AD18 -> 877850.11
A19: 6/30/2004 | B19: 2.4 | D19: 2017 | E19: =AVERAGE(B70:B73)/100 -> 0.0185 | K19: 47 | L19: =IF(RAND()<($E$37/$E$35),$E$32+SQRT(RAND()*$E$35*$E$37),$E$31-SQRT((1-RAND())*$E$36*$E$35)) -> 0.021582242 | M19: 39279.836 | N19: =N18*(1+L19) -> 64324.953 | O19: ='Best scenario'!$S$27 -> 27997.84 | P19: =P18*(1+L19) -> 45849.471 | T19: 47 | U19: =IF(RAND()<($E$37/$E$35),$E$32+SQRT(RAND()*$E$35*$E$37),$E$31-SQRT((1-RAND())*$E$36*$E$35)) -> 0.028307891 | V19: 39279.836 | W19: =W18*(1+U19) -> 66605.966 | X19: =W19+X18 -> 937229.12 | AA19: 47 | AB19: =IF(RAND()<($E$37/$E$35),$E$32+SQRT(RAND()*$E$35*$E$37),$E$31-SQRT((1-RAND())*$E$36*$E$35)) -> 0.037330082 | AC19: 39279.836 | AD19: =AD18*(1+AB19) -> 67074.3 | AE19: =AE18+AD19 -> 944924.41
A20: 9/30/2004 | B20: 2.5 | D20: 2018 | E20: =AVERAGE(B74:B77)/100 -> 0.016 | K20: 48 | L20: =IF(RAND()<($E$37/$E$35),$E$32+SQRT(RAND()*$E$35*$E$37),$E$31-SQRT((1-RAND())*$E$36*$E$35)) -> 0.034790337 | M20: 39279.836 | N20: =N19*(1+L20) -> 66562.839 | O20: ='Best scenario'!$S$27 -> 27997.84 | P20: =P19*(1+L20) -> 47444.59 | T20: 48 | U20: =IF(RAND()<($E$37/$E$35),$E$32+SQRT(RAND()*$E$35*$E$37),$E$31-SQRT((1-RAND())*$E$36*$E$35)) -> 0.037341082 | V20: 39279.836 | W20: =W19*(1+U20) -> 69093.105 | X20: =W20+X19 -> 1006322.2 | AA20: 48 | AB20: =IF(RAND()<($E$37/$E$35),$E$32+SQRT(RAND()*$E$35*$E$37),$E$31-SQRT((1-RAND())*$E$36*$E$35)) -> 0.045077953 | AC20: 39279.836 | AD20: =AD19*(1+AB20) -> 70097.872 | AE20: =AE19+AD20 -> 1015022.3
A21: 12/31/2004 | B21: 2.7 | D21: 2019 | E21: =AVERAGE(B78:B81)/100 -> 0.0165 | K21: 49 | L21: =IF(RAND()<($E$37/$E$35),$E$32+SQRT(RAND()*$E$35*$E$37),$E$31-SQRT((1-RAND())*$E$36*$E$35)) -> 0.033607699 | M21: 39279.836 | N21: =N20*(1+L21) -> 68799.863 | O21: ='Best scenario'!$S$27 -> 27997.84 | P21: =P20*(1+L21) -> 49039.093 | T21: 49 | U21: =IF(RAND()<($E$37/$E$35),$E$32+SQRT(RAND()*$E$35*$E$37),$E$31-SQRT((1-RAND())*$E$36*$E$35)) -> 0.03325446 | V21: 39279.836 | W21: =W20*(1+U21) -> 71390.759 | X21: =W21+X20 -> 1077713 | AA21: 49 | AB21: =IF(RAND()<($E$37/$E$35),$E$32+SQRT(RAND()*$E$35*$E$37),$E$31-SQRT((1-RAND())*$E$36*$E$35)) -> 0.036497304 | AC21: 39279.836 | AD21: =AD20*(1+AB21) -> 72656.255 | AE21: =AE20+AD21 -> 1087678.5
A22: 3/31/2005 | B22: 2.8 | D22: 2020 | E22: =AVERAGE(B82:B85)/100 -> 0.017 | K22: 50 | L22: =IF(RAND()<($E$37/$E$35),$E$32+SQRT(RAND()*$E$35*$E$37),$E$31-SQRT((1-RAND())*$E$36*$E$35)) -> 0.015525863 | M22: 39279.836 | N22: =N21*(1+L22) -> 69868.041 | O22: ='Best scenario'!$S$27 -> 27997.84 | P22: =P21*(1+L22) -> 49800.468 | T22: 50 | U22: =IF(RAND()<($E$37/$E$35),$E$32+SQRT(RAND()*$E$35*$E$37),$E$31-SQRT((1-RAND())*$E$36*$E$35)) -> 0.030491369 | V22: 39279.836 | W22: =W21*(1+U22) -> 73567.561 | X22: =W22+X21 -> 1151280.5 | AA22: 50 | AB22: =IF(RAND()<($E$37/$E$35),$E$32+SQRT(RAND()*$E$35*$E$37),$E$31-SQRT((1-RAND())*$E$36*$E$35)) -> 0.05470807 | AC22: 39279.836 | AD22: =AD21*(1+AB22) -> 76631.139 | AE22: =AE21+AD22 -> 1164309.7
A23: 6/30/2005 | B23: 2.8 | D23: 2021 | E23: =AVERAGE(B86:B89)/100 -> 0.039 | K23: 51 | L23: =IF(RAND()<($E$37/$E$35),$E$32+SQRT(RAND()*$E$35*$E$37),$E$31-SQRT((1-RAND())*$E$36*$E$35)) -> 0.020934226 | M23: 39279.836 | N23: =N22*(1+L23) -> 71330.674 | O23: ='Best scenario'!$S$27 -> 27997.84 | P23: =P22*(1+L23) -> 50843.002 | T23: 51 | U23: =IF(RAND()<($E$37/$E$35),$E$32+SQRT(RAND()*$E$35*$E$37),$E$31-SQRT((1-RAND())*$E$36*$E$35)) -> 0.036065726 | V23: 39279.836 | W23: =W22*(1+U23) -> 76220.828 | X23: =W23+X22 -> 1227501.4 | AA23: 51 | AB23: =IF(RAND()<($E$37/$E$35),$E$32+SQRT(RAND()*$E$35*$E$37),$E$31-SQRT((1-RAND())*$E$36*$E$35)) -> 0.033734455 | AC23: 39279.836 | AD23: =AD22*(1+AB23) -> 79216.249 | AE23: =AE22+AD23 -> 1243525.9
A24: 9/30/2005 | B24: 3.4 | D24: 2022 | E24: =AVERAGE(B90:B93)/100 -> 0.0715 | K24: 52 | L24: =IF(RAND()<($E$37/$E$35),$E$32+SQRT(RAND()*$E$35*$E$37),$E$31-SQRT((1-RAND())*$E$36*$E$35)) -> 0.015493415 | M24: 39279.836 | N24: =N23*(1+L24) -> 72435.83 | O24: ='Best scenario'!$S$27 -> 27997.84 | P24: =P23*(1+L24) -> 51630.734 | T24: 52 | U24: =IF(RAND()<($E$37/$E$35),$E$32+SQRT(RAND()*$E$35*$E$37),$E$31-SQRT((1-RAND())*$E$36*$E$35)) -> 0.026501742 | V24: 39279.836 | W24: =W23*(1+U24) -> 78240.813 | X24: =W24+X23 -> 1305742.2 | AA24: 52 | AB24: =IF(RAND()<($E$37/$E$35),$E$32+SQRT(RAND()*$E$35*$E$37),$E$31-SQRT((1-RAND())*$E$36*$E$35)) -> 0.03908637 | AC24: 39279.836 | AD24: =AD23*(1+AB24) -> 82312.524 | AE24: =AE23+AD24 -> 1325838.5
A25: 12/31/2005 | B25: 3.2 | D25: 2023 | E25: =AVERAGE(B94:B97)/100 -> 0.0575 | K25: 53 | L25: =IF(RAND()<($E$37/$E$35),$E$32+SQRT(RAND()*$E$35*$E$37),$E$31-SQRT((1-RAND())*$E$36*$E$35)) -> 0.039102249 | M25: 39279.836 | N25: =N24*(1+L25) -> 75268.234 | O25: ='Best scenario'!$S$27 -> 27997.84 | P25: =P24*(1+L25) -> 53649.611 | T25: 53 | U25: =IF(RAND()<($E$37/$E$35),$E$32+SQRT(RAND()*$E$35*$E$37),$E$31-SQRT((1-RAND())*$E$36*$E$35)) -> 0.030286273 | V25: 39279.836 | W25: =W24*(1+U25) -> 80610.436 | X25: =W25+X24 -> 1386352.6 | AA25: 53 | AB25: =IF(RAND()<($E$37/$E$35),$E$32+SQRT(RAND()*$E$35*$E$37),$E$31-SQRT((1-RAND())*$E$36*$E$35)) -> 0.046557727 | AC25: 39279.836 | AD25: =AD24*(1+AB25) -> 86144.808 | AE25: =AE24+AD25 -> 1411983.3
A26: 3/31/2006 | B26: 3.3 | D26: 2024 | E26: =AVERAGE(B98:B101)/100 -> 0.02925 | K26: 54 | L26: =IF(RAND()<($E$37/$E$35),$E$32+SQRT(RAND()*$E$35*$E$37),$E$31-SQRT((1-RAND())*$E$36*$E$35)) -> 0.016039489 | M26: 39279.836 | N26: =N25*(1+L26) -> 76475.498 | O26: ='Best scenario'!$S$27 -> 27997.84 | P26: =P25*(1+L26) -> 54510.124 | T26: 54 | U26: =IF(RAND()<($E$37/$E$35),$E$32+SQRT(RAND()*$E$35*$E$37),$E$31-SQRT((1-RAND())*$E$36*$E$35)) -> 0.036807577 | V26: 39279.836 | W26: =W25*(1+U26) -> 83577.51 | X26: =W26+X25 -> 1469930.1 | AA26: 54 | AB26: =IF(RAND()<($E$37/$E$35),$E$32+SQRT(RAND()*$E$35*$E$37),$E$31-SQRT((1-RAND())*$E$36*$E$35)) -> 0.052671538 | AC26: 39279.836 | AD26: =AD25*(1+AB26) -> 90682.188 | AE26: =AE25+AD26 -> 1502665.4
A27: 6/30/2006 | B27: 4 | D27: 2025 | E27: =2.5/100 -> 0.025 | K27: 55 | L27: =IF(RAND()<($E$37/$E$35),$E$32+SQRT(RAND()*$E$35*$E$37),$E$31-SQRT((1-RAND())*$E$36*$E$35)) -> 0.026132525 | M27: 39279.836 | N27: =N26*(1+L27) -> 78473.995 | O27: ='Best scenario'!$S$27 -> 27997.84 | P27: =P26*(1+L27) -> 55934.611 | T27: 55 | U27: =IF(RAND()<($E$37/$E$35),$E$32+SQRT(RAND()*$E$35*$E$37),$E$31-SQRT((1-RAND())*$E$36*$E$35)) -> 0.030609113 | V27: 39279.836 | W27: =W26*(1+U27) -> 86135.744 | X27: =W27+X26 -> 1556065.9 | AA27: 55 | AB27: =IF(RAND()<($E$37/$E$35),$E$32+SQRT(RAND()*$E$35*$E$37),$E$31-SQRT((1-RAND())*$E$36*$E$35)) -> 0.034495225 | AC27: 39279.836 | AD27: =AD26*(1+AB27) -> 93810.29 | AE27: =AE26+AD27 -> 1596475.7
A28: 9/30/2006 | B28: 3.5 | K28: 56 | L28: =IF(RAND()<($E$37/$E$35),$E$32+SQRT(RAND()*$E$35*$E$37),$E$31-SQRT((1-RAND())*$E$36*$E$35)) -> 0.029447209 | M28: 39279.836 | N28: =N27*(1+L28) -> 80784.836 | O28: ='Best scenario'!$S$27 -> 27997.84 | P28: =P27*(1+L28) -> 57581.729 | T28: 56 | U28: =IF(RAND()<($E$37/$E$35),$E$32+SQRT(RAND()*$E$35*$E$37),$E$31-SQRT((1-RAND())*$E$36*$E$35)) -> 0.060715234 | V28: 39279.836 | W28: =W27*(1+U28) -> 91365.496 | X28: =W28+X27 -> 1647431.4 | AA28: 56 | AB28: =IF(RAND()<($E$37/$E$35),$E$32+SQRT(RAND()*$E$35*$E$37),$E$31-SQRT((1-RAND())*$E$36*$E$35)) -> 0.033391959 | AC28: 39279.836 | AD28: =AD27*(1+AB28) -> 96942.8 | AE28: =AE27+AD28 -> 1693418.5
A29: 12/31/2006 | B29: 2.6 | D29: Average | E29: =AVERAGE(E2:E27) -> 0.025625 | K29: 57 | L29: =IF(RAND()<($E$37/$E$35),$E$32+SQRT(RAND()*$E$35*$E$37),$E$31-SQRT((1-RAND())*$E$36*$E$35)) -> 0.027775209 | M29: 39279.836 | N29: =N28*(1+L29) -> 83028.651 | O29: ='Best scenario'!$S$27 -> 27997.84 | P29: =P28*(1+L29) -> 59181.074 | T29: 57 | U29: =IF(RAND()<($E$37/$E$35),$E$32+SQRT(RAND()*$E$35*$E$37),$E$31-SQRT((1-RAND())*$E$36*$E$35)) -> 0.020636283 | V29: 39279.836 | W29: =W28*(1+U29) -> 93250.94 | X29: =W29+X28 -> 1740682.3 | AA29: 57 | AB29: =IF(RAND()<($E$37/$E$35),$E$32+SQRT(RAND()*$E$35*$E$37),$E$31-SQRT((1-RAND())*$E$36*$E$35)) -> 0.027623832 | AC29: 39279.836 | AD29: =AD28*(1+AB29) -> 99620.731 | AE29: =AE28+AD29 -> 1793039.3
A30: 3/31/2007 | B30: 2.5 | D30: Std Dev | E30: =_xlfn.STDEV.S(E2:E27) -> 0.01510931 | K30: 58 | L30: =IF(RAND()<($E$37/$E$35),$E$32+SQRT(RAND()*$E$35*$E$37),$E$31-SQRT((1-RAND())*$E$36*$E$35)) -> 0.024128344 | M30: 39279.836 | N30: =N29*(1+L30) -> 85031.995 | O30: ='Best scenario'!$S$27 -> 27997.84 | P30: =P29*(1+L30) -> 60609.015 | T30: 58 | U30: =IF(RAND()<($E$37/$E$35),$E$32+SQRT(RAND()*$E$35*$E$37),$E$31-SQRT((1-RAND())*$E$36*$E$35)) -> 0.020028507 | V30: 39279.836 | W30: =W29*(1+U30) -> 95118.617 | X30: =W30+X29 -> 1835800.9 | AA30: 58 | AB30: =IF(RAND()<($E$37/$E$35),$E$32+SQRT(RAND()*$E$35*$E$37),$E$31-SQRT((1-RAND())*$E$36*$E$35)) -> 0.017122758 | AC30: 39279.836 | AD30: =AD29*(1+AB30) -> 101326.51 | AE30: =AE29+AD30 -> 1894365.8
A31: 6/30/2007 | B31: 2 | D31: max(b) | E31: =MAX(E2:E27) -> 0.0715 | K31: 59 | L31: =IF(RAND()<($E$37/$E$35),$E$32+SQRT(RAND()*$E$35*$E$37),$E$31-SQRT((1-RAND())*$E$36*$E$35)) -> 0.016612542 | M31: 39279.836 | N31: =N30*(1+L31) -> 86444.593 | O31: ='Best scenario'!$S$27 -> 27997.84 | P31: =P30*(1+L31) -> 61615.885 | T31: 59 | U31: =IF(RAND()<($E$37/$E$35),$E$32+SQRT(RAND()*$E$35*$E$37),$E$31-SQRT((1-RAND())*$E$36*$E$35)) -> 0.025319139 | V31: 39279.836 | W31: =W30*(1+U31) -> 97526.938 | X31: =W31+X30 -> 1933327.9 | AA31: 59 | AB31: =IF(RAND()<($E$37/$E$35),$E$32+SQRT(RAND()*$E$35*$E$37),$E$31-SQRT((1-RAND())*$E$36*$E$35)) -> 0.046875227 | AC31: 39279.836 | AD31: =AD30*(1+AB31) -> 106076.22 | AE31: =AE30+AD31 -> 2000442
A32: 9/30/2007 | B32: 1.8 | D32: min(a) | E32: =MIN(E2:E27) -> 0.003 | K32: 60 | L32: =IF(RAND()<($E$37/$E$35),$E$32+SQRT(RAND()*$E$35*$E$37),$E$31-SQRT((1-RAND())*$E$36*$E$35)) -> 0.037842721 | M32: 39279.836 | N32: =N31*(1+L32) -> 89715.891 | O32: ='Best scenario'!$S$27 -> 27997.84 | P32: =P31*(1+L32) -> 63947.598 | T32: 60 | U32: =IF(RAND()<($E$37/$E$35),$E$32+SQRT(RAND()*$E$35*$E$37),$E$31-SQRT((1-RAND())*$E$36*$E$35)) -> 0.029054603 | V32: 39279.836 | W32: =W31*(1+U32) -> 100360.54 | X32: =W32+X31 -> 2033688.4 | AA32: 60 | AB32: =IF(RAND()<($E$37/$E$35),$E$32+SQRT(RAND()*$E$35*$E$37),$E$31-SQRT((1-RAND())*$E$36*$E$35)) -> 0.019452707 | AC32: 39279.836 | AD32: =AD31*(1+AB32) -> 108139.69 | AE32: =AE31+AD32 -> 2108581.7
A33: 12/31/2007 | B33: 3.2 | D33: mode(m) | E33: 0.025 | K33: 61 | L33: =IF(RAND()<($E$37/$E$35),$E$32+SQRT(RAND()*$E$35*$E$37),$E$31-SQRT((1-RAND())*$E$36*$E$35)) -> 0.0045210187 | M33: 39279.836 | N33: =N32*(1+L33) -> 90121.499 | O33: ='Best scenario'!$S$27 -> 27997.84 | P33: =P32*(1+L33) -> 64236.706 | T33: 61 | U33: =IF(RAND()<($E$37/$E$35),$E$32+SQRT(RAND()*$E$35*$E$37),$E$31-SQRT((1-RAND())*$E$36*$E$35)) -> 0.037266258 | V33: 39279.836 | W33: =W32*(1+U33) -> 104100.61 | X33: =W33+X32 -> 2137789 | AA33: 61 | AB33: =IF(RAND()<($E$37/$E$35),$E$32+SQRT(RAND()*$E$35*$E$37),$E$31-SQRT((1-RAND())*$E$36*$E$35)) -> 0.021355663 | AC33: 39279.836 | AD33: =AD32*(1+AB33) -> 110449.08 | AE33: =AE32+AD33 -> 2219030.8
A34: 3/31/2008 | B34: 3.4 | K34: 62 | L34: =IF(RAND()<($E$37/$E$35),$E$32+SQRT(RAND()*$E$35*$E$37),$E$31-SQRT((1-RAND())*$E$36*$E$35)) -> 0.032346751 | M34: 39279.836 | N34: =N33*(1+L34) -> 93036.636 | O34: ='Best scenario'!$S$27 -> 27997.84 | P34: =P33*(1+L34) -> 66314.555 | T34: 62 | U34: =IF(RAND()<($E$37/$E$35),$E$32+SQRT(RAND()*$E$35*$E$37),$E$31-SQRT((1-RAND())*$E$36*$E$35)) -> 0.043697971 | V34: 39279.836 | W34: =W33*(1+U34) -> 108649.59 | X34: =W34+X33 -> 2246438.6 | AA34: 62 | AB34: =IF(RAND()<($E$37/$E$35),$E$32+SQRT(RAND()*$E$35*$E$37),$E$31-SQRT((1-RAND())*$E$36*$E$35)) -> 0.029988279 | AC34: 39279.836 | AD34: =AD33*(1+AB34) -> 113761.26 | AE34: =AE33+AD34 -> 2332792
A35: 6/30/2008 | B35: 4 | D35: b-a | E35: =E31-E32 -> 0.0685 | K35: 63 | L35: =IF(RAND()<($E$37/$E$35),$E$32+SQRT(RAND()*$E$35*$E$37),$E$31-SQRT((1-RAND())*$E$36*$E$35)) -> 0.058692107 | M35: 39279.836 | N35: =N34*(1+L35) -> 98497.152 | O35: ='Best scenario'!$S$27 -> 27997.84 | P35: =P34*(1+L35) -> 70206.696 | T35: 63 | U35: =IF(RAND()<($E$37/$E$35),$E$32+SQRT(RAND()*$E$35*$E$37),$E$31-SQRT((1-RAND())*$E$36*$E$35)) -> 0.060971185 | V35: 39279.836 | W35: =W34*(1+U35) -> 115274.09 | X35: =W35+X34 -> 2361712.7 | AA35: 63 | AB35: =IF(RAND()<($E$37/$E$35),$E$32+SQRT(RAND()*$E$35*$E$37),$E$31-SQRT((1-RAND())*$E$36*$E$35)) -> 0.058445039 | AC35: 39279.836 | AD35: =AD34*(1+AB35) -> 120410.04 | AE35: =AE34+AD35 -> 2453202.1
A36: 9/30/2008 | B36: 5.1 | D36: b-m | E36: =E31-E33 -> 0.0465 | K36: 64 | L36: =IF(RAND()<($E$37/$E$35),$E$32+SQRT(RAND()*$E$35*$E$37),$E$31-SQRT((1-RAND())*$E$36*$E$35)) -> 0.03698715 | M36: 39279.836 | N36: =N35*(1+L36) -> 102140.28 | O36: ='Best scenario'!$S$27 -> 27997.84 | P36: =P35*(1+L36) -> 72803.441 | T36: 64 | U36: =IF(RAND()<($E$37/$E$35),$E$32+SQRT(RAND()*$E$35*$E$37),$E$31-SQRT((1-RAND())*$E$36*$E$35)) -> 0.021857165 | V36: 39279.836 | W36: =W35*(1+U36) -> 117793.65 | X36: =W36+X35 -> 2479506.3 | AA36: 64 | AB36: =IF(RAND()<($E$37/$E$35),$E$32+SQRT(RAND()*$E$35*$E$37),$E$31-SQRT((1-RAND())*$E$36*$E$35)) -> 0.037874007 | AC36: 39279.836 | AD36: =AD35*(1+AB36) -> 124970.45 | AE36: =AE35+AD36 -> 2578172.5
A37: 12/31/2008 | B37: 3.4 | D37: m-a | E37: =E33-E32 -> 0.022 | K37: 65 | L37: =IF(RAND()<($E$37/$E$35),$E$32+SQRT(RAND()*$E$35*$E$37),$E$31-SQRT((1-RAND())*$E$36*$E$35)) -> 0.021582597 | M37: 39279.836 | N37: =N36*(1+L37) -> 104344.73 | O37: ='Best scenario'!$S$27 -> 27997.84 | P37: =P36*(1+L37) -> 74374.728 | T37: 65 | U37: =IF(RAND()<($E$37/$E$35),$E$32+SQRT(RAND()*$E$35*$E$37),$E$31-SQRT((1-RAND())*$E$36*$E$35)) -> 0.019000293 | V37: 39279.836 | W37: =W36*(1+U37) -> 120031.77 | X37: =W37+X36 -> 2599538.1 | AA37: 65 | AB37: =IF(RAND()<($E$37/$E$35),$E$32+SQRT(RAND()*$E$35*$E$37),$E$31-SQRT((1-RAND())*$E$36*$E$35)) -> 0.040941558 | AC37: 39279.836 | AD37: =AD36*(1+AB37) -> 130086.93 | AE37: =AE36+AD37 -> 2708259.4
A38: 3/31/2009 | B38: 3 | D38: random | E38: =RAND() -> 0.9553852 | K38: 66 | L38: =IF(RAND()<($E$37/$E$35),$E$32+SQRT(RAND()*$E$35*$E$37),$E$31-SQRT((1-RAND())*$E$36*$E$35)) -> 0.032187875 | M38: 39279.836 | N38: =N37*(1+L38) -> 107703.37 | O38: ='Best scenario'!$S$27 -> 27997.84 | P38: =P37*(1+L38) -> 76768.693 | T38: 66 | U38: =IF(RAND()<($E$37/$E$35),$E$32+SQRT(RAND()*$E$35*$E$37),$E$31-SQRT((1-RAND())*$E$36*$E$35)) -> 0.023140523 | V38: 39279.836 | W38: =W37*(1+U38) -> 122809.36 | X38: =W38+X37 -> 2722347.5 | AA38: 66 | AB38: =IF(RAND()<($E$37/$E$35),$E$32+SQRT(RAND()*$E$35*$E$37),$E$31-SQRT((1-RAND())*$E$36*$E$35)) -> 0.040152661 | AC38: 39279.836 | AD38: =AD37*(1+AB38) -> 135310.27 | AE38: =AE37+AD38 -> 2843569.7
A39: 6/30/2009 | B39: 1.9 | D39: triangular | E39: =IF(RAND()<($E$37/$E$35),$E$32+SQRT(RAND()*$E$35*$E$37),$E$31-SQRT((1-RAND())*$E$36*$E$35)) -> 0.049647176 | K39: 67 | L39: =IF(RAND()<($E$37/$E$35),$E$32+SQRT(RAND()*$E$35*$E$37),$E$31-SQRT((1-RAND())*$E$36*$E$35)) -> 0.019946922 | M39: 39279.836 | N39: =N38*(1+L39) -> 109851.72 | O39: ='Best scenario'!$S$27 -> 27997.84 | P39: =P38*(1+L39) -> 78299.992 | T39: 67 | U39: =IF(RAND()<($E$37/$E$35),$E$32+SQRT(RAND()*$E$35*$E$37),$E$31-SQRT((1-RAND())*$E$36*$E$35)) -> 0.035673238 | V39: 39279.836 | W39: =W38*(1+U39) -> 127190.37 | X39: =W39+X38 -> 2849537.8 | AA39: 67 | AB39: =IF(RAND()<($E$37/$E$35),$E$32+SQRT(RAND()*$E$35*$E$37),$E$31-SQRT((1-RAND())*$E$36*$E$35)) -> 0.016054469 | AC39: 39279.836 | AD39: =AD38*(1+AB39) -> 137482.61 | AE39: =AE38+AD39 -> 2981052.3
A40: 9/30/2009 | B40: 1.7 | K40: 68 | L40: =IF(RAND()<($E$37/$E$35),$E$32+SQRT(RAND()*$E$35*$E$37),$E$31-SQRT((1-RAND())*$E$36*$E$35)) -> 0.03675447 | M40: 39279.836 | N40: =N39*(1+L40) -> 113889.26 | O40: ='Best scenario'!$S$27 -> 27997.84 | P40: =P39*(1+L40) -> 81177.867 | T40: 68 | U40: =IF(RAND()<($E$37/$E$35),$E$32+SQRT(RAND()*$E$35*$E$37),$E$31-SQRT((1-RAND())*$E$36*$E$35)) -> 0.016151258 | V40: 39279.836 | W40: =W39*(1+U40) -> 129244.66 | X40: =W40+X39 -> 2978782.5 | AA40: 68 | AB40: =IF(RAND()<($E$37/$E$35),$E$32+SQRT(RAND()*$E$35*$E$37),$E$31-SQRT((1-RAND())*$E$36*$E$35)) -> 0.052278732 | AC40: 39279.836 | AD40: =AD39*(1+AB40) -> 144670.02 | AE40: =AE39+AD40 -> 3125722.3
A41: 12/31/2009 | B41: 2 | K41: 69 | L41: =IF(RAND()<($E$37/$E$35),$E$32+SQRT(RAND()*$E$35*$E$37),$E$31-SQRT((1-RAND())*$E$36*$E$35)) -> 0.02876934 | M41: 39279.836 | N41: =N40*(1+L41) -> 117165.78 | O41: ='Best scenario'!$S$27 -> 27997.84 | P41: =P40*(1+L41) -> 83513.3 | T41: 69 | U41: =IF(RAND()<($E$37/$E$35),$E$32+SQRT(RAND()*$E$35*$E$37),$E$31-SQRT((1-RAND())*$E$36*$E$35)) -> 0.035845985 | V41: 39279.836 | W41: =W40*(1+U41) -> 133877.56 | X41: =W41+X40 -> 3112660.1 | AA41: 69 | AB41: =IF(RAND()<($E$37/$E$35),$E$32+SQRT(RAND()*$E$35*$E$37),$E$31-SQRT((1-RAND())*$E$36*$E$35)) -> 0.024239153 | AC41: 39279.836 | AD41: =AD40*(1+AB41) -> 148176.7 | AE41: =AE40+AD41 -> 3273899
A42: 3/31/2010 | B42: 2 | K42: 70 | L42: =IF(RAND()<($E$37/$E$35),$E$32+SQRT(RAND()*$E$35*$E$37),$E$31-SQRT((1-RAND())*$E$36*$E$35)) -> 0.03483304 | M42: 39279.836 | N42: =N41*(1+L42) -> 121247.02 | O42: ='Best scenario'!$S$27 -> 27997.84 | P42: =P41*(1+L42) -> 86422.322 | T42: 70 | U42: =IF(RAND()<($E$37/$E$35),$E$32+SQRT(RAND()*$E$35*$E$37),$E$31-SQRT((1-RAND())*$E$36*$E$35)) -> 0.01522153 | V42: 39279.836 | W42: =W41*(1+U42) -> 135915.38 | X42: =W42+X41 -> 3248575.4 | AA42: 70 | AB42: =IF(RAND()<($E$37/$E$35),$E$32+SQRT(RAND()*$E$35*$E$37),$E$31-SQRT((1-RAND())*$E$36*$E$35)) -> 0.051796644 | AC42: 39279.836 | AD42: =AD41*(1+AB42) -> 155851.76 | AE42: =AE41+AD42 -> 3429750.8
A43: 6/30/2010 | B43: 1.7 | K43: 71 | L43: =IF(RAND()<($E$37/$E$35),$E$32+SQRT(RAND()*$E$35*$E$37),$E$31-SQRT((1-RAND())*$E$36*$E$35)) -> 0.062402913 | M43: 39279.836 | N43: =N42*(1+L43) -> 128813.19 | O43: ='Best scenario'!$S$27 -> 27997.84 | P43: =P42*(1+L43) -> 91815.327 | T43: 71 | U43: =IF(RAND()<($E$37/$E$35),$E$32+SQRT(RAND()*$E$35*$E$37),$E$31-SQRT((1-RAND())*$E$36*$E$35)) -> 0.014508509 | V43: 39279.836 | W43: =W42*(1+U43) -> 137887.31 | X43: =W43+X42 -> 3386462.7 | AA43: 71 | AB43: =IF(RAND()<($E$37/$E$35),$E$32+SQRT(RAND()*$E$35*$E$37),$E$31-SQRT((1-RAND())*$E$36*$E$35)) -> 0.054052702 | AC43: 39279.836 | AD43: =AD42*(1+AB43) -> 164275.97 | AE43: =AE42+AD43 -> 3594026.8
A44: 9/30/2010 | B44: 1.5 | K44: 72 | L44: =IF(RAND()<($E$37/$E$35),$E$32+SQRT(RAND()*$E$35*$E$37),$E$31-SQRT((1-RAND())*$E$36*$E$35)) -> 0.038147937 | M44: 39279.836 | N44: =N43*(1+L44) -> 133727.15 | O44: ='Best scenario'!$S$27 -> 27997.84 | P44: =P43*(1+L44) -> 95317.892 | T44: 72 | U44: =IF(RAND()<($E$37/$E$35),$E$32+SQRT(RAND()*$E$35*$E$37),$E$31-SQRT((1-RAND())*$E$36*$E$35)) -> 0.029357936 | V44: 39279.836 | W44: =W43*(1+U44) -> 141935.39 | X44: =W44+X43 -> 3528398.1 | AA44: 72 | AB44: =IF(RAND()<($E$37/$E$35),$E$32+SQRT(RAND()*$E$35*$E$37),$E$31-SQRT((1-RAND())*$E$36*$E$35)) -> 0.050736357 | AC44: 39279.836 | AD44: =AD43*(1+AB44) -> 172610.73 | AE44: =AE43+AD44 -> 3766637.5
A45: 12/31/2010 | B45: 4 | K45: 73 | L45: =IF(RAND()<($E$37/$E$35),$E$32+SQRT(RAND()*$E$35*$E$37),$E$31-SQRT((1-RAND())*$E$36*$E$35)) -> 0.038034774 | M45: 39279.836 | N45: =N44*(1+L45) -> 138813.43 | O45: ='Best scenario'!$S$27 -> 27997.84 | P45: =P44*(1+L45) -> 98943.287 | T45: 73 | U45: =IF(RAND()<($E$37/$E$35),$E$32+SQRT(RAND()*$E$35*$E$37),$E$31-SQRT((1-RAND())*$E$36*$E$35)) -> 0.027481379 | V45: 39279.836 | W45: =W44*(1+U45) -> 145835.97 | X45: =W45+X44 -> 3674234.1 | AA45: 73 | AB45: =IF(RAND()<($E$37/$E$35),$E$32+SQRT(RAND()*$E$35*$E$37),$E$31-SQRT((1-RAND())*$E$36*$E$35)) -> 0.028625571 | AC45: 39279.836 | AD45: =AD44*(1+AB45) -> 177551.81 | AE45: =AE44+AD45 -> 3944189.3
A46: 3/31/2011 | B46: 4.5 | K46: 74 | L46: =IF(RAND()<($E$37/$E$35),$E$32+SQRT(RAND()*$E$35*$E$37),$E$31-SQRT((1-RAND())*$E$36*$E$35)) -> 0.037263244 | M46: 39279.836 | N46: =N45*(1+L46) -> 143986.07 | O46: ='Best scenario'!$S$27 -> 27997.84 | P46: =P45*(1+L46) -> 102630.23 | T46: 74 | U46: =IF(RAND()<($E$37/$E$35),$E$32+SQRT(RAND()*$E$35*$E$37),$E$31-SQRT((1-RAND())*$E$36*$E$35)) -> 0.030345615 | V46: 39279.836 | W46: =W45*(1+U46) -> 150261.46 | X46: =W46+X45 -> 3824495.6 | AA46: 74 | AB46: =IF(RAND()<($E$37/$E$35),$E$32+SQRT(RAND()*$E$35*$E$37),$E$31-SQRT((1-RAND())*$E$36*$E$35)) -> 0.022115008 | AC46: 39279.836 | AD46: =AD45*(1+AB46) -> 181478.37 | AE46: =AE45+AD46 -> 4125667.7
A47: 6/30/2011 | B47: 5.3 | K47: 75 | L47: =IF(RAND()<($E$37/$E$35),$E$32+SQRT(RAND()*$E$35*$E$37),$E$31-SQRT((1-RAND())*$E$36*$E$35)) -> 0.010370977 | M47: 39279.836 | N47: =N46*(1+L47) -> 145479.34 | O47: ='Best scenario'!$S$27 -> 27997.84 | P47: =P46*(1+L47) -> 103694.61 | T47: 75 | U47: =IF(RAND()<($E$37/$E$35),$E$32+SQRT(RAND()*$E$35*$E$37),$E$31-SQRT((1-RAND())*$E$36*$E$35)) -> 0.01681122 | V47: 39279.836 | W47: =W46*(1+U47) -> 152787.54 | X47: =W47+X46 -> 3977283.1 | AA47: 75 | AB47: =IF(RAND()<($E$37/$E$35),$E$32+SQRT(RAND()*$E$35*$E$37),$E$31-SQRT((1-RAND())*$E$36*$E$35)) -> 0.030720627 | AC47: 39279.836 | AD47: =AD46*(1+AB47) -> 187053.5 | AE47: =AE46+AD47 -> 4312721.2
A48: 9/30/2011 | B48: 4.6 | K48: 76 | L48: =IF(RAND()<($E$37/$E$35),$E$32+SQRT(RAND()*$E$35*$E$37),$E$31-SQRT((1-RAND())*$E$36*$E$35)) -> 0.053322051 | M48: 39279.836 | N48: =N47*(1+L48) -> 153236.6 | O48: ='Best scenario'!$S$27 -> 27997.84 | P48: =P47*(1+L48) -> 109223.82 | T48: 76 | U48: =IF(RAND()<($E$37/$E$35),$E$32+SQRT(RAND()*$E$35*$E$37),$E$31-SQRT((1-RAND())*$E$36*$E$35)) -> 0.033013255 | V48: 39279.836 | W48: =W47*(1+U48) -> 157831.55 | X48: =W48+X47 -> 4135114.7 | AA48: 76 | AB48: =IF(RAND()<($E$37/$E$35),$E$32+SQRT(RAND()*$E$35*$E$37),$E$31-SQRT((1-RAND())*$E$36*$E$35)) -> 0.031951945 | AC48: 39279.836 | AD48: =AD47*(1+AB48) -> 193030.22 | AE48: =AE47+AD48 -> 4505751.4
A49: 12/31/2011 | B49: 1.8 | K49: 77 | L49: =IF(RAND()<($E$37/$E$35),$E$32+SQRT(RAND()*$E$35*$E$37),$E$31-SQRT((1-RAND())*$E$36*$E$35)) -> 0.055928137 | M49: 39279.836 | N49: =N48*(1+L49) -> 161806.84 | O49: ='Best scenario'!$S$27 -> 27997.84 | P49: =P48*(1+L49) -> 115332.5 | T49: 77 | U49: =IF(RAND()<($E$37/$E$35),$E$32+SQRT(RAND()*$E$35*$E$37),$E$31-SQRT((1-RAND())*$E$36*$E$35)) -> 0.032869178 | V49: 39279.836 | W49: =W48*(1+U49) -> 163019.34 | X49: =W49+X48 -> 4298134 | AA49: 77 | AB49: =IF(RAND()<($E$37/$E$35),$E$32+SQRT(RAND()*$E$35*$E$37),$E$31-SQRT((1-RAND())*$E$36*$E$35)) -> 0.029506438 | AC49: 39279.836 | AD49: =AD48*(1+AB49) -> 198725.86 | AE49: =AE48+AD49 -> 4704477.3
A50: 3/31/2012 | B50: 1.6 | K50: 78 | L50: =IF(RAND()<($E$37/$E$35),$E$32+SQRT(RAND()*$E$35*$E$37),$E$31-SQRT((1-RAND())*$E$36*$E$35)) -> 0.028857805 | M50: 39279.836 | N50: =N49*(1+L50) -> 166476.23 | O50: ='Best scenario'!$S$27 -> 27997.84 | P50: =P49*(1+L50) -> 118660.75 | T50: 78 | U50: =IF(RAND()<($E$37/$E$35),$E$32+SQRT(RAND()*$E$35*$E$37),$E$31-SQRT((1-RAND())*$E$36*$E$35)) -> 0.044760358 | V50: 39279.836 | W50: =W49*(1+U50) -> 170316.15 | X50: =W50+X49 -> 4468450.1 | AA50: 78 | AB50: =IF(RAND()<($E$37/$E$35),$E$32+SQRT(RAND()*$E$35*$E$37),$E$31-SQRT((1-RAND())*$E$36*$E$35)) -> 0.014820571 | AC50: 39279.836 | AD50: =AD49*(1+AB50) -> 201671.09 | AE50: =AE49+AD50 -> 4906148.3
A51: 6/30/2012 | B51: 1 | K51: 79 | L51: =IF(RAND()<($E$37/$E$35),$E$32+SQRT(RAND()*$E$35*$E$37),$E$31-SQRT((1-RAND())*$E$36*$E$35)) -> 0.026914688 | M51: 39279.836 | N51: =N50*(1+L51) -> 170956.88 | O51: ='Best scenario'!$S$27 -> 27997.84 | P51: =P50*(1+L51) -> 121854.46 | T51: 79 | U51: =IF(RAND()<($E$37/$E$35),$E$32+SQRT(RAND()*$E$35*$E$37),$E$31-SQRT((1-RAND())*$E$36*$E$35)) -> 0.018688925 | V51: 39279.836 | W51: =W50*(1+U51) -> 173499.17 | X51: =W51+X50 -> 4641949.3 | AA51: 79 | AB51: =IF(RAND()<($E$37/$E$35),$E$32+SQRT(RAND()*$E$35*$E$37),$E$31-SQRT((1-RAND())*$E$36*$E$35)) -> 0.036552862 | AC51: 39279.836 | AD51: =AD50*(1+AB51) -> 209042.74 | AE51: =AE50+AD51 -> 5115191.1
... A56: 9/30/2013 | B56: 1.4 | K56: 84 | L56: =IF(RAND()<($E$37/$E$35),$E$32+SQRT(RAND()*$E$35*$E$37),$E$31-SQRT((1-RAND())*$E$36*$E$35)) -> 0.039233095 | M56: 39279.836 | N56: =N55*(1+L56) -> 208807.7 | O56: ='Best scenario'!$S$27 -> 27997.84 | P56: =P55*(1+L56) -> 148833.73 | T56: 84 | U56: =IF(RAND()<($E$37/$E$35),$E$32+SQRT(RAND()*$E$35*$E$37),$E$31-SQRT((1-RAND())*$E$36*$E$35)) -> 0.030736776 | V56: 39279.836 | W56: =W55*(1+U56) -> 203528.08 | X56: =W56+X55 -> 5607519.2 | AA56: 84 | AB56: =IF(RAND()<($E$37/$E$35),$E$32+SQRT(RAND()*$E$35*$E$37),$E$31-SQRT((1-RAND())*$E$36*$E$35)) -> 0.059012497 | AC56: 39279.836 | AD56: =AD55*(1+AB56) -> 251279.46 | AE56: =AE55+AD56 -> 6280688
A57: 12/31/2013 | B57: 1.6 | L57: Emergency Fund(Total) | M57: 39279.836 | U57: Emergency Fund(Total) | V57: 39279.836 | AB57: Emergency Fund(Total) | AC57: 39279.836
A58: 3/31/2014 | B58: 1.5 | L58: Traveling expenditure per year | M58: 10000 | O58: Total NZ Super | P58: =SUM(P37:P56) -> 2129499.6 | U58: Traveling expenditure per year | V58: 10000 | AB58: Traveling expenditure per year | AC58: 10000
A59: 6/30/2014 | B59: 1.6 | L59: Retirement period | M59: 20 | U59: Retirement period | V59: 25 | AB59: Retirement period | AC59: 22
A60: 9/30/2014 | B60: 1 | L60: Total expenditure | M60: =SUM(N37:N56)+M57+M58*M59 -> 3226881.5 | U60: Total expenditure | V60: =SUM(W32:W56)+V57+(V59*V58) -> 3963471.2 | AB60: Total expenditure | AC60: =SUM(AD35:AD56)+AC57+AC58*AC59 -> 4207175.8
A61: 12/31/2014 | B61: 0.8
A62: 3/31/2015 | B62: 0.3 | J62: Trails | K62: Total Expenditure | S62: Trails | T62: Total Expenditure | Z62: Trails | AA62: Total Expenditure
A63: 6/30/2015 | B63: 0.4 | J63: {=_xlfn.SEQUENCE(1000)} -> 1 | K63: =M60 -> 3226881.5 | M63: count | N63: =COUNT(K63:K1062) -> 1000 | S63: {=_xlfn.SEQUENCE(1000)} -> 1 | T63: =V60 -> 3963471.2 | V63: count | W63: =COUNT(T63:T1062) -> 1000 | Z63: {=_xlfn.SEQUENCE(1000)} -> 1 | AA63: =AC60 -> 4207175.8 | AC63: count | AD63: =COUNT(AA63:AA1062) -> 1000
A64: 9/30/2015 | B64: 0.4 | J64: 2 | K64: 3503856.5 | M64: max | N64: =MAX(K63:K1062) -> 4546770.4 | S64: 2 | T64: 4602632.8 | V64: max | W64: =MAX(T63:T1062) -> 5441562.1 | Z64: 2 | AA64: 3585055.4 | AC64: max | AD64: =MAX(AA63:AA1062) -> 5064932.1
A65: 12/31/2015 | B65: 0.1 | J65: 3 | K65: 3249647.2 | M65: min | N65: =MIN(K63:K1062) -> 2850091.3 | S65: 3 | T65: 3732631.7 | V65: min | W65: =MIN(T63:T1062) -> 3370280.9 | Z65: 3 | AA65: 3505048.1 | AC65: min | AD65: =MIN(AA63:AA1062) -> 3047416.5
A66: 3/31/2016 | B66: 0.4 | J66: 4 | K66: 3574246.3 | M66: mean | N66: =AVERAGE(K63:K1062) -> 3625499.2 | O66: =AVERAGE(L63:L1062) -> #DIV/0! | S66: 4 | T66: 4279427.2 | V66: mean | W66: =AVERAGE(T63:T1062) -> 4253088.1 | Z66: 4 | AA66: 3882299.3 | AC66: mean | AD66: =AVERAGE(AA63:AA1062) -> 3891102.8
A67: 6/30/2016 | B67: 0.4 | J67: 5 | K67: 3943896.4 | M67: SD | N67: =_xlfn.STDEV.S(K63:K1062) -> 263405.24 | S67: 5 | T67: 3696507 | V67: SD | W67: =_xlfn.STDEV.S(T63:T1062) -> 311204.01 | Z67: 5 | AA67: 3896063 | AC67: SD | AD67: =_xlfn.STDEV.S(AA63:AA1062) -> 285064.95
A68: 9/30/2016 | B68: 0.4 | J68: 6 | K68: 3461109 | S68: 6 | T68: 4076792.6 | Z68: 6 | AA68: 4085621.1
A69: 12/31/2016 | B69: 1.3 | J69: 7 | K69: 3855315.7 | M69: 95%CI | N69: =N66+_xlfn.CONFIDENCE.T(0.05,N67,N63) -> 3641844.8 | S69: 7 | T69: 4419103.3 | V69: 95%CI | W69: =W66+_xlfn.CONFIDENCE.T(0.05,W67,W63) -> 4272399.8 | Z69: 7 | AA69: 4284392 | AC69: 95%CI | AD69: =AD66+_xlfn.CONFIDENCE.T(0.05,AD67,AD63) -> 3908792.5
A70: 3/31/2017 | B70: 2.2 | J70: 8 | K70: 3770013.8 | N70: =N66-_xlfn.CONFIDENCE.T(0.05,N67,N63) -> 3609153.7 | S70: 8 | T70: 4052603.6 | W70: =W66-_xlfn.CONFIDENCE.T(0.05,W67,W63) -> 4233776.5 | Z70: 8 | AA70: 4068429.7 | AD70: =AD66-_xlfn.CONFIDENCE.T(0.05,AD67,AD63) -> 3873413.2
A71: 6/30/2017 | B71: 1.7 | J71: 9 | K71: 3746697.7 | S71: 9 | T71: 4446631.5 | Z71: 9 | AA71: 4410121.2
A72: 9/30/2017 | B72: 1.9 | J72: 10 | K72: 3436996.1 | S72: 10 | T72: 4232271.1 | Z72: 10 | AA72: 3826736.6
A73: 12/31/2017 | B73: 1.6 | J73: 11 | K73: 3422013 | S73: 11 | T73: 4090961.4 | Z73: 11 | AA73: 3957872.8 | AD73: 4956876.7
A74: 3/31/2018 | B74: 1.1 | J74: 12 | K74: 3490953.3 | S74: 12 | T74: 4207413.9 | Z74: 12 | AA74: 3668110.6 | AD74: 3146474.4
A75: 6/30/2018 | B75: 1.5 | J75: 13 | K75: 4012821 | S75: 13 | T75: 4406852.7 | Z75: 13 | AA75: 3876366.4 | AD75: 3883813.2
A76: 9/30/2018 | B76: 1.9 | J76: 14 | K76: 4069841 | S76: 14 | T76: 3799777.1 | Z76: 14 | AA76: 3583706.3 | AD76: 283586.51
A77: 12/31/2018 | B77: 1.9 | J77: 15 | K77: 3790066.3 | S77: 15 | T77: 4229876.9 | Z77: 15 | AA77: 3721538.3
A78: 3/31/2019 | B78: 1.5 | J78: 16 | K78: 3322460.9 | S78: 16 | T78: 3959760.7 | Z78: 16 | AA78: 3938213.3 | AD78: 3901411
A79: 6/30/2019 | B79: 1.7 | J79: 17 | K79: 3649266 | S79: 17 | T79: 5169718.4 | Z79: 17 | AA79: 3837528 | AD79: 3866215.3
A80: 9/30/2019 | B80: 1.5 | J80: 18 | K80: 3357976.9 | S80: 18 | T80: 4115604.2 | Z80: 18 | AA80: 3810513.6
A81: 12/31/2019 | B81: 1.9 | J81: 19 | K81: 3767051.2 | S81: 19 | T81: 4606025.3 | Z81: 19 | AA81: 3867062
A82: 3/31/2020 | B82: 2.5 | J82: 20 | K82: 3650352.3 | S82: 20 | T82: 4144398.9 | Z82: 20 | AA82: 3649541.3
A83: 6/30/2020 | B83: 1.5 | J83: 21 | K83: 3540165.1 | S83: 21 | T83: 3727863.8 | Z83: 21 | AA83: 3754858.4
A84: 9/30/2020 | B84: 1.4 | J84: 22 | K84: 3427285.3 | S84: 22 | T84: 4627960 | Z84: 22 | AA84: 3950885.4
A85: 12/31/2020 | B85: 1.4 | J85: 23 | K85: 4192060.5 | S85: 23 | T85: 4187651.6 | Z85: 23 | AA85: 4117054.5
A86: 3/31/2021 | B86: 1.5 | J86: 24 | K86: 3823103.4 | S86: 24 | T86: 4388761.3 | Z86: 24 | AA86: 3869973.9
A87: 6/30/2021 | B87: 3.3 | J87: 25 | K87: 3365138.3 | S87: 25 | T87: 3989097.8 | Z87: 25 | AA87: 3555710.5
A88: 9/30/2021 | B88: 4.9 | J88: 26 | K88: 4136605.3 | S88: 26 | T88: 4211041 | Z88: 26 | AA88: 3926569.6
A89: 12/31/2021 | B89: 5.9 | J89: 27 | K89: 3961156.7 | S89: 27 | T89: 3656823.8 | Z89: 27 | AA89: 3602384.6
A90: 3/31/2022 | B90: 6.9 | J90: 28 | K90: 3980784.1 | S90: 28 | T90: 4400351.7 | Z90: 28 | AA90: 5064932.1
A91: 6/30/2022 | B91: 7.3 | J91: 29 | K91: 3798773.2 | S91: 29 | T91: 4226991.8 | Z91: 29 | AA91: 4116090.3
... A102: 3/31/2025 | B102: 2.5 | J102: 40 | K102: 3602345.4 | S102: 40 | T102: 4074382.9 | Z102: 40 | AA102: 3691918.7
J103: 41 | K103: 3575701.9 | S103: 41 | T103: 4167276.3 | Z103: 41 | AA103: 4340179.7
J104: 42 | K104: 3957376.1 | S104: 42 | T104: 3982381 | Z104: 42 | AA104: 3727466.6
J105: 43 | K105: 3151902.7 | S105: 43 | T105: 4140424.3 | Z105: 43 | AA105: 3953901.7
J106: 44 | K106: 3243688 | S106: 44 | T106: 3838202.4 | Z106: 44 | AA106: 3919287.1
J107: 45 | K107: 3577697 | S107: 45 | T107: 4704502.3 | Z107: 45 | AA107: 3917838.7
J108: 46 | K108: 3626189.8 | S108: 46 | T108: 4657907.6 | Z108: 46 | AA108: 3419646.3
J109: 47 | K109: 3516781.5 | S109: 47 | T109: 3841876.6 | Z109: 47 | AA109: 3789432
J110: 48 | K110: 3624752 | S110: 48 | T110: 4217324.6 | Z110: 48 | AA110: 3209627.1
J111: 49 | K111: 3495547.2 | S111: 49 | T111: 4439900.5 | Z111: 49 | AA111: 4560522.1
J112: 50 | K112: 3582444.9 | S112: 50 | T112: 4161559.8 | Z112: 50 | AA112: 3738484.6
J113: 51 | K113: 3550089.3 | S113: 51 | T113: 4022260 | Z113: 51 | AA113: 3593851.9
J114: 52 | K114: 3396423.2 | S114: 52 | T114: 3674323.7 | Z114: 52 | AA114: 4159352
...

Sheet task3 model
A1: EMILY'S RETIREMENT MODEL
A3: Parameter
A4: current salary: | B4: 70000 | C4: (rand) | D4: =RAND() -> 0.54360729
A5: average growth rate/ yearly （ μ）： | B5: 0.035
A6: Standard variation（σ）： | B6: 0.007
A7: Estimated growth rate(norm) | B7: =_xlfn.NORM.INV(D4,B5,B6) -> 0.035766681
A8: Estimated salary | B8: =B4*(1+B7) -> 72503.668
A9: Contribution rate from Emily | B9: 0.06 | C9: 0.03 | D9: 0.06 | E9: 0.1
A10: superannuation rate from company | B10: 0.021 | C10: Deduct ESCT tax ($57,601 – $84,000) | D10: ESCT tax (> $84,000) | E10: Contribute based on pre-tax salary.
A11: KiwiSaver revenue tax(before retirement) | B11: 0.28
A12: KiwiSaver revenue tax(after retirement) | C12: NZ Super+bank intrest+fund revenue
A13: NZ Super tax | B13: 1076.84
A14: superannuation compensation from goverment | B14: =IF(B8*B9>C15,D15,B8*B9*50%) -> 521.43 | C14: Min personal contribute | D14: Max Member Tax Credit
C15: 1042.86 | D15: 521.43
A16: Annual Bank Savings | B16: =C17*(1+D17) -> 5581.242 | C16: Money saved per year | D16: Rate
C17: 5364 | D17: 0.0405
A18: Decision Variables | B18: Current allocation | C18: Annual Growth Rate | D18: Volatility （SD）
A19: Harbor safe | B19: 0.4 | C19: 0.0375 | D19: 0.05
A20: Horizon | B20: 0.3 | C20: 0.065 | D20: 0.105
A21: Skyhigh | B21: 0.3 | C21: 0.1025 | D21: 0.2075
A22: Total | B22: =SUM(B19:B21) -> 1
A23: Retirement age | B23: 65 | C23: 60 | D23: 63 | E23: 65
F24: 0.06
B25: NORM.INV(D4,B5,B6) | C25: C19*(1+B20) | D25: IF(C10<84000,3%*(1-C13),3%*(1-D13)) | E25: IF(B8*B9>C13,D13,B8*B9*50%) | F25: C20*(B11+D20)+B14
A26: Year old（30-65 years old） | B26: Salary growth rate | C26: estimated salary | D26: superannuation rate from company | E26: superannuation compensation from gov | F26: Annual superannuation (pre-tax) | G26: Harbor safe growth rate | H26: Harborsafe revenue | I26: Harborsafe balance | J26: Horizon growth rate | K26: Horizon revenue | L26: Horizon balance | M26: Skyhigh growth rate | N26: Skyhigh revenue | O26: Skyhigh balance | P26: Total balance (pre tax) | Q26: Amount needs taxed | R26: Kiwisaver TAX | S26: NZ super | T26: Total Balance( after tax)
A27: 30 | B27: =_xlfn.NORM.INV(RAND(),$B$5,$B$6) -> 0.026319585 | C27: 70000 | D27: =IF(C27<84000,3%*(1-30%),3%*(1-33%)) -> 0.021 | E27: =$B$14 -> 521.43 | F27: =C27*($B$9+D27)+E27 -> 6191.43 | G27: =_xlfn.NORM.INV(RAND(),$C$19,$D$19) -> 0.0816207 | H27: =(F27*$B$19)*G27 -> 202.13954 | I27: =F27*B20*(1+G27) -> 2009.0337 | J27: =_xlfn.NORM.INV(RAND(),$C$20,$D$20) -> -0.024019188 | K27: =F27*$B$20*J27 -> -44.613936 | L27: =F27*B21*(1+J27) -> 1812.8151 | M27: =_xlfn.NORM.INV(RAND(),$C$21,$D$21) -> -0.17132512 | N27: =F27*$B$21*M27 -> -318.22424 | O27: =F27*B22*(1+M27) -> 5130.6825 | P27: =I27+L27+O27 -> 8952.5312 | Q27: =H27+K27+N27 -> -160.69864 | R27: =IF(Q27>0,Q27*$B$11,0) -> 0 | S27: =26*$B$13 -> 27997.84 | T27: =P27-R27+S27 -> 36950.371
A28: 31 | B28: =_xlfn.NORM.INV(RAND(),$B$5,$B$6) -> 0.044815107 | C28: =C27*(1+B28) -> 73137.057 | D28: =IF(C28<84000,3%*(1-30%),3%*(1-33%)) -> 0.021 | E28: =$B$14 -> 521.43 | F28: =C28*($B$9+D28)+E28 -> 6445.5317 | G28: =_xlfn.NORM.INV(RAND(),$C$19,$D$19) -> 0.029723412 | H28: =(I27+F28*$B$19)*G28 -> 136.34861 | I28: =(I27+(F28*$B$19))*(1+G28) -> 4723.5949 | J28: =_xlfn.NORM.INV(RAND(),$C$20,$D$20) -> 0.024092778 | K28: =(L27+F28*$B$20)*J28 -> 90.26298 | L28: =(L27+F28*$B$20)*(1+J28) -> 3836.7375 | M28: =_xlfn.NORM.INV(RAND(),$C$21,$D$21) -> 0.087053578 | N28: =(O27+F28*$B$21)*M28 -> 614.97625 | O28: =(O27+F28*$B$21)*(1+M28) -> 7679.3183 | P28: =I28+L28+O28 -> 16239.651 | Q28: =H28+K28+N28 -> 841.58784 | R28: =IF(Q28>0,Q28*$B$11,0) -> 235.6446 | S28: =26*$B$13 -> 27997.84 | T28: =P28-R28+S28 -> 44001.846
A29: 32 | B29: =_xlfn.NORM.INV(RAND(),$B$5,$B$6) -> 0.035467104 | C29: 70001 | D29: =IF(C29<84000,3%*(1-30%),3%*(1-33%)) -> 0.021 | E29: =$B$14 -> 521.43 | F29: =C29*($B$9+D29)+E29 -> 6191.511 | G29: =_xlfn.NORM.INV(RAND(),$C$19,$D$19) -> 0.11601819 | H29: =(I28+F29*$B$19)*G29 -> 835.35409 | I29: =(I28+(F29*$B$19))*(1+G29) -> 8035.5534 | J29: =_xlfn.NORM.INV(RAND(),$C$20,$D$20) -> -0.14280802 | K29: =(L28+F29*$B$20)*J29 -> -813.17612 | L29: =(L28+F29*$B$20)*(1+J29) -> 4881.0147 | M29: =_xlfn.NORM.INV(RAND(),$C$21,$D$21) -> -0.069793463 | N29: =(O28+F29*$B$21)*M29 -> -665.60431 | O29: =(O28+F29*$B$21)*(1+M29) -> 8871.1672 | P29: =I29+L29+O29 -> 21787.735 | Q29: =H29+K29+N29 -> -643.42634 | R29: =IF(Q29>0,Q29*$B$11,0) -> 0 | S29: =26*$B$13 -> 27997.84 | T29: =P29-R29+S29 -> 49785.575
A30: 33 | B30: =_xlfn.NORM.INV(RAND(),$B$5,$B$6) -> 0.041427519 | C30: =C29*(1+B30) -> 72900.968 | D30: =IF(C30<84000,3%*(1-30%),3%*(1-33%)) -> 0.021 | E30: =$B$14 -> 521.43 | F30: =C30*($B$9+D30)+E30 -> 6426.4084 | G30: =_xlfn.NORM.INV(RAND(),$C$19,$D$19) -> 0.015809457 | H30: =(I29+F30*$B$19)*G30 -> 167.67695 | I30: =(I29+(F30*$B$19))*(1+G30) -> 10773.794 | J30: =_xlfn.NORM.INV(RAND(),$C$20,$D$20) -> -0.082415133 | K30: =(L29+F30*$B$20)*J30 -> -561.15947 | L30: =(L29+F30*$B$20)*(1+J30) -> 6247.7778 | M30: =_xlfn.NORM.INV(RAND(),$C$21,$D$21) -> -0.004780018 | N30: =(O29+F30*$B$21)*M30 -> -51.619843 | O30: =(O29+F30*$B$21)*(1+M30) -> 10747.47 | P30: =I30+L30+O30 -> 27769.041 | Q30: =H30+K30+N30 -> -445.10237 | R30: =IF(Q30>0,Q30*$B$11,0) -> 0 | S30: =26*$B$13 -> 27997.84 | T30: =P30-R30+S30 -> 55766.881
A31: 34 | B31: =_xlfn.NORM.INV(RAND(),$B$5,$B$6) -> 0.039309997 | C31: =C30*(1+B31) -> 75766.705 | D31: =IF(C31<84000,3%*(1-30%),3%*(1-33%)) -> 0.021 | E31: =$B$14 -> 521.43 | F31: =C31*($B$9+D31)+E31 -> 6658.5331 | G31: =_xlfn.NORM.INV(RAND(),$C$19,$D$19) -> 0.061697096 | H31: =(I30+F31*$B$19)*G31 -> 829.03665 | I31: =(I30+(F31*$B$19))*(1+G31) -> 14266.244 | J31: =_xlfn.NORM.INV(RAND(),$C$20,$D$20) -> -0.085779462 | K31: =(L30+F31*$B$20)*J31 -> -707.28063 | L31: =(L30+F31*$B$20)*(1+J31) -> 7538.0571 | M31: =_xlfn.NORM.INV(RAND(),$C$21,$D$21) -> -0.012014141 | N31: =(O30+F31*$B$21)*M31 -> -153.12058 | O31: =(O30+F31*$B$21)*(1+M31) -> 12591.909 | P31: =I31+L31+O31 -> 34396.21 | Q31: =H31+K31+N31 -> -31.364566 | R31: =IF(Q31>0,Q31*$B$11,0) -> 0 | S31: =26*$B$13 -> 27997.84 | T31: =P31-R31+S31 -> 62394.05
A32: 35 | B32: =_xlfn.NORM.INV(RAND(),$B$5,$B$6) -> 0.038054866 | C32: =C31*(1+B32) -> 78649.996 | D32: =IF(C32<84000,3%*(1-30%),3%*(1-33%)) -> 0.021 | E32: =$B$14 -> 521.43 | F32: =C32*($B$9+D32)+E32 -> 6892.0797 | G32: =_xlfn.NORM.INV(RAND(),$C$19,$D$19) -> 0.10772774 | H32: =(I31+F32*$B$19)*G32 -> 1833.8575 | I32: =(I31+(F32*$B$19))*(1+G32) -> 18856.933 | J32: =_xlfn.NORM.INV(RAND(),$C$20,$D$20) -> 0.18073218 | K32: =(L31+F32*$B$20)*J32 -> 1736.0557 | L32: =(L31+F32*$B$20)*(1+J32) -> 11341.737 | M32: =_xlfn.NORM.INV(RAND(),$C$21,$D$21) -> -0.27658243 | N32: =(O31+F32*$B$21)*M32 -> -4054.5693 | O32: =(O31+F32*$B$21)*(1+M32) -> 10604.964 | P32: =I32+L32+O32 -> 40803.633 | Q32: =H32+K32+N32 -> -484.65615 | R32: =IF(Q32>0,Q32*$B$11,0) -> 0 | S32: =26*$B$13 -> 27997.84 | T32: =P32-R32+S32 -> 68801.473
A33: 36 | B33: =_xlfn.NORM.INV(RAND(),$B$5,$B$6) -> 0.033462026 | C33: =C32*(1+B33) -> 81281.785 | D33: =IF(C33<84000,3%*(1-30%),3%*(1-33%)) -> 0.021 | E33: =$B$14 -> 521.43 | F33: =C33*($B$9+D33)+E33 -> 7105.2546 | G33: =_xlfn.NORM.INV(RAND(),$C$19,$D$19) -> 0.027934819 | H33: =(I32+F33*$B$19)*G33 -> 606.15861 | I33: =(I32+(F33*$B$19))*(1+G33) -> 22305.193 | J33: =_xlfn.NORM.INV(RAND(),$C$20,$D$20) -> 0.11212143 | K33: =(L32+F33*$B$20)*J33 -> 1510.6472 | L33: =(L32+F33*$B$20)*(1+J33) -> 14983.96 | M33: =_xlfn.NORM.INV(RAND(),$C$21,$D$21) -> 0.022506598 | N33: =(O32+F33*$B$21)*M33 -> 286.6562 | O33: =(O32+F33*$B$21)*(1+M33) -> 13023.196 | P33: =I33+L33+O33 -> 50312.35 | Q33: =H33+K33+N33 -> 2403.462 | R33: =IF(Q33>0,Q33*$B$11,0) -> 672.96935 | S33: =26*$B$13 -> 27997.84 | T33: =P33-R33+S33 -> 77637.221
A34: 37 | B34: =_xlfn.NORM.INV(RAND(),$B$5,$B$6) -> 0.043618735 | C34: =C33*(1+B34) -> 84827.193 | D34: =IF(C34<84000,3%*(1-30%),3%*(1-33%)) -> 0.0201 | E34: =$B$14 -> 521.43 | F34: =C34*($B$9+D34)+E34 -> 7316.0882 | G34: =_xlfn.NORM.INV(RAND(),$C$19,$D$19) -> 0.0047179551 | H34: =(I33+F34*$B$19)*G34 -> 119.04169 | I34: =(I33+(F34*$B$19))*(1+G34) -> 25350.67 | J34: =_xlfn.NORM.INV(RAND(),$C$20,$D$20) -> 0.0061529385 | K34: =(L33+F34*$B$20)*J34 -> 105.70002 | L34: =(L33+F34*$B$20)*(1+J34) -> 17284.487 | M34: =_xlfn.NORM.INV(RAND(),$C$21,$D$21) -> 0.28694314 | N34: =(O33+F34*$B$21)*M34 -> 4366.7073 | O34: =(O33+F34*$B$21)*(1+M34) -> 19584.73 | P34: =I34+L34+O34 -> 62219.887 | Q34: =H34+K34+N34 -> 4591.449 | R34: =IF(Q34>0,Q34*$B$11,0) -> 1285.6057 | S34: =26*$B$13 -> 27997.84 | T34: =P34-R34+S34 -> 88932.121
A35: 38 | B35: =_xlfn.NORM.INV(RAND(),$B$5,$B$6) -> 0.039078973 | C35: =C34*(1+B35) -> 88142.153 | D35: =IF(C35<84000,3%*(1-30%),3%*(1-33%)) -> 0.0201 | E35: =$B$14 -> 521.43 | F35: =C35*($B$9+D35)+E35 -> 7581.6165 | G35: =_xlfn.NORM.INV(RAND(),$C$19,$D$19) -> 0.078410443 | H35: =(I34+F35*$B$19)*G35 -> 2225.5485 | I35: =(I34+(F35*$B$19))*(1+G35) -> 30608.865 | J35: =_xlfn.NORM.INV(RAND(),$C$20,$D$20) -> -0.0019885745 | K35: =(L34+F35*$B$20)*J35 -> -38.894471 | L35: =(L34+F35*$B$20)*(1+J35) -> 19520.077 | M35: =_xlfn.NORM.INV(RAND(),$C$21,$D$21) -> 0.29082835 | N35: =(O34+F35*$B$21)*M35 -> 6357.2795 | O35: =(O34+F35*$B$21)*(1+M35) -> 28216.495 | P35: =I35+L35+O35 -> 78345.437 | Q35: =H35+K35+N35 -> 8543.9335 | R35: =IF(Q35>0,Q35*$B$11,0) -> 2392.3014 | S35: =26*$B$13 -> 27997.84 | T35: =P35-R35+S35 -> 103950.98
A36: 39 | B36: =_xlfn.NORM.INV(RAND(),$B$5,$B$6) -> 0.031974948 | C36: =C35*(1+B36) -> 90960.494 | D36: =IF(C36<84000,3%*(1-30%),3%*(1-33%)) -> 0.0201 | E36: =$B$14 -> 521.43 | F36: =C36*($B$9+D36)+E36 -> 7807.3655 | G36: =_xlfn.NORM.INV(RAND(),$C$19,$D$19) -> 0.12969062 | H36: =(I35+F36*$B$19)*G36 -> 4374.6995 | I36: =(I35+(F36*$B$19))*(1+G36) -> 38106.511 | J36: =_xlfn.NORM.INV(RAND(),$C$20,$D$20) -> 0.10182776 | K36: =(L35+F36*$B$20)*J36 -> 2226.1877 | L36: =(L35+F36*$B$20)*(1+J36) -> 24088.474 | M36: =_xlfn.NORM.INV(RAND(),$C$21,$D$21) -> 0.39827204 | N36: =(O35+F36*$B$21)*M36 -> 12170.678 | O36: =(O35+F36*$B$21)*(1+M36) -> 42729.382 | P36: =I36+L36+O36 -> 104924.37 | Q36: =H36+K36+N36 -> 18771.565 | R36: =IF(Q36>0,Q36*$B$11,0) -> 5256.0381 | S36: =26*$B$13 -> 27997.84 | T36: =P36-R36+S36 -> 127666.17
A37: 40 | B37: =_xlfn.NORM.INV(RAND(),$B$5,$B$6) -> 0.028381014 | C37: =C36*(1+B37) -> 93542.045 | D37: =IF(C37<84000,3%*(1-30%),3%*(1-33%)) -> 0.0201 | E37: =$B$14 -> 521.43 | F37: =C37*($B$9+D37)+E37 -> 8014.1478 | G37: =_xlfn.NORM.INV(RAND(),$C$19,$D$19) -> 0.042994834 | H37: =(I36+F37*$B$19)*G37 -> 1776.2099 | I37: =(I36+(F37*$B$19))*(1+G37) -> 43088.38 | J37: =_xlfn.NORM.INV(RAND(),$C$20,$D$20) -> 0.15055057 | K37: =(L36+F37*$B$20)*J37 -> 3988.4939 | L37: =(L36+F37*$B$20)*(1+J37) -> 30481.213 | M37: =_xlfn.NORM.INV(RAND(),$C$21,$D$21) -> 0.10786315 | N37: =(O36+F37*$B$21)*M37 -> 4868.2551 | O37: =(O36+F37*$B$21)*(1+M37) -> 50001.881 | P37: =I37+L37+O37 -> 123571.47 | Q37: =H37+K37+N37 -> 10632.959 | R37: =IF(Q37>0,Q37*$B$11,0) -> 2977.2285 | S37: =26*$B$13 -> 27997.84 | T37: =P37-R37+S37 -> 148592.09
A38: 41 | B38: =_xlfn.NORM.INV(RAND(),$B$5,$B$6) -> 0.035312768 | C38: =C37*(1+B38) -> 96845.273 | D38: =IF(C38<84000,3%*(1-30%),3%*(1-33%)) -> 0.0201 | E38: =$B$14 -> 521.43 | F38: =C38*($B$9+D38)+E38 -> 8278.7364 | G38: =_xlfn.NORM.INV(RAND(),$C$19,$D$19) -> 0.029480941 | H38: =(I37+F38*$B$19)*G38 -> 1367.912 | I38: =(I37+(F38*$B$19))*(1+G38) -> 47767.787 | J38: =_xlfn.NORM.INV(RAND(),$C$20,$D$20) -> 0.0070541237 | K38: =(L37+F38*$B$20)*J38 -> 232.53801 | L38: =(L37+F38*$B$20)*(1+J38) -> 33197.372 | M38: =_xlfn.NORM.INV(RAND(),$C$21,$D$21) -> 0.13268978 | N38: =(O37+F38*$B$21)*M38 -> 6964.2897 | O38: =(O37+F38*$B$21)*(1+M38) -> 59449.792 | P38: =I38+L38+O38 -> 140414.95 | Q38: =H38+K38+N38 -> 8564.7397 | R38: =IF(Q38>0,Q38*$B$11,0) -> 2398.1271 | S38: =26*$B$13 -> 27997.84 | T38: =P38-R38+S38 -> 166014.66
A39: 42 | B39: =_xlfn.NORM.INV(RAND(),$B$5,$B$6) -> 0.05593305 | C39: =C38*(1+B39) -> 102262.12 | D39: =IF(C39<84000,3%*(1-30%),3%*(1-33%)) -> 0.0201 | E39: =$B$14 -> 521.43 | F39: =C39*($B$9+D39)+E39 -> 8712.6262 | G39: =_xlfn.NORM.INV(RAND(),$C$19,$D$19) -> 0.025224944 | H39: =(I38+F39*$B$19)*G39 -> 1292.8499 | I39: =(I38+(F39*$B$19))*(1+G39) -> 52545.687 | J39: =_xlfn.NORM.INV(RAND(),$C$20,$D$20) -> 0.10862586 | K39: =(L38+F39*$B$20)*J39 -> 3890.0179 | L39: =(L38+F39*$B$20)*(1+J39) -> 39701.177 | M39: =_xlfn.NORM.INV(RAND(),$C$21,$D$21) -> 0.0086125944 | N39: =(O38+F39*$B$21)*M39 -> 534.52844 | O39: =(O38+F39*$B$21)*(1+M39) -> 62598.108 | P39: =I39+L39+O39 -> 154844.97 | Q39: =H39+K39+N39 -> 5717.3963 | R39: =IF(Q39>0,Q39*$B$11,0) -> 1600.871 | S39: =26*$B$13 -> 27997.84 | T39: =P39-R39+S39 -> 181241.94
A40: 43 | B40: =_xlfn.NORM.INV(RAND(),$B$5,$B$6) -> 0.029584197 | C40: =C39*(1+B40) -> 105287.47 | D40: =IF(C40<84000,3%*(1-30%),3%*(1-33%)) -> 0.0201 | E40: =$B$14 -> 521.43 | F40: =C40*($B$9+D40)+E40 -> 8954.9562 | G40: =_xlfn.NORM.INV(RAND(),$C$19,$D$19) -> -0.014573622 | H40: =(I39+F40*$B$19)*G40 -> -817.98343 | I40: =(I39+(F40*$B$19))*(1+G40) -> 55309.686 | J40: =_xlfn.NORM.INV(RAND(),$C$20,$D$20) -> -0.045071695 | K40: =(L39+F40*$B$20)*J40 -> -1910.4839 | L40: =(L39+F40*$B$20)*(1+J40) -> 40477.18 | M40: =_xlfn.NORM.INV(RAND(),$C$21,$D$21) -> 0.20335842 | N40: =(O39+F40*$B$21)*M40 -> 13276.172 | O40: =(O39+F40*$B$21)*(1+M40) -> 78560.767 | P40: =I40+L40+O40 -> 174347.63 | Q40: =H40+K40+N40 -> 10547.704 | R40: =IF(Q40>0,Q40*$B$11,0) -> 2953.3573 | S40: =26*$B$13 -> 27997.84 | T40: =P40-R40+S40 -> 199392.12
A41: 44 | B41: =_xlfn.NORM.INV(RAND(),$B$5,$B$6) -> 0.029380655 | C41: =C40*(1+B41) -> 108380.88 | D41: =IF(C41<84000,3%*(1-30%),3%*(1-33%)) -> 0.0201 | E41: =$B$14 -> 521.43 | F41: =C41*($B$9+D41)+E41 -> 9202.7387 | G41: =_xlfn.NORM.INV(RAND(),$C$19,$D$19) -> -0.00081464032 | H41: =(I40+F41*$B$19)*G41 -> -48.056269 | I41: =(I40+(F41*$B$19))*(1+G41) -> 58942.725 | J41: =_xlfn.NORM.INV(RAND(),$C$20,$D$20) -> 0.052595577 | K41: =(L40+F41*$B$20)*J41 -> 2274.1277 | L41: =(L40+F41*$B$20)*(1+J41) -> 45512.13 | M41: =_xlfn.NORM.INV(RAND(),$C$21,$D$21) -> 0.39494411 | N41: =(O40+F41*$B$21)*M41 -> 32117.482 | O41: =(O40+F41*$B$21)*(1+M41) -> 113439.07 | P41: =I41+L41+O41 -> 217893.93 | Q41: =H41+K41+N41 -> 34343.553 | R41: =IF(Q41>0,Q41*$B$11,0) -> 9616.195 | S41: =26*$B$13 -> 27997.84 | T41: =P41-R41+S41 -> 236275.57
... A62: 65 | B62: =_xlfn.NORM.INV(RAND(),$B$5,$B$6) -> 0.032311371 | C62: =C61*(1+B62) -> 225364.94 | D62: =IF(C62<84000,3%*(1-30%),3%*(1-33%)) -> 0.0201 | E62: =$B$14 -> 521.43 | F62: =C62*($B$9+D62)+E62 -> 18573.162 | G62: =_xlfn.NORM.INV(RAND(),$C$19,$D$19) -> 0.05806593 | H62: =(I61+F62*$B$19)*G62 -> 13998.123 | I62: =(I61+(F62*$B$19))*(1+G62) -> 255071.04 | J62: =_xlfn.NORM.INV(RAND(),$C$20,$D$20) -> -0.081622209 | K62: =(L61+F62*$B$20)*J62 -> -14101.576 | L62: =(L61+F62*$B$20)*(1+J62) -> 158664.84 | M62: =_xlfn.NORM.INV(RAND(),$C$21,$D$21) -> 0.18945258 | N62: =(O61+F62*$B$21)*M62 -> 475140.52 | O62: =(O61+F62*$B$21)*(1+M62) -> 2983106 | P62: =I62+L62+O62 -> 3396841.8 | Q62: =H62+K62+N62 -> 475037.06 | R62: =IF(Q62>0,Q62*$B$11,0) -> 133010.38 | S62: =26*$B$13 -> 27997.84 | T62: =P62-R62+S62 -> 3291829.3
B64: Sum | C64: =SUM(C27:C62) -> 4724815.8 | E64: =SUM(E27:E62) -> 18771.48 | F64: =SUM(F27:F62) -> 397698.79 | P64: =P62 -> 3396841.8 | R64: =SUM(R27:R62) -> 895204.39 | T64: =P64-R64+'Inflation rate & expenditure1'!P58 -> 4631137
A67: trial | B67: Total balance | C67: Total expenditure | D67: Status | E67: Difference
A68: {=_xlfn.SEQUENCE(5000)} -> 1 | B68: =T64 -> 4631137 | C68: ='Inflation rate & expenditure1'!W66 -> 4253088.1 | D68: =IF(B68>=C68,"met","unmet") -> met | E68: =B68-C68 -> 378048.88
A69: 2 | B69: 3211507.7 | C69: 4253057.5 | D69: unmet | E69: -1041549.8
A70: 3 | B70: 4364135.4 | C70: 4253289 | D70: met | E70: 110846.42
A71: 4 | B71: 3638210.4 | C71: 4253483.5 | D71: unmet | E71: -615273.1
A72: 5 | B72: 4669669.8 | C72: 4253666.8 | D72: met | E72: 416002.91
A73: 6 | B73: 4006451.9 | C73: 4252978.4 | D73: unmet | E73: -246526.51
A74: 7 | B74: 3263998.9 | C74: 4253350.8 | D74: unmet | E74: -989351.9
A75: 8 | B75: 4181223.6 | C75: 4253133.4 | D75: unmet | E75: -71909.784
A76: 9 | B76: 3237644 | C76: 4253178.2 | D76: unmet | E76: -1015534.2
A77: 10 | B77: 3533650.4 | C77: 4253534 | D77: unmet | E77: -719883.65
A78: 11 | B78: 4819640.9 | C78: 4253230 | D78: met | E78: 566410.86
A79: 12 | B79: 4047263.5 | C79: 4253547.3 | D79: unmet | E79: -206283.79
A80: 13 | B80: 4356150.4 | C80: 4253304.9 | D80: met | E80: 102845.58
... A98: 31 | B98: 4151872.9 | C98: 4253330.3 | D98: unmet | E98: -101457.41
A99: 32 | B99: 2920099.6 | C99: 4253259 | D99: unmet | E99: -1333159.3 | H99: count | I99: =COUNT(B68:B5067) -> 5000
A100: 33 | B100: 3684977.5 | C100: 4252918.3 | D100: unmet | E100: -567940.78 | H100: max balance | I100: =MAX(B68:B5067) -> 10656678
A101: 34 | B101: 4172147.1 | C101: 4253345.9 | D101: unmet | E101: -81198.805 | H101: min balance | I101: =MIN(B68:B5067) -> 2518216.1
A102: 35 | B102: 4852017 | C102: 4253537.6 | D102: met | E102: 598479.4 | H102: mean balance | I102: =AVERAGE(B68:B5067) -> 3620505.5
A103: 36 | B103: 3523407.3 | C103: 4253722.3 | D103: unmet | E103: -730315.01 | H103: SD | I103: =_xlfn.STDEV.S(B68:B5067) -> 726750.6
A104: 37 | B104: 3590611.2 | C104: 4253462 | D104: unmet | E104: -662850.82
A105: 38 | B105: 3527851.3 | C105: 4253421.1 | D105: unmet | E105: -725569.86 | H105: 95%C.I | I105: =I103-_xlfn.CONFIDENCE.T(0.05,I103,I99) -> 706601.59
A106: 39 | B106: 3057292.4 | C106: 4252884.6 | D106: unmet | E106: -1195592.2 | I106: =I103+_xlfn.CONFIDENCE.T(0.05,I103,I99) -> 746899.61
A107: 40 | B107: 3832669.4 | C107: 4253841.5 | D107: unmet | E107: -421172.07 | H107: 95%P.I | I107: =_xlfn.PERCENTILE.EXC(B68:B5067,0.025) -> 2815536.9
A108: 41 | B108: 3315365.8 | C108: 4252927.9 | D108: unmet | E108: -937562.03 | I108: =_xlfn.PERCENTILE.EXC(B68:B5067,0.975) -> 5533118.6
A109: 42 | B109: 5307963.9 | C109: 4253300.3 | D109: met | E109: 1054663.6 | H109: Met Number | I109: =COUNTIF(D68:D5067,"=met") -> 640
A110: 43 | B110: 3191725.2 | C110: 4253396.8 | D110: unmet | E110: -1061671.7 | H110: P(met) | I110: =I109/I99 -> 0.128
A111: 44 | B111: 5465303.5 | C111: 4253484.8 | D111: met | E111: 1211818.7 | H111: SE | I111: =SQRT(((1-I110)*I110)/I99) -> 0.0047247434
A112: 45 | B112: 3468273.4 | C112: 4252951.6 | D112: unmet | E112: -784678.18 | H112: 95%C.I | I112: =I110+(_xlfn.NORM.S.INV(0.975))*I111 -> 0.13726033
A113: 46 | B113: 3153104.1 | C113: 4253151.4 | D113: unmet | E113: -1100047.3 | I113: =I110-(_xlfn.NORM.S.INV(0.975))*I111 -> 0.11873967
A114: 47 | B114: 3402295.1 | C114: 4253403.9 | D114: unmet | E114: -851108.82
A115: 48 | B115: 3346139.3 | C115: 4253005.5 | D115: unmet | E115: -906866.23
A116: 49 | B116: 3582557.5 | C116: 4253684.9 | D116: unmet | E116: -671127.43 | H116: Fixed value
A117: 50 | B117: 3346128.5 | C117: 4253213.8 | D117: unmet | E117: -907085.32 | H117: count | I117: 5000
A118: 51 | B118: 4186543.9 | C118: 4253614.9 | D118: unmet | E118: -67070.957 | H118: max balance | I118: 4197368.1
A119: 52 | B119: 4522641.4 | C119: 4253403.8 | D119: met | E119: 269237.66 | H119: min balance | I119: 245823.78
A120: 53 | B120: 3815499.4 | C120: 4253648.9 | D120: unmet | E120: -438149.42 | H120: mean balance | I120: 621904.3
A121: 54 | B121: 3663277.3 | C121: 4253477.1 | D121: unmet | E121: -590199.81 | H121: SD | I121: 303302.74
A122: 55 | B122: 3183664.1 | C122: 4253718 | D122: unmet | E122: -1070053.9
A123: 56 | B123: 2935435 | C123: 4252895.3 | D123: unmet | E123: -1317460.2 | H123: 95%C.I | I123: 294893.73 | K123: 2504918.2
A124: 57 | B124: 3152187.4 | C124: 4254410.4 | D124: unmet | E124: -1102223 | I124: 311711.74 | K124: 450943.29
A125: 58 | B125: 3137247.2 | C125: 4253097.9 | D125: unmet | E125: -1115850.7 | H125: 95%P.I | I125: 314111.01
A126: 59 | B126: 3594458.4 | C126: 4253152.7 | D126: unmet | E126: -658694.3 | I126: 1431100.5
A127: 60 | B127: 3081825.3 | C127: 4253069.8 | D127: unmet | E127: -1171244.5 | H127: Unmet Number | I127: 4763
A128: 61 | B128: 3380528.3 | C128: 4254031.3 | D128: unmet | E128: -873502.95 | H128: P(unmet) | I128: 0.9526
A129: 62 | B129: 3588936.5 | C129: 4253557.6 | D129: unmet | E129: -664621.18 | H129: SE | I129: 0.0030051037
A130: 63 | B130: 3667313.6 | C130: 4253167.3 | D130: unmet | E130: -585853.7 | H130: 95%C.I | I130: 0.95848989
A131: 64 | B131: 3116333.9 | C131: 4253240.1 | D131: unmet | E131: -1136906.2 | I131: 0.94671011
A132: 65 | B132: 4082350.8 | C132: 4253261.5 | D132: unmet | E132: -170910.79
A133: 66 | B133: 4169458.2 | C133: 4253161.3 | D133: unmet | E133: -83703.11
A134: 67 | B134: 3711303.6 | C134: 4253390.3 | D134: unmet | E134: -542086.78
A135: 68 | B135: 2694199.9 | C135: 4253652.3 | D135: unmet | E135: -1559452.4
A136: 69 | B136: 2800800.2 | C136: 4253415.5 | D136: unmet | E136: -1452615.4
A137: 70 | B137: 3140379.7 | C137: 4253175.6 | D137: unmet | E137: -1112795.9
A138: 71 | B138: 2951468.4 | C138: 4253396.3 | D138: unmet | E138: -1301927.9
A139: 72 | B139: 4983548.8 | C139: 4253463 | D139: met | E139: 730085.81
A140: 73 | B140: 3871054 | C140: 4253479.6 | D140: unmet | E140: -382425.55
A141: 74 | B141: 3576889 | C141: 4252923.7 | D141: unmet | E141: -676034.7
...

Sheet Bank saving
A1: age | B1: beginning Balance | C1: annual deposit | D1: principal for interest calculation | E1: annual interest rate | F1: annual interest earned | G1: ending balance
A2: 35 | B2: 19803 | C2: =523*12 -> 6276 | D2: =B2+C2 -> 26079 | E2: 0.0335 | F2: =D2*E2 -> 873.6465 | G2: =F2+D2 -> 26952.646 | H2: <-$19803 is added because it is the average amount that NZ have in their bank at the age 26-30(reference below)
A3: 36 | B3: =G2 -> 26952.646 | C3: =523*12 -> 6276 | D3: =B3+C3 -> 33228.647 | E3: 0.0335 | F3: =D3*E3 -> 1113.1597 | G3: =F3+D3 -> 34341.806 | H3: https://www.rnz.co.nz/news/business/545015/what-average-kiwisavers-balances-are-at-your-age
A4: 37 | B4: =G3 -> 34341.806 | C4: =523*12 -> 6276 | D4: =B4+C4 -> 40617.806 | E4: 0.0335 | F4: =D4*E4 -> 1360.6965 | G4: =F4+D4 -> 41978.503
A5: 38 | B5: =G4 -> 41978.503 | C5: =523*12 -> 6276 | D5: =B5+C5 -> 48254.503 | E5: 0.0335 | F5: =D5*E5 -> 1616.5258 | G5: =F5+D5 -> 49871.029
A6: 39 | B6: =G5 -> 49871.029 | C6: =523*12 -> 6276 | D6: =B6+C6 -> 56147.029 | E6: 0.0335 | F6: =D6*E6 -> 1880.9255 | G6: =F6+D6 -> 58027.954
A7: 40 | B7: =G6 -> 58027.954 | C7: =523*12 -> 6276 | D7: =B7+C7 -> 64303.954 | E7: 0.0335 | F7: =D7*E7 -> 2154.1825 | G7: =F7+D7 -> 66458.136
A8: 41 | B8: =G7 -> 66458.136 | C8: =523*12 -> 6276 | D8: =B8+C8 -> 72734.136 | E8: 0.0335 | F8: =D8*E8 -> 2436.5936 | G8: =F8+D8 -> 75170.73
A9: 42 | B9: =G8 -> 75170.73 | C9: =523*12 -> 6276 | D9: =B9+C9 -> 81446.73 | E9: 0.0335 | F9: =D9*E9 -> 2728.4655 | G9: =F9+D9 -> 84175.195
A10: 43 | B10: =G9 -> 84175.195 | C10: =523*12 -> 6276 | D10: =B10+C10 -> 90451.195 | E10: 0.0335 | F10: =D10*E10 -> 3030.115 | G10: =F10+D10 -> 93481.31
A11: 44 | B11: =G10 -> 93481.31 | C11: =523*12 -> 6276 | D11: =B11+C11 -> 99757.31 | E11: 0.0335 | F11: =D11*E11 -> 3341.8699 | G11: =F11+D11 -> 103099.18
A12: 45 | B12: =G11 -> 103099.18 | C12: =523*12 -> 6276 | D12: =B12+C12 -> 109375.18 | E12: 0.0335 | F12: =D12*E12 -> 3664.0685 | G12: =F12+D12 -> 113039.25
A13: 46 | B13: =G12 -> 113039.25 | C13: =523*12 -> 6276 | D13: =B13+C13 -> 119315.25 | E13: 0.0335 | F13: =D13*E13 -> 3997.0608 | G13: =F13+D13 -> 123312.31
A14: 47 | B14: =G13 -> 123312.31 | C14: =523*12 -> 6276 | D14: =B14+C14 -> 129588.31 | E14: 0.0335 | F14: =D14*E14 -> 4341.2084 | G14: =F14+D14 -> 133929.52
A15: 48 | B15: =G14 -> 133929.52 | C15: =523*12 -> 6276 | D15: =B15+C15 -> 140205.52 | E15: 0.0335 | F15: =D15*E15 -> 4696.8849 | G15: =F15+D15 -> 144902.4
... A32: 65 | B32: =G31 -> 379908.14 | C32: =523*12 -> 6276 | D32: =B32+C32 -> 386184.14 | E32: 0.0335 | F32: =D32*E32 -> 12937.169 | G32: =F32+D32 -> 399121.31
E33: ^ this rate is from Kiwi Bank the 3.35% per annum rate savings (reference)
E34: https://www.kiwibank.co.nz/personal-banking/investments/savings-accounts/notice-saver/
